Workbook

Sheet PLANO DE SAÚDE
B2: TIPO DE DESP: | F2: =SUM(F4:F211) -> 291294.1 | M2: TOTAL | O2: CONTA | P2: 31201005 | Q2: 31201003
A3: EST | B3: NOME | C3: CCUSTO | D3: DATA | E3: Nº DOC | F3: MENSAL | G3: EXAME | H3: DESCON | I3: REPRES | J3: INSCRI | M3: =SUM(M4:M211) -> 291294.1
A4: 101 | B4: UNIMED ITUVERAVA | C4: 13021 | E4: UNIMED ITUVERAVA | F4: 546.96 | K4: ="|"&"PAGTO DOC - "&E4&"|"&"PLANO DE SAUDE - "&B4&"|"&"C CUSTO - "&LEFT(C4,5)&"|"&"TOTAL: "&F4&"|" -> |PAGTO DOC - UNIMED ITUVERAVA|PLANO DE SAUDE - UNIMED ITUVERAVA|C CUSTO - 13021|TOTAL: 546,96| | M4: =SUM(F4:L4) -> 546.96 | N4: ="|"&"PAGTO DOC - "&F4&"|"&"DESP - "&B4&"|"&"CENTRO CUSTO - "&C4&"|"&I4&"|"&G4&"|"&#REF!&"|"&J4&"|"&H4&"|"&K4&"|"&L4&"|" -> #REF! | O4: =IF(M4=0,0,IF(E4="SEGURO DE VIDA EM GRUPO","31201003","31201005")) -> 31201005
A5: 101 | B5: UNIMED ITUVERAVA | C5: 14051 | E5: UNIMED ITUVERAVA | F5: 2161.26 | K5: ="|"&"PAGTO DOC - "&E5&"|"&"PLANO DE SAUDE - "&B5&"|"&"C CUSTO - "&LEFT(C5,5)&"|"&"TOTAL: "&F5&"|" -> |PAGTO DOC - UNIMED ITUVERAVA|PLANO DE SAUDE - UNIMED ITUVERAVA|C CUSTO - 14051|TOTAL: 2161,26| | M5: =SUM(F5:L5) -> 2161.26 | N5: ="|"&"PAGTO DOC - "&F5&"|"&"DESP - "&B5&"|"&"CENTRO CUSTO - "&C5&"|"&I5&"|"&G5&"|"&#REF!&"|"&J5&"|"&H5&"|"&K5&"|"&L5&"|" -> #REF! | O5: =IF(M5=0,0,IF(E5="SEGURO DE VIDA EM GRUPO","31201003","31201005")) -> 31201005
A6: 101 | B6: UNIMED ITUVERAVA | C6: 14058 | E6: UNIMED ITUVERAVA | F6: 2014.32 | K6: ="|"&"PAGTO DOC - "&E6&"|"&"PLANO DE SAUDE - "&B6&"|"&"C CUSTO - "&LEFT(C6,5)&"|"&"TOTAL: "&F6&"|" -> |PAGTO DOC - UNIMED ITUVERAVA|PLANO DE SAUDE - UNIMED ITUVERAVA|C CUSTO - 14058|TOTAL: 2014,32| | M6: =SUM(F6:L6) -> 2014.32 | N6: ="|"&"PAGTO DOC - "&F6&"|"&"DESP - "&B6&"|"&"CENTRO CUSTO - "&C6&"|"&I6&"|"&G6&"|"&#REF!&"|"&J6&"|"&H6&"|"&K6&"|"&L6&"|" -> #REF! | O6: =IF(M6=0,0,IF(E6="SEGURO DE VIDA EM GRUPO","31201003","31201005")) -> 31201005
A7: 101 | B7: UNIMED ITUVERAVA | C7: 31060 | E7: UNIMED ITUVERAVA | F7: 546.96 | K7: ="|"&"PAGTO DOC - "&E7&"|"&"PLANO DE SAUDE - "&B7&"|"&"C CUSTO - "&LEFT(C7,5)&"|"&"TOTAL: "&F7&"|" -> |PAGTO DOC - UNIMED ITUVERAVA|PLANO DE SAUDE - UNIMED ITUVERAVA|C CUSTO - 31060|TOTAL: 546,96| | M7: =SUM(F7:L7) -> 546.96 | N7: ="|"&"PAGTO DOC - "&F7&"|"&"DESP - "&B7&"|"&"CENTRO CUSTO - "&C7&"|"&I7&"|"&G7&"|"&#REF!&"|"&J7&"|"&H7&"|"&K7&"|"&L7&"|" -> #REF! | O7: =IF(M7=0,0,IF(E7="SEGURO DE VIDA EM GRUPO","31201003","31201005")) -> 31201005
A8: 101 | B8: UNIMED ITUVERAVA | C8: 31070 | E8: UNIMED ITUVERAVA | F8: 546.96 | K8: ="|"&"PAGTO DOC - "&E8&"|"&"PLANO DE SAUDE - "&B8&"|"&"C CUSTO - "&LEFT(C8,5)&"|"&"TOTAL: "&F8&"|" -> |PAGTO DOC - UNIMED ITUVERAVA|PLANO DE SAUDE - UNIMED ITUVERAVA|C CUSTO - 31070|TOTAL: 546,96| | M8: =SUM(F8:L8) -> 546.96 | N8: ="|"&"PAGTO DOC - "&F8&"|"&"DESP - "&B8&"|"&"CENTRO CUSTO - "&C8&"|"&I8&"|"&G8&"|"&#REF!&"|"&J8&"|"&H8&"|"&K8&"|"&L8&"|" -> #REF! | O8: =IF(M8=0,0,IF(E8="SEGURO DE VIDA EM GRUPO","31201003","31201005")) -> 31201005
A9: 101 | B9: UNIMED ITUVERAVA | C9: 31114 | E9: UNIMED ITUVERAVA | F9: 2417.14 | K9: ="|"&"PAGTO DOC - "&E9&"|"&"PLANO DE SAUDE - "&B9&"|"&"C CUSTO - "&LEFT(C9,5)&"|"&"TOTAL: "&F9&"|" -> |PAGTO DOC - UNIMED ITUVERAVA|PLANO DE SAUDE - UNIMED ITUVERAVA|C CUSTO - 31114|TOTAL: 2417,14| | M9: =SUM(F9:L9) -> 2417.14 | N9: ="|"&"PAGTO DOC - "&F9&"|"&"DESP - "&B9&"|"&"CENTRO CUSTO - "&C9&"|"&I9&"|"&G9&"|"&#REF!&"|"&J9&"|"&H9&"|"&K9&"|"&L9&"|" -> #REF! | O9: =IF(M9=0,0,IF(E9="SEGURO DE VIDA EM GRUPO","31201003","31201005")) -> 31201005
A10: 101 | B10: UNIMED ITUVERAVA | C10: 11012 | E10: UNIMED ITUVERAVA | F10: 1093.92 | K10: ="|"&"PAGTO DOC - "&E10&"|"&"PLANO DE SAUDE - "&B10&"|"&"C CUSTO - "&LEFT(C10,5)&"|"&"TOTAL: "&F10&"|" -> |PAGTO DOC - UNIMED ITUVERAVA|PLANO DE SAUDE - UNIMED ITUVERAVA|C CUSTO - 11012|TOTAL: 1093,92| | M10: =SUM(F10:L10) -> 1093.92 | N10: ="|"&"PAGTO DOC - "&F10&"|"&"DESP - "&B10&"|"&"CENTRO CUSTO - "&C10&"|"&I10&"|"&G10&"|"&#REF!&"|"&J10&"|"&H10&"|"&K10&"|"&L10&"|" -> #REF! | O10: =IF(M10=0,0,IF(E10="SEGURO DE VIDA EM GRUPO","31201003","31201005")) -> 31201005
A11: 101 | B11: UNIMED ITUVERAVA | C11: 13011 | E11: UNIMED ITUVERAVA | F11: 1323.22 | K11: ="|"&"PAGTO DOC - "&E11&"|"&"PLANO DE SAUDE - "&B11&"|"&"C CUSTO - "&LEFT(C11,5)&"|"&"TOTAL: "&F11&"|" -> |PAGTO DOC - UNIMED ITUVERAVA|PLANO DE SAUDE - UNIMED ITUVERAVA|C CUSTO - 13011|TOTAL: 1323,22| | M11: =SUM(F11:L11) -> 1323.22 | N11: ="|"&"PAGTO DOC - "&F11&"|"&"DESP - "&B11&"|"&"CENTRO CUSTO - "&C11&"|"&I11&"|"&G11&"|"&#REF!&"|"&J11&"|"&H11&"|"&K11&"|"&L11&"|" -> #REF! | O11: =IF(M11=0,0,IF(E11="SEGURO DE VIDA EM GRUPO","31201003","31201005")) -> 31201005
A12: 101 | B12: UNIMED ITUVERAVA | C12: 13012 | E12: UNIMED ITUVERAVA | F12: 1005.56 | K12: ="|"&"PAGTO DOC - "&E12&"|"&"PLANO DE SAUDE - "&B12&"|"&"C CUSTO - "&LEFT(C12,5)&"|"&"TOTAL: "&F12&"|" -> |PAGTO DOC - UNIMED ITUVERAVA|PLANO DE SAUDE - UNIMED ITUVERAVA|C CUSTO - 13012|TOTAL: 1005,56| | M12: =SUM(F12:L12) -> 1005.56 | N12: ="|"&"PAGTO DOC - "&F12&"|"&"DESP - "&B12&"|"&"CENTRO CUSTO - "&C12&"|"&I12&"|"&G12&"|"&#REF!&"|"&J12&"|"&H12&"|"&K12&"|"&L12&"|" -> #REF! | O12: =IF(M12=0,0,IF(E12="SEGURO DE VIDA EM GRUPO","31201003","31201005")) -> 31201005
A13: 101 | B13: UNIMED ITUVERAVA | C13: 13013 | E13: UNIMED ITUVERAVA | F13: 8067.44 | K13: ="|"&"PAGTO DOC - "&E13&"|"&"PLANO DE SAUDE - "&B13&"|"&"C CUSTO - "&LEFT(C13,5)&"|"&"TOTAL: "&F13&"|" -> |PAGTO DOC - UNIMED ITUVERAVA|PLANO DE SAUDE - UNIMED ITUVERAVA|C CUSTO - 13013|TOTAL: 8067,44| | M13: =SUM(F13:L13) -> 8067.44 | N13: ="|"&"PAGTO DOC - "&F13&"|"&"DESP - "&B13&"|"&"CENTRO CUSTO - "&C13&"|"&I13&"|"&G13&"|"&#REF!&"|"&J13&"|"&H13&"|"&K13&"|"&L13&"|" -> #REF! | O13: =IF(M13=0,0,IF(E13="SEGURO DE VIDA EM GRUPO","31201003","31201005")) -> 31201005
A14: 101 | B14: UNIMED ITUVERAVA | C14: 13014 | E14: UNIMED ITUVERAVA | F14: 2187.84 | K14: ="|"&"PAGTO DOC - "&E14&"|"&"PLANO DE SAUDE - "&B14&"|"&"C CUSTO - "&LEFT(C14,5)&"|"&"TOTAL: "&F14&"|" -> |PAGTO DOC - UNIMED ITUVERAVA|PLANO DE SAUDE - UNIMED ITUVERAVA|C CUSTO - 13014|TOTAL: 2187,84| | M14: =SUM(F14:L14) -> 2187.84 | N14: ="|"&"PAGTO DOC - "&F14&"|"&"DESP - "&B14&"|"&"CENTRO CUSTO - "&C14&"|"&I14&"|"&G14&"|"&#REF!&"|"&J14&"|"&H14&"|"&K14&"|"&L14&"|" -> #REF! | O14: =IF(M14=0,0,IF(E14="SEGURO DE VIDA EM GRUPO","31201003","31201005")) -> 31201005
A15: 101 | B15: UNIMED ITUVERAVA | C15: 13016 | E15: UNIMED ITUVERAVA | F15: 1464.16 | K15: ="|"&"PAGTO DOC - "&E15&"|"&"PLANO DE SAUDE - "&B15&"|"&"C CUSTO - "&LEFT(C15,5)&"|"&"TOTAL: "&F15&"|" -> |PAGTO DOC - UNIMED ITUVERAVA|PLANO DE SAUDE - UNIMED ITUVERAVA|C CUSTO - 13016|TOTAL: 1464,16| | M15: =SUM(F15:L15) -> 1464.16 | N15: ="|"&"PAGTO DOC - "&F15&"|"&"DESP - "&B15&"|"&"CENTRO CUSTO - "&C15&"|"&I15&"|"&G15&"|"&#REF!&"|"&J15&"|"&H15&"|"&K15&"|"&L15&"|" -> #REF! | O15: =IF(M15=0,0,IF(E15="SEGURO DE VIDA EM GRUPO","31201003","31201005")) -> 31201005
A16: 101 | B16: UNIMED ITUVERAVA | C16: 13017 | E16: UNIMED ITUVERAVA | F16: 1640.88 | K16: ="|"&"PAGTO DOC - "&E16&"|"&"PLANO DE SAUDE - "&B16&"|"&"C CUSTO - "&LEFT(C16,5)&"|"&"TOTAL: "&F16&"|" -> |PAGTO DOC - UNIMED ITUVERAVA|PLANO DE SAUDE - UNIMED ITUVERAVA|C CUSTO - 13017|TOTAL: 1640,88| | M16: =SUM(F16:L16) -> 1640.88 | N16: ="|"&"PAGTO DOC - "&F16&"|"&"DESP - "&B16&"|"&"CENTRO CUSTO - "&C16&"|"&I16&"|"&G16&"|"&#REF!&"|"&J16&"|"&H16&"|"&K16&"|"&L16&"|" -> #REF! | O16: =IF(M16=0,0,IF(E16="SEGURO DE VIDA EM GRUPO","31201003","31201005")) -> 31201005
A17: 101 | B17: UNIMED ITUVERAVA | C17: 13018 | E17: UNIMED ITUVERAVA | F17: 1005.56 | K17: ="|"&"PAGTO DOC - "&E17&"|"&"PLANO DE SAUDE - "&B17&"|"&"C CUSTO - "&LEFT(C17,5)&"|"&"TOTAL: "&F17&"|" -> |PAGTO DOC - UNIMED ITUVERAVA|PLANO DE SAUDE - UNIMED ITUVERAVA|C CUSTO - 13018|TOTAL: 1005,56| | M17: =SUM(F17:L17) -> 1005.56 | N17: ="|"&"PAGTO DOC - "&F17&"|"&"DESP - "&B17&"|"&"CENTRO CUSTO - "&C17&"|"&I17&"|"&G17&"|"&#REF!&"|"&J17&"|"&H17&"|"&K17&"|"&L17&"|" -> #REF! | O17: =IF(M17=0,0,IF(E17="SEGURO DE VIDA EM GRUPO","31201003","31201005")) -> 31201005
A18: 101 | B18: UNIMED ITUVERAVA | C18: 13019 | E18: UNIMED ITUVERAVA | F18: 776.26 | K18: ="|"&"PAGTO DOC - "&E18&"|"&"PLANO DE SAUDE - "&B18&"|"&"C CUSTO - "&LEFT(C18,5)&"|"&"TOTAL: "&F18&"|" -> |PAGTO DOC - UNIMED ITUVERAVA|PLANO DE SAUDE - UNIMED ITUVERAVA|C CUSTO - 13019|TOTAL: 776,26| | M18: =SUM(F18:L18) -> 776.26 | N18: ="|"&"PAGTO DOC - "&F18&"|"&"DESP - "&B18&"|"&"CENTRO CUSTO - "&C18&"|"&I18&"|"&G18&"|"&#REF!&"|"&J18&"|"&H18&"|"&K18&"|"&L18&"|" -> #REF! | O18: =IF(M18=0,0,IF(E18="SEGURO DE VIDA EM GRUPO","31201003","31201005")) -> 31201005
A19: 101 | B19: UNIMED ITUVERAVA | C19: 13021 | E19: UNIMED ITUVERAVA | F19: 2646.44 | K19: ="|"&"PAGTO DOC - "&E19&"|"&"PLANO DE SAUDE - "&B19&"|"&"C CUSTO - "&LEFT(C19,5)&"|"&"TOTAL: "&F19&"|" -> |PAGTO DOC - UNIMED ITUVERAVA|PLANO DE SAUDE - UNIMED ITUVERAVA|C CUSTO - 13021|TOTAL: 2646,44| | M19: =SUM(F19:L19) -> 2646.44 | N19: ="|"&"PAGTO DOC - "&F19&"|"&"DESP - "&B19&"|"&"CENTRO CUSTO - "&C19&"|"&I19&"|"&G19&"|"&#REF!&"|"&J19&"|"&H19&"|"&K19&"|"&L19&"|" -> #REF! | O19: =IF(M19=0,0,IF(E19="SEGURO DE VIDA EM GRUPO","31201003","31201005")) -> 31201005
A20: 101 | B20: UNIMED ITUVERAVA | C20: 14012 | E20: UNIMED ITUVERAVA | F20: 1870.18 | K20: ="|"&"PAGTO DOC - "&E20&"|"&"PLANO DE SAUDE - "&B20&"|"&"C CUSTO - "&LEFT(C20,5)&"|"&"TOTAL: "&F20&"|" -> |PAGTO DOC - UNIMED ITUVERAVA|PLANO DE SAUDE - UNIMED ITUVERAVA|C CUSTO - 14012|TOTAL: 1870,18| | M20: =SUM(F20:L20) -> 1870.18 | N20: ="|"&"PAGTO DOC - "&F20&"|"&"DESP - "&B20&"|"&"CENTRO CUSTO - "&C20&"|"&I20&"|"&G20&"|"&#REF!&"|"&J20&"|"&H20&"|"&K20&"|"&L20&"|" -> #REF! | O20: =IF(M20=0,0,IF(E20="SEGURO DE VIDA EM GRUPO","31201003","31201005")) -> 31201005
A21: 101 | B21: UNIMED ITUVERAVA | C21: 14051 | E21: UNIMED ITUVERAVA | F21: 2707.02 | K21: ="|"&"PAGTO DOC - "&E21&"|"&"PLANO DE SAUDE - "&B21&"|"&"C CUSTO - "&LEFT(C21,5)&"|"&"TOTAL: "&F21&"|" -> |PAGTO DOC - UNIMED ITUVERAVA|PLANO DE SAUDE - UNIMED ITUVERAVA|C CUSTO - 14051|TOTAL: 2707,02| | M21: =SUM(F21:L21) -> 2707.02 | N21: ="|"&"PAGTO DOC - "&F21&"|"&"DESP - "&B21&"|"&"CENTRO CUSTO - "&C21&"|"&I21&"|"&G21&"|"&#REF!&"|"&J21&"|"&H21&"|"&K21&"|"&L21&"|" -> #REF! | O21: =IF(M21=0,0,IF(E21="SEGURO DE VIDA EM GRUPO","31201003","31201005")) -> 31201005
... A42: 101 | B42: UNIMED ITUVERAVA | C42: 55030 | E42: UNIMED ITUVERAVA | F42: 546.96 | K42: ="|"&"PAGTO DOC - "&E42&"|"&"PLANO DE SAUDE - "&B42&"|"&"C CUSTO - "&LEFT(C42,5)&"|"&"TOTAL: "&F42&"|" -> |PAGTO DOC - UNIMED ITUVERAVA|PLANO DE SAUDE - UNIMED ITUVERAVA|C CUSTO - 55030|TOTAL: 546,96| | M42: =SUM(F42:L42) -> 546.96 | N42: ="|"&"PAGTO DOC - "&F42&"|"&"DESP - "&B42&"|"&"CENTRO CUSTO - "&C42&"|"&I42&"|"&G42&"|"&#REF!&"|"&J42&"|"&H42&"|"&K42&"|"&L42&"|" -> #REF! | O42: =IF(M42=0,0,IF(E42="SEGURO DE VIDA EM GRUPO","31201003","31201005")) -> 31201005
A43: 101 | B43: UNIMED ITUVERAVA | C43: 21012 | E43: UNIMED ITUVERAVA | F43: 229.3 | K43: ="|"&"PAGTO DOC - "&E43&"|"&"PLANO DE SAUDE - "&B43&"|"&"C CUSTO - "&LEFT(C43,5)&"|"&"TOTAL: "&F43&"|" -> |PAGTO DOC - UNIMED ITUVERAVA|PLANO DE SAUDE - UNIMED ITUVERAVA|C CUSTO - 21012|TOTAL: 229,3| | M43: =SUM(F43:L43) -> 229.3 | N43: ="|"&"PAGTO DOC - "&F43&"|"&"DESP - "&B43&"|"&"CENTRO CUSTO - "&C43&"|"&I43&"|"&G43&"|"&#REF!&"|"&J43&"|"&H43&"|"&K43&"|"&L43&"|" -> #REF! | O43: =IF(M43=0,0,IF(E43="SEGURO DE VIDA EM GRUPO","31201003","31201005")) -> 31201005
A44: 101 | B44: UNIMED ITUVERAVA | C44: 31090 | E44: UNIMED ITUVERAVA | F44: 546.96 | K44: ="|"&"PAGTO DOC - "&E44&"|"&"PLANO DE SAUDE - "&B44&"|"&"C CUSTO - "&LEFT(C44,5)&"|"&"TOTAL: "&F44&"|" -> |PAGTO DOC - UNIMED ITUVERAVA|PLANO DE SAUDE - UNIMED ITUVERAVA|C CUSTO - 31090|TOTAL: 546,96| | M44: =SUM(F44:L44) -> 546.96 | N44: ="|"&"PAGTO DOC - "&F44&"|"&"DESP - "&B44&"|"&"CENTRO CUSTO - "&C44&"|"&I44&"|"&G44&"|"&#REF!&"|"&J44&"|"&H44&"|"&K44&"|"&L44&"|" -> #REF! | O44: =IF(M44=0,0,IF(E44="SEGURO DE VIDA EM GRUPO","31201003","31201005")) -> 31201005
A45: 101 | B45: UNIMED ITUVERAVA | C45: 13016 | E45: UNIMED ITUVERAVA | F45: 229.3 | K45: ="|"&"PAGTO DOC - "&E45&"|"&"PLANO DE SAUDE - "&B45&"|"&"C CUSTO - "&LEFT(C45,5)&"|"&"TOTAL: "&F45&"|" -> |PAGTO DOC - UNIMED ITUVERAVA|PLANO DE SAUDE - UNIMED ITUVERAVA|C CUSTO - 13016|TOTAL: 229,3| | M45: =SUM(F45:L45) -> 229.3 | N45: ="|"&"PAGTO DOC - "&F45&"|"&"DESP - "&B45&"|"&"CENTRO CUSTO - "&C45&"|"&I45&"|"&G45&"|"&#REF!&"|"&J45&"|"&H45&"|"&K45&"|"&L45&"|" -> #REF! | O45: =IF(M45=0,0,IF(E45="SEGURO DE VIDA EM GRUPO","31201003","31201005")) -> 31201005
A46: 101 | B46: UNIMED ITUVERAVA | C46: 33050 | E46: UNIMED ITUVERAVA | F46: 546.96 | K46: ="|"&"PAGTO DOC - "&E46&"|"&"PLANO DE SAUDE - "&B46&"|"&"C CUSTO - "&LEFT(C46,5)&"|"&"TOTAL: "&F46&"|" -> |PAGTO DOC - UNIMED ITUVERAVA|PLANO DE SAUDE - UNIMED ITUVERAVA|C CUSTO - 33050|TOTAL: 546,96| | M46: =SUM(F46:L46) -> 546.96 | N46: ="|"&"PAGTO DOC - "&F46&"|"&"DESP - "&B46&"|"&"CENTRO CUSTO - "&C46&"|"&I46&"|"&G46&"|"&#REF!&"|"&J46&"|"&H46&"|"&K46&"|"&L46&"|" -> #REF! | O46: =IF(M46=0,0,IF(E46="SEGURO DE VIDA EM GRUPO","31201003","31201005")) -> 31201005
A47: 101 | B47: UNIMED ITUVERAVA | C47: 21011 | E47: UNIMED ITUVERAVA | F47: 229.3 | K47: ="|"&"PAGTO DOC - "&E47&"|"&"PLANO DE SAUDE - "&B47&"|"&"C CUSTO - "&LEFT(C47,5)&"|"&"TOTAL: "&F47&"|" -> |PAGTO DOC - UNIMED ITUVERAVA|PLANO DE SAUDE - UNIMED ITUVERAVA|C CUSTO - 21011|TOTAL: 229,3| | M47: =SUM(F47:L47) -> 229.3 | N47: ="|"&"PAGTO DOC - "&F47&"|"&"DESP - "&B47&"|"&"CENTRO CUSTO - "&C47&"|"&I47&"|"&G47&"|"&#REF!&"|"&J47&"|"&H47&"|"&K47&"|"&L47&"|" -> #REF! | O47: =IF(M47=0,0,IF(E47="SEGURO DE VIDA EM GRUPO","31201003","31201005")) -> 31201005
A48: 101 | B48: SEGURO DE VIDA EM GRUPO | C48: 11011 | E48: SEGURO DE VIDA EM GRUPO | F48: 74.15 | K48: ="|"&"PAGTO DOC - "&E48&"|"&"PLANO DE SAUDE - "&B48&"|"&"C CUSTO - "&LEFT(C48,5)&"|"&"TOTAL: "&F48&"|" -> |PAGTO DOC - SEGURO DE VIDA EM GRUPO|PLANO DE SAUDE - SEGURO DE VIDA EM GRUPO|C CUSTO - 11011|TOTAL: 74,15| | M48: =SUM(F48:L48) -> 74.15 | N48: ="|"&"PAGTO DOC - "&F48&"|"&"DESP - "&B48&"|"&"CENTRO CUSTO - "&C48&"|"&I48&"|"&G48&"|"&#REF!&"|"&J48&"|"&H48&"|"&K48&"|"&L48&"|" -> #REF! | O48: =IF(M48=0,0,IF(E48="SEGURO DE VIDA EM GRUPO","31201003","31201005")) -> 31201003
A49: 101 | B49: SEGURO DE VIDA EM GRUPO | C49: 13013 | E49: SEGURO DE VIDA EM GRUPO | F49: 8.04 | K49: ="|"&"PAGTO DOC - "&E49&"|"&"PLANO DE SAUDE - "&B49&"|"&"C CUSTO - "&LEFT(C49,5)&"|"&"TOTAL: "&F49&"|" -> |PAGTO DOC - SEGURO DE VIDA EM GRUPO|PLANO DE SAUDE - SEGURO DE VIDA EM GRUPO|C CUSTO - 13013|TOTAL: 8,04| | M49: =SUM(F49:L49) -> 8.04 | N49: ="|"&"PAGTO DOC - "&F49&"|"&"DESP - "&B49&"|"&"CENTRO CUSTO - "&C49&"|"&I49&"|"&G49&"|"&#REF!&"|"&J49&"|"&H49&"|"&K49&"|"&L49&"|" -> #REF! | O49: =IF(M49=0,0,IF(E49="SEGURO DE VIDA EM GRUPO","31201003","31201005")) -> 31201003
A50: 101 | B50: SEGURO DE VIDA EM GRUPO | C50: 13014 | E50: SEGURO DE VIDA EM GRUPO | F50: 74.15 | K50: ="|"&"PAGTO DOC - "&E50&"|"&"PLANO DE SAUDE - "&B50&"|"&"C CUSTO - "&LEFT(C50,5)&"|"&"TOTAL: "&F50&"|" -> |PAGTO DOC - SEGURO DE VIDA EM GRUPO|PLANO DE SAUDE - SEGURO DE VIDA EM GRUPO|C CUSTO - 13014|TOTAL: 74,15| | M50: =SUM(F50:L50) -> 74.15 | N50: ="|"&"PAGTO DOC - "&F50&"|"&"DESP - "&B50&"|"&"CENTRO CUSTO - "&C50&"|"&I50&"|"&G50&"|"&#REF!&"|"&J50&"|"&H50&"|"&K50&"|"&L50&"|" -> #REF! | O50: =IF(M50=0,0,IF(E50="SEGURO DE VIDA EM GRUPO","31201003","31201005")) -> 31201003
A51: 101 | B51: SEGURO DE VIDA EM GRUPO | C51: 14050 | E51: SEGURO DE VIDA EM GRUPO | F51: 72.36 | K51: ="|"&"PAGTO DOC - "&E51&"|"&"PLANO DE SAUDE - "&B51&"|"&"C CUSTO - "&LEFT(C51,5)&"|"&"TOTAL: "&F51&"|" -> |PAGTO DOC - SEGURO DE VIDA EM GRUPO|PLANO DE SAUDE - SEGURO DE VIDA EM GRUPO|C CUSTO - 14050|TOTAL: 72,36| | M51: =SUM(F51:L51) -> 72.36 | N51: ="|"&"PAGTO DOC - "&F51&"|"&"DESP - "&B51&"|"&"CENTRO CUSTO - "&C51&"|"&I51&"|"&G51&"|"&#REF!&"|"&J51&"|"&H51&"|"&K51&"|"&L51&"|" -> #REF! | O51: =IF(M51=0,0,IF(E51="SEGURO DE VIDA EM GRUPO","31201003","31201005")) -> 31201003
A52: 101 | B52: SEGURO DE VIDA EM GRUPO | C52: 14051 | E52: SEGURO DE VIDA EM GRUPO | F52: 201 | K52: ="|"&"PAGTO DOC - "&E52&"|"&"PLANO DE SAUDE - "&B52&"|"&"C CUSTO - "&LEFT(C52,5)&"|"&"TOTAL: "&F52&"|" -> |PAGTO DOC - SEGURO DE VIDA EM GRUPO|PLANO DE SAUDE - SEGURO DE VIDA EM GRUPO|C CUSTO - 14051|TOTAL: 201| | M52: =SUM(F52:L52) -> 201 | N52: ="|"&"PAGTO DOC - "&F52&"|"&"DESP - "&B52&"|"&"CENTRO CUSTO - "&C52&"|"&I52&"|"&G52&"|"&#REF!&"|"&J52&"|"&H52&"|"&K52&"|"&L52&"|" -> #REF! | O52: =IF(M52=0,0,IF(E52="SEGURO DE VIDA EM GRUPO","31201003","31201005")) -> 31201003
A53: 101 | B53: SEGURO DE VIDA EM GRUPO | C53: 14052 | E53: SEGURO DE VIDA EM GRUPO | F53: 88.44 | K53: ="|"&"PAGTO DOC - "&E53&"|"&"PLANO DE SAUDE - "&B53&"|"&"C CUSTO - "&LEFT(C53,5)&"|"&"TOTAL: "&F53&"|" -> |PAGTO DOC - SEGURO DE VIDA EM GRUPO|PLANO DE SAUDE - SEGURO DE VIDA EM GRUPO|C CUSTO - 14052|TOTAL: 88,44| | M53: =SUM(F53:L53) -> 88.44 | N53: ="|"&"PAGTO DOC - "&F53&"|"&"DESP - "&B53&"|"&"CENTRO CUSTO - "&C53&"|"&I53&"|"&G53&"|"&#REF!&"|"&J53&"|"&H53&"|"&K53&"|"&L53&"|" -> #REF! | O53: =IF(M53=0,0,IF(E53="SEGURO DE VIDA EM GRUPO","31201003","31201005")) -> 31201003
A54: 101 | B54: SEGURO DE VIDA EM GRUPO | C54: 14054 | E54: SEGURO DE VIDA EM GRUPO | F54: 90.23 | K54: ="|"&"PAGTO DOC - "&E54&"|"&"PLANO DE SAUDE - "&B54&"|"&"C CUSTO - "&LEFT(C54,5)&"|"&"TOTAL: "&F54&"|" -> |PAGTO DOC - SEGURO DE VIDA EM GRUPO|PLANO DE SAUDE - SEGURO DE VIDA EM GRUPO|C CUSTO - 14054|TOTAL: 90,23| | M54: =SUM(F54:L54) -> 90.23 | N54: ="|"&"PAGTO DOC - "&F54&"|"&"DESP - "&B54&"|"&"CENTRO CUSTO - "&C54&"|"&I54&"|"&G54&"|"&#REF!&"|"&J54&"|"&H54&"|"&K54&"|"&L54&"|" -> #REF! | O54: =IF(M54=0,0,IF(E54="SEGURO DE VIDA EM GRUPO","31201003","31201005")) -> 31201003
... A65: 101 | B65: SEGURO DE VIDA EM GRUPO | C65: 31200 | E65: SEGURO DE VIDA EM GRUPO | F65: 8.04 | K65: ="|"&"PAGTO DOC - "&E65&"|"&"PLANO DE SAUDE - "&B65&"|"&"C CUSTO - "&LEFT(C65,5)&"|"&"TOTAL: "&F65&"|" -> |PAGTO DOC - SEGURO DE VIDA EM GRUPO|PLANO DE SAUDE - SEGURO DE VIDA EM GRUPO|C CUSTO - 31200|TOTAL: 8,04| | M65: =SUM(F65:L65) -> 8.04 | N65: ="|"&"PAGTO DOC - "&F65&"|"&"DESP - "&B65&"|"&"CENTRO CUSTO - "&C65&"|"&I65&"|"&G65&"|"&#REF!&"|"&J65&"|"&H65&"|"&K65&"|"&L65&"|" -> #REF! | O65: =IF(M65=0,0,IF(E65="SEGURO DE VIDA EM GRUPO","31201003","31201005")) -> 31201003
A66: 101 | B66: SEGURO DE VIDA EM GRUPO | C66: 11011 | E66: SEGURO DE VIDA EM GRUPO | F66: 230.49 | K66: ="|"&"PAGTO DOC - "&E66&"|"&"PLANO DE SAUDE - "&B66&"|"&"C CUSTO - "&LEFT(C66,5)&"|"&"TOTAL: "&F66&"|" -> |PAGTO DOC - SEGURO DE VIDA EM GRUPO|PLANO DE SAUDE - SEGURO DE VIDA EM GRUPO|C CUSTO - 11011|TOTAL: 230,49| | M66: =SUM(F66:L66) -> 230.49 | N66: ="|"&"PAGTO DOC - "&F66&"|"&"DESP - "&B66&"|"&"CENTRO CUSTO - "&C66&"|"&I66&"|"&G66&"|"&#REF!&"|"&J66&"|"&H66&"|"&K66&"|"&L66&"|" -> #REF! | O66: =IF(M66=0,0,IF(E66="SEGURO DE VIDA EM GRUPO","31201003","31201005")) -> 31201003
A67: 101 | B67: SEGURO DE VIDA EM GRUPO | C67: 11012 | E67: SEGURO DE VIDA EM GRUPO | F67: 90.23 | K67: ="|"&"PAGTO DOC - "&E67&"|"&"PLANO DE SAUDE - "&B67&"|"&"C CUSTO - "&LEFT(C67,5)&"|"&"TOTAL: "&F67&"|" -> |PAGTO DOC - SEGURO DE VIDA EM GRUPO|PLANO DE SAUDE - SEGURO DE VIDA EM GRUPO|C CUSTO - 11012|TOTAL: 90,23| | M67: =SUM(F67:L67) -> 90.23 | N67: ="|"&"PAGTO DOC - "&F67&"|"&"DESP - "&B67&"|"&"CENTRO CUSTO - "&C67&"|"&I67&"|"&G67&"|"&#REF!&"|"&J67&"|"&H67&"|"&K67&"|"&L67&"|" -> #REF! | O67: =IF(M67=0,0,IF(E67="SEGURO DE VIDA EM GRUPO","31201003","31201005")) -> 31201003
A68: 101 | B68: SEGURO DE VIDA EM GRUPO | C68: 11013 | E68: SEGURO DE VIDA EM GRUPO | F68: 74.15 | K68: ="|"&"PAGTO DOC - "&E68&"|"&"PLANO DE SAUDE - "&B68&"|"&"C CUSTO - "&LEFT(C68,5)&"|"&"TOTAL: "&F68&"|" -> |PAGTO DOC - SEGURO DE VIDA EM GRUPO|PLANO DE SAUDE - SEGURO DE VIDA EM GRUPO|C CUSTO - 11013|TOTAL: 74,15| | M68: =SUM(F68:L68) -> 74.15 | N68: ="|"&"PAGTO DOC - "&F68&"|"&"DESP - "&B68&"|"&"CENTRO CUSTO - "&C68&"|"&I68&"|"&G68&"|"&#REF!&"|"&J68&"|"&H68&"|"&K68&"|"&L68&"|" -> #REF! | O68: =IF(M68=0,0,IF(E68="SEGURO DE VIDA EM GRUPO","31201003","31201005")) -> 31201003
A69: 101 | B69: SEGURO DE VIDA EM GRUPO | C69: 13011 | E69: SEGURO DE VIDA EM GRUPO | F69: 64.32 | K69: ="|"&"PAGTO DOC - "&E69&"|"&"PLANO DE SAUDE - "&B69&"|"&"C CUSTO - "&LEFT(C69,5)&"|"&"TOTAL: "&F69&"|" -> |PAGTO DOC - SEGURO DE VIDA EM GRUPO|PLANO DE SAUDE - SEGURO DE VIDA EM GRUPO|C CUSTO - 13011|TOTAL: 64,32| | M69: =SUM(F69:L69) -> 64.32 | N69: ="|"&"PAGTO DOC - "&F69&"|"&"DESP - "&B69&"|"&"CENTRO CUSTO - "&C69&"|"&I69&"|"&G69&"|"&#REF!&"|"&J69&"|"&H69&"|"&K69&"|"&L69&"|" -> #REF! | O69: =IF(M69=0,0,IF(E69="SEGURO DE VIDA EM GRUPO","31201003","31201005")) -> 31201003
A70: 101 | B70: SEGURO DE VIDA EM GRUPO | C70: 13012 | E70: SEGURO DE VIDA EM GRUPO | F70: 16.08 | K70: ="|"&"PAGTO DOC - "&E70&"|"&"PLANO DE SAUDE - "&B70&"|"&"C CUSTO - "&LEFT(C70,5)&"|"&"TOTAL: "&F70&"|" -> |PAGTO DOC - SEGURO DE VIDA EM GRUPO|PLANO DE SAUDE - SEGURO DE VIDA EM GRUPO|C CUSTO - 13012|TOTAL: 16,08| | M70: =SUM(F70:L70) -> 16.08 | N70: ="|"&"PAGTO DOC - "&F70&"|"&"DESP - "&B70&"|"&"CENTRO CUSTO - "&C70&"|"&I70&"|"&G70&"|"&#REF!&"|"&J70&"|"&H70&"|"&K70&"|"&L70&"|" -> #REF! | O70: =IF(M70=0,0,IF(E70="SEGURO DE VIDA EM GRUPO","31201003","31201005")) -> 31201003
A71: 101 | B71: SEGURO DE VIDA EM GRUPO | C71: 13013 | E71: SEGURO DE VIDA EM GRUPO | F71: 128.33 | K71: ="|"&"PAGTO DOC - "&E71&"|"&"PLANO DE SAUDE - "&B71&"|"&"C CUSTO - "&LEFT(C71,5)&"|"&"TOTAL: "&F71&"|" -> |PAGTO DOC - SEGURO DE VIDA EM GRUPO|PLANO DE SAUDE - SEGURO DE VIDA EM GRUPO|C CUSTO - 13013|TOTAL: 128,33| | M71: =SUM(F71:L71) -> 128.33 | N71: ="|"&"PAGTO DOC - "&F71&"|"&"DESP - "&B71&"|"&"CENTRO CUSTO - "&C71&"|"&I71&"|"&G71&"|"&#REF!&"|"&J71&"|"&H71&"|"&K71&"|"&L71&"|" -> #REF! | O71: =IF(M71=0,0,IF(E71="SEGURO DE VIDA EM GRUPO","31201003","31201005")) -> 31201003
A72: 101 | B72: SEGURO DE VIDA EM GRUPO | C72: 13014 | E72: SEGURO DE VIDA EM GRUPO | F72: 40.2 | K72: ="|"&"PAGTO DOC - "&E72&"|"&"PLANO DE SAUDE - "&B72&"|"&"C CUSTO - "&LEFT(C72,5)&"|"&"TOTAL: "&F72&"|" -> |PAGTO DOC - SEGURO DE VIDA EM GRUPO|PLANO DE SAUDE - SEGURO DE VIDA EM GRUPO|C CUSTO - 13014|TOTAL: 40,2| | M72: =SUM(F72:L72) -> 40.2 | N72: ="|"&"PAGTO DOC - "&F72&"|"&"DESP - "&B72&"|"&"CENTRO CUSTO - "&C72&"|"&I72&"|"&G72&"|"&#REF!&"|"&J72&"|"&H72&"|"&K72&"|"&L72&"|" -> #REF! | O72: =IF(M72=0,0,IF(E72="SEGURO DE VIDA EM GRUPO","31201003","31201005")) -> 31201003
A73: 101 | B73: SEGURO DE VIDA EM GRUPO | C73: 13016 | E73: SEGURO DE VIDA EM GRUPO | F73: 40.2 | K73: ="|"&"PAGTO DOC - "&E73&"|"&"PLANO DE SAUDE - "&B73&"|"&"C CUSTO - "&LEFT(C73,5)&"|"&"TOTAL: "&F73&"|" -> |PAGTO DOC - SEGURO DE VIDA EM GRUPO|PLANO DE SAUDE - SEGURO DE VIDA EM GRUPO|C CUSTO - 13016|TOTAL: 40,2| | M73: =SUM(F73:L73) -> 40.2 | N73: ="|"&"PAGTO DOC - "&F73&"|"&"DESP - "&B73&"|"&"CENTRO CUSTO - "&C73&"|"&I73&"|"&G73&"|"&#REF!&"|"&J73&"|"&H73&"|"&K73&"|"&L73&"|" -> #REF! | O73: =IF(M73=0,0,IF(E73="SEGURO DE VIDA EM GRUPO","31201003","31201005")) -> 31201003
A74: 101 | B74: SEGURO DE VIDA EM GRUPO | C74: 13017 | E74: SEGURO DE VIDA EM GRUPO | F74: 32.16 | K74: ="|"&"PAGTO DOC - "&E74&"|"&"PLANO DE SAUDE - "&B74&"|"&"C CUSTO - "&LEFT(C74,5)&"|"&"TOTAL: "&F74&"|" -> |PAGTO DOC - SEGURO DE VIDA EM GRUPO|PLANO DE SAUDE - SEGURO DE VIDA EM GRUPO|C CUSTO - 13017|TOTAL: 32,16| | M74: =SUM(F74:L74) -> 32.16 | N74: ="|"&"PAGTO DOC - "&F74&"|"&"DESP - "&B74&"|"&"CENTRO CUSTO - "&C74&"|"&I74&"|"&G74&"|"&#REF!&"|"&J74&"|"&H74&"|"&K74&"|"&L74&"|" -> #REF! | O74: =IF(M74=0,0,IF(E74="SEGURO DE VIDA EM GRUPO","31201003","31201005")) -> 31201003
A75: 101 | B75: SEGURO DE VIDA EM GRUPO | C75: 13018 | E75: SEGURO DE VIDA EM GRUPO | F75: 24.12 | K75: ="|"&"PAGTO DOC - "&E75&"|"&"PLANO DE SAUDE - "&B75&"|"&"C CUSTO - "&LEFT(C75,5)&"|"&"TOTAL: "&F75&"|" -> |PAGTO DOC - SEGURO DE VIDA EM GRUPO|PLANO DE SAUDE - SEGURO DE VIDA EM GRUPO|C CUSTO - 13018|TOTAL: 24,12| | M75: =SUM(F75:L75) -> 24.12 | N75: ="|"&"PAGTO DOC - "&F75&"|"&"DESP - "&B75&"|"&"CENTRO CUSTO - "&C75&"|"&I75&"|"&G75&"|"&#REF!&"|"&J75&"|"&H75&"|"&K75&"|"&L75&"|" -> #REF! | O75: =IF(M75=0,0,IF(E75="SEGURO DE VIDA EM GRUPO","31201003","31201005")) -> 31201003
A76: 101 | B76: SEGURO DE VIDA EM GRUPO | C76: 13019 | E76: SEGURO DE VIDA EM GRUPO | F76: 24.12 | K76: ="|"&"PAGTO DOC - "&E76&"|"&"PLANO DE SAUDE - "&B76&"|"&"C CUSTO - "&LEFT(C76,5)&"|"&"TOTAL: "&F76&"|" -> |PAGTO DOC - SEGURO DE VIDA EM GRUPO|PLANO DE SAUDE - SEGURO DE VIDA EM GRUPO|C CUSTO - 13019|TOTAL: 24,12| | M76: =SUM(F76:L76) -> 24.12 | N76: ="|"&"PAGTO DOC - "&F76&"|"&"DESP - "&B76&"|"&"CENTRO CUSTO - "&C76&"|"&I76&"|"&G76&"|"&#REF!&"|"&J76&"|"&H76&"|"&K76&"|"&L76&"|" -> #REF! | O76: =IF(M76=0,0,IF(E76="SEGURO DE VIDA EM GRUPO","31201003","31201005")) -> 31201003
A77: 101 | B77: SEGURO DE VIDA EM GRUPO | C77: 13021 | E77: SEGURO DE VIDA EM GRUPO | F77: 64.32 | K77: ="|"&"PAGTO DOC - "&E77&"|"&"PLANO DE SAUDE - "&B77&"|"&"C CUSTO - "&LEFT(C77,5)&"|"&"TOTAL: "&F77&"|" -> |PAGTO DOC - SEGURO DE VIDA EM GRUPO|PLANO DE SAUDE - SEGURO DE VIDA EM GRUPO|C CUSTO - 13021|TOTAL: 64,32| | M77: =SUM(F77:L77) -> 64.32 | N77: ="|"&"PAGTO DOC - "&F77&"|"&"DESP - "&B77&"|"&"CENTRO CUSTO - "&C77&"|"&I77&"|"&G77&"|"&#REF!&"|"&J77&"|"&H77&"|"&K77&"|"&L77&"|" -> #REF! | O77: =IF(M77=0,0,IF(E77="SEGURO DE VIDA EM GRUPO","31201003","31201005")) -> 31201003
... A106: 101 | B106: SEGURO DE VIDA EM GRUPO | C106: 33060 | E106: SEGURO DE VIDA EM GRUPO | F106: 80.4 | K106: ="|"&"PAGTO DOC - "&E106&"|"&"PLANO DE SAUDE - "&B106&"|"&"C CUSTO - "&LEFT(C106,5)&"|"&"TOTAL: "&F106&"|" -> |PAGTO DOC - SEGURO DE VIDA EM GRUPO|PLANO DE SAUDE - SEGURO DE VIDA EM GRUPO|C CUSTO - 33060|TOTAL: 80,4| | M106: =SUM(F106:L106) -> 80.4 | N106: ="|"&"PAGTO DOC - "&F106&"|"&"DESP - "&B106&"|"&"CENTRO CUSTO - "&C106&"|"&I106&"|"&G106&"|"&#REF!&"|"&J106&"|"&H106&"|"&K106&"|"&L106&"|" -> #REF! | O106: =IF(M106=0,0,IF(E106="SEGURO DE VIDA EM GRUPO","31201003","31201005")) -> 31201003
A107: 101 | B107: SEGURO DE VIDA EM GRUPO | C107: 55030 | E107: SEGURO DE VIDA EM GRUPO | F107: 16.08 | K107: ="|"&"PAGTO DOC - "&E107&"|"&"PLANO DE SAUDE - "&B107&"|"&"C CUSTO - "&LEFT(C107,5)&"|"&"TOTAL: "&F107&"|" -> |PAGTO DOC - SEGURO DE VIDA EM GRUPO|PLANO DE SAUDE - SEGURO DE VIDA EM GRUPO|C CUSTO - 55030|TOTAL: 16,08| | M107: =SUM(F107:L107) -> 16.08 | O107: =IF(M107=0,0,IF(E107="SEGURO DE VIDA EM GRUPO","31201003","31201005")) -> 31201003
A108: 101 | B108: SEGURO DE VIDA EM GRUPO | C108: 31090 | E108: SEGURO DE VIDA EM GRUPO | F108: 8.04 | K108: ="|"&"PAGTO DOC - "&E108&"|"&"PLANO DE SAUDE - "&B108&"|"&"C CUSTO - "&LEFT(C108,5)&"|"&"TOTAL: "&F108&"|" -> |PAGTO DOC - SEGURO DE VIDA EM GRUPO|PLANO DE SAUDE - SEGURO DE VIDA EM GRUPO|C CUSTO - 31090|TOTAL: 8,04| | M108: =SUM(F108:L108) -> 8.04 | O108: =IF(M108=0,0,IF(E108="SEGURO DE VIDA EM GRUPO","31201003","31201005")) -> 31201003
A109: 101 | B109: SEGURO DE VIDA EM GRUPO | C109: 31116 | E109: SEGURO DE VIDA EM GRUPO | F109: 16.08 | K109: ="|"&"PAGTO DOC - "&E109&"|"&"PLANO DE SAUDE - "&B109&"|"&"C CUSTO - "&LEFT(C109,5)&"|"&"TOTAL: "&F109&"|" -> |PAGTO DOC - SEGURO DE VIDA EM GRUPO|PLANO DE SAUDE - SEGURO DE VIDA EM GRUPO|C CUSTO - 31116|TOTAL: 16,08| | M109: =SUM(F109:L109) -> 16.08 | N109: ="|"&"PAGTO DOC - "&F109&"|"&"DESP - "&B109&"|"&"CENTRO CUSTO - "&C109&"|"&I109&"|"&G109&"|"&#REF!&"|"&J109&"|"&H109&"|"&K109&"|"&L109&"|" -> #REF! | O109: =IF(M109=0,0,IF(E109="SEGURO DE VIDA EM GRUPO","31201003","31201005")) -> 31201003
A110: 101 | B110: SEGURO DE VIDA EM GRUPO | C110: 33050 | E110: SEGURO DE VIDA EM GRUPO | F110: 16.08 | K110: ="|"&"PAGTO DOC - "&E110&"|"&"PLANO DE SAUDE - "&B110&"|"&"C CUSTO - "&LEFT(C110,5)&"|"&"TOTAL: "&F110&"|" -> |PAGTO DOC - SEGURO DE VIDA EM GRUPO|PLANO DE SAUDE - SEGURO DE VIDA EM GRUPO|C CUSTO - 33050|TOTAL: 16,08| | M110: =SUM(F110:L110) -> 16.08 | N110: ="|"&"PAGTO DOC - "&F110&"|"&"DESP - "&B110&"|"&"CENTRO CUSTO - "&C110&"|"&I110&"|"&G110&"|"&#REF!&"|"&J110&"|"&H110&"|"&K110&"|"&L110&"|" -> #REF! | O110: =IF(M110=0,0,IF(E110="SEGURO DE VIDA EM GRUPO","31201003","31201005")) -> 31201003
A111: 101 | B111: SEGURO DE VIDA EM GRUPO | C111: 14012 | E111: SEGURO DE VIDA EM GRUPO | F111: 16.08 | K111: ="|"&"PAGTO DOC - "&E111&"|"&"PLANO DE SAUDE - "&B111&"|"&"C CUSTO - "&LEFT(C111,5)&"|"&"TOTAL: "&F111&"|" -> |PAGTO DOC - SEGURO DE VIDA EM GRUPO|PLANO DE SAUDE - SEGURO DE VIDA EM GRUPO|C CUSTO - 14012|TOTAL: 16,08| | M111: =SUM(F111:L111) -> 16.08 | N111: ="|"&"PAGTO DOC - "&F111&"|"&"DESP - "&B111&"|"&"CENTRO CUSTO - "&C111&"|"&I111&"|"&G111&"|"&#REF!&"|"&J111&"|"&H111&"|"&K111&"|"&L111&"|" -> #REF! | O111: =IF(M111=0,0,IF(E111="SEGURO DE VIDA EM GRUPO","31201003","31201005")) -> 31201003
A112: 101 | B112: SEGURO DE VIDA EM GRUPO | C112: 21012 | E112: SEGURO DE VIDA EM GRUPO | F112: 8.04 | K112: ="|"&"PAGTO DOC - "&E112&"|"&"PLANO DE SAUDE - "&B112&"|"&"C CUSTO - "&LEFT(C112,5)&"|"&"TOTAL: "&F112&"|" -> |PAGTO DOC - SEGURO DE VIDA EM GRUPO|PLANO DE SAUDE - SEGURO DE VIDA EM GRUPO|C CUSTO - 21012|TOTAL: 8,04| | M112: =SUM(F112:L112) -> 8.04 | N112: ="|"&"PAGTO DOC - "&F112&"|"&"DESP - "&B112&"|"&"CENTRO CUSTO - "&C112&"|"&I112&"|"&G112&"|"&#REF!&"|"&J112&"|"&H112&"|"&K112&"|"&L112&"|" -> #REF! | O112: =IF(M112=0,0,IF(E112="SEGURO DE VIDA EM GRUPO","31201003","31201005")) -> 31201003
A113: 101 | B113: SEGURO DE VIDA EM GRUPO | C113: 13016 | E113: SEGURO DE VIDA EM GRUPO | F113: 8.04 | K113: ="|"&"PAGTO DOC - "&E113&"|"&"PLANO DE SAUDE - "&B113&"|"&"C CUSTO - "&LEFT(C113,5)&"|"&"TOTAL: "&F113&"|" -> |PAGTO DOC - SEGURO DE VIDA EM GRUPO|PLANO DE SAUDE - SEGURO DE VIDA EM GRUPO|C CUSTO - 13016|TOTAL: 8,04| | M113: =SUM(F113:L113) -> 8.04 | N113: ="|"&"PAGTO DOC - "&F113&"|"&"DESP - "&B113&"|"&"CENTRO CUSTO - "&C113&"|"&I113&"|"&G113&"|"&#REF!&"|"&J113&"|"&H113&"|"&K113&"|"&L113&"|" -> #REF! | O113: =IF(M113=0,0,IF(E113="SEGURO DE VIDA EM GRUPO","31201003","31201005")) -> 31201003
A114: 101 | B114: SEGURO DE VIDA EM GRUPO | C114: 13021 | E114: SEGURO DE VIDA EM GRUPO | F114: 8.04 | K114: ="|"&"PAGTO DOC - "&E114&"|"&"PLANO DE SAUDE - "&B114&"|"&"C CUSTO - "&LEFT(C114,5)&"|"&"TOTAL: "&F114&"|" -> |PAGTO DOC - SEGURO DE VIDA EM GRUPO|PLANO DE SAUDE - SEGURO DE VIDA EM GRUPO|C CUSTO - 13021|TOTAL: 8,04| | M114: =SUM(F114:L114) -> 8.04 | N114: ="|"&"PAGTO DOC - "&F114&"|"&"DESP - "&B114&"|"&"CENTRO CUSTO - "&C114&"|"&I114&"|"&G114&"|"&#REF!&"|"&J114&"|"&H114&"|"&K114&"|"&L114&"|" -> #REF! | O114: =IF(M114=0,0,IF(E114="SEGURO DE VIDA EM GRUPO","31201003","31201005")) -> 31201003
A115: 101 | B115: SEGURO DE VIDA EM GRUPO | C115: 21011 | E115: SEGURO DE VIDA EM GRUPO | F115: 8.04 | K115: ="|"&"PAGTO DOC - "&E115&"|"&"PLANO DE SAUDE - "&B115&"|"&"C CUSTO - "&LEFT(C115,5)&"|"&"TOTAL: "&F115&"|" -> |PAGTO DOC - SEGURO DE VIDA EM GRUPO|PLANO DE SAUDE - SEGURO DE VIDA EM GRUPO|C CUSTO - 21011|TOTAL: 8,04| | M115: =SUM(F115:L115) -> 8.04 | N115: ="|"&"PAGTO DOC - "&F115&"|"&"DESP - "&B115&"|"&"CENTRO CUSTO - "&C115&"|"&I115&"|"&G115&"|"&#REF!&"|"&J115&"|"&H115&"|"&K115&"|"&L115&"|" -> #REF! | O115: =IF(M115=0,0,IF(E115="SEGURO DE VIDA EM GRUPO","31201003","31201005")) -> 31201003
A116: 101 | B116: SEGURO DE VIDA EM GRUPO | C116: 33010 | E116: SEGURO DE VIDA EM GRUPO | F116: 8.04 | K116: ="|"&"PAGTO DOC - "&E116&"|"&"PLANO DE SAUDE - "&B116&"|"&"C CUSTO - "&LEFT(C116,5)&"|"&"TOTAL: "&F116&"|" -> |PAGTO DOC - SEGURO DE VIDA EM GRUPO|PLANO DE SAUDE - SEGURO DE VIDA EM GRUPO|C CUSTO - 33010|TOTAL: 8,04| | M116: =SUM(F116:L116) -> 8.04 | N116: ="|"&"PAGTO DOC - "&F116&"|"&"DESP - "&B116&"|"&"CENTRO CUSTO - "&C116&"|"&I116&"|"&G116&"|"&#REF!&"|"&J116&"|"&H116&"|"&K116&"|"&L116&"|" -> #REF! | O116: =IF(M116=0,0,IF(E116="SEGURO DE VIDA EM GRUPO","31201003","31201005")) -> 31201003
A117: 101 | B117: SEGURO SAÚDE | C117: 13014 | E117: SEGURO SAÚDE | F117: 2502.52 | K117: ="|"&"PAGTO DOC - "&E117&"|"&"PLANO DE SAUDE - "&B117&"|"&"C CUSTO - "&LEFT(C117,5)&"|"&"TOTAL: "&F117&"|" -> |PAGTO DOC - SEGURO SAÚDE|PLANO DE SAUDE - SEGURO SAÚDE|C CUSTO - 13014|TOTAL: 2502,52| | M117: =SUM(F117:L117) -> 2502.52 | N117: ="|"&"PAGTO DOC - "&F117&"|"&"DESP - "&B117&"|"&"CENTRO CUSTO - "&C117&"|"&I117&"|"&G117&"|"&#REF!&"|"&J117&"|"&H117&"|"&K117&"|"&L117&"|" -> #REF! | O117: =IF(M117=0,0,IF(E117="SEGURO DE VIDA EM GRUPO","31201003","31201005")) -> 31201005
A118: 101 | B118: SEGURO SAÚDE | C118: 14050 | E118: SEGURO SAÚDE | F118: 1238.55 | K118: ="|"&"PAGTO DOC - "&E118&"|"&"PLANO DE SAUDE - "&B118&"|"&"C CUSTO - "&LEFT(C118,5)&"|"&"TOTAL: "&F118&"|" -> |PAGTO DOC - SEGURO SAÚDE|PLANO DE SAUDE - SEGURO SAÚDE|C CUSTO - 14050|TOTAL: 1238,55| | M118: =SUM(F118:L118) -> 1238.55 | N118: ="|"&"PAGTO DOC - "&F118&"|"&"DESP - "&B118&"|"&"CENTRO CUSTO - "&C118&"|"&I118&"|"&G118&"|"&#REF!&"|"&J118&"|"&H118&"|"&K118&"|"&L118&"|" -> #REF! | O118: =IF(M118=0,0,IF(E118="SEGURO DE VIDA EM GRUPO","31201003","31201005")) -> 31201005
A119: 101 | B119: SEGURO SAÚDE | C119: 15012 | E119: SEGURO SAÚDE | F119: 2502.52 | K119: ="|"&"PAGTO DOC - "&E119&"|"&"PLANO DE SAUDE - "&B119&"|"&"C CUSTO - "&LEFT(C119,5)&"|"&"TOTAL: "&F119&"|" -> |PAGTO DOC - SEGURO SAÚDE|PLANO DE SAUDE - SEGURO SAÚDE|C CUSTO - 15012|TOTAL: 2502,52| | M119: =SUM(F119:L119) -> 2502.52 | N119: ="|"&"PAGTO DOC - "&F119&"|"&"DESP - "&B119&"|"&"CENTRO CUSTO - "&C119&"|"&I119&"|"&G119&"|"&#REF!&"|"&J119&"|"&H119&"|"&K119&"|"&L119&"|" -> #REF! | O119: =IF(M119=0,0,IF(E119="SEGURO DE VIDA EM GRUPO","31201003","31201005")) -> 31201005
A120: 101 | B120: SEGURO SAÚDE | C120: 15056 | E120: SEGURO SAÚDE | F120: 1238.55 | K120: ="|"&"PAGTO DOC - "&E120&"|"&"PLANO DE SAUDE - "&B120&"|"&"C CUSTO - "&LEFT(C120,5)&"|"&"TOTAL: "&F120&"|" -> |PAGTO DOC - SEGURO SAÚDE|PLANO DE SAUDE - SEGURO SAÚDE|C CUSTO - 15056|TOTAL: 1238,55| | M120: =SUM(F120:L120) -> 1238.55 | N120: ="|"&"PAGTO DOC - "&F120&"|"&"DESP - "&B120&"|"&"CENTRO CUSTO - "&C120&"|"&I120&"|"&G120&"|"&#REF!&"|"&J120&"|"&H120&"|"&K120&"|"&L120&"|" -> #REF! | O120: =IF(M120=0,0,IF(E120="SEGURO DE VIDA EM GRUPO","31201003","31201005")) -> 31201005
A121: 101 | B121: SEGURO SAÚDE | C121: 11011 | E121: SEGURO SAÚDE | F121: 33358.46 | K121: ="|"&"PAGTO DOC - "&E121&"|"&"PLANO DE SAUDE - "&B121&"|"&"C CUSTO - "&LEFT(C121,5)&"|"&"TOTAL: "&F121&"|" -> |PAGTO DOC - SEGURO SAÚDE|PLANO DE SAUDE - SEGURO SAÚDE|C CUSTO - 11011|TOTAL: 33358,46| | M121: =SUM(F121:L121) -> 33358.46 | N121: ="|"&"PAGTO DOC - "&F121&"|"&"DESP - "&B121&"|"&"CENTRO CUSTO - "&C121&"|"&I121&"|"&G121&"|"&#REF!&"|"&J121&"|"&H121&"|"&K121&"|"&L121&"|" -> #REF! | O121: =IF(M121=0,0,IF(E121="SEGURO DE VIDA EM GRUPO","31201003","31201005")) -> 31201005
A122: 101 | B122: SEGURO SAÚDE | C122: 11012 | E122: SEGURO SAÚDE | F122: 15015.12 | K122: ="|"&"PAGTO DOC - "&E122&"|"&"PLANO DE SAUDE - "&B122&"|"&"C CUSTO - "&LEFT(C122,5)&"|"&"TOTAL: "&F122&"|" -> |PAGTO DOC - SEGURO SAÚDE|PLANO DE SAUDE - SEGURO SAÚDE|C CUSTO - 11012|TOTAL: 15015,12| | M122: =SUM(F122:L122) -> 15015.12 | N122: ="|"&"PAGTO DOC - "&F122&"|"&"DESP - "&B122&"|"&"CENTRO CUSTO - "&C122&"|"&I122&"|"&G122&"|"&#REF!&"|"&J122&"|"&H122&"|"&K122&"|"&L122&"|" -> #REF! | O122: =IF(M122=0,0,IF(E122="SEGURO DE VIDA EM GRUPO","31201003","31201005")) -> 31201005
A123: 101 | B123: SEGURO SAÚDE | C123: 11013 | E123: SEGURO SAÚDE | F123: 7507.56 | K123: ="|"&"PAGTO DOC - "&E123&"|"&"PLANO DE SAUDE - "&B123&"|"&"C CUSTO - "&LEFT(C123,5)&"|"&"TOTAL: "&F123&"|" -> |PAGTO DOC - SEGURO SAÚDE|PLANO DE SAUDE - SEGURO SAÚDE|C CUSTO - 11013|TOTAL: 7507,56| | M123: =SUM(F123:L123) -> 7507.56 | N123: ="|"&"PAGTO DOC - "&F123&"|"&"DESP - "&B123&"|"&"CENTRO CUSTO - "&C123&"|"&I123&"|"&G123&"|"&#REF!&"|"&J123&"|"&H123&"|"&K123&"|"&L123&"|" -> #REF! | O123: =IF(M123=0,0,IF(E123="SEGURO DE VIDA EM GRUPO","31201003","31201005")) -> 31201005
A124: 101 | B124: SEGURO SAÚDE | C124: 13013 | E124: SEGURO SAÚDE | F124: 5005.04 | K124: ="|"&"PAGTO DOC - "&E124&"|"&"PLANO DE SAUDE - "&B124&"|"&"C CUSTO - "&LEFT(C124,5)&"|"&"TOTAL: "&F124&"|" -> |PAGTO DOC - SEGURO SAÚDE|PLANO DE SAUDE - SEGURO SAÚDE|C CUSTO - 13013|TOTAL: 5005,04| | M124: =SUM(F124:L124) -> 5005.04 | N124: ="|"&"PAGTO DOC - "&F124&"|"&"DESP - "&B124&"|"&"CENTRO CUSTO - "&C124&"|"&I124&"|"&G124&"|"&#REF!&"|"&J124&"|"&H124&"|"&K124&"|"&L124&"|" -> #REF! | O124: =IF(M124=0,0,IF(E124="SEGURO DE VIDA EM GRUPO","31201003","31201005")) -> 31201005
A125: 101 | B125: SEGURO SAÚDE | C125: 14051 | E125: SEGURO SAÚDE | F125: 4979.62 | K125: ="|"&"PAGTO DOC - "&E125&"|"&"PLANO DE SAUDE - "&B125&"|"&"C CUSTO - "&LEFT(C125,5)&"|"&"TOTAL: "&F125&"|" -> |PAGTO DOC - SEGURO SAÚDE|PLANO DE SAUDE - SEGURO SAÚDE|C CUSTO - 14051|TOTAL: 4979,62| | M125: =SUM(F125:L125) -> 4979.62 | N125: ="|"&"PAGTO DOC - "&F125&"|"&"DESP - "&B125&"|"&"CENTRO CUSTO - "&C125&"|"&I125&"|"&G125&"|"&#REF!&"|"&J125&"|"&H125&"|"&K125&"|"&L125&"|" -> #REF! | O125: =IF(M125=0,0,IF(E125="SEGURO DE VIDA EM GRUPO","31201003","31201005")) -> 31201005
A126: 101 | B126: SEGURO SAÚDE | C126: 14056 | E126: SEGURO SAÚDE | F126: 2477.1 | K126: ="|"&"PAGTO DOC - "&E126&"|"&"PLANO DE SAUDE - "&B126&"|"&"C CUSTO - "&LEFT(C126,5)&"|"&"TOTAL: "&F126&"|" -> |PAGTO DOC - SEGURO SAÚDE|PLANO DE SAUDE - SEGURO SAÚDE|C CUSTO - 14056|TOTAL: 2477,1| | M126: =SUM(F126:L126) -> 2477.1 | N126: ="|"&"PAGTO DOC - "&F126&"|"&"DESP - "&B126&"|"&"CENTRO CUSTO - "&C126&"|"&I126&"|"&G126&"|"&#REF!&"|"&J126&"|"&H126&"|"&K126&"|"&L126&"|" -> #REF! | O126: =IF(M126=0,0,IF(E126="SEGURO DE VIDA EM GRUPO","31201003","31201005")) -> 31201005
A127: 101 | B127: SEGURO SAÚDE | C127: 15012 | E127: SEGURO SAÚDE | F127: 1238.55 | K127: ="|"&"PAGTO DOC - "&E127&"|"&"PLANO DE SAUDE - "&B127&"|"&"C CUSTO - "&LEFT(C127,5)&"|"&"TOTAL: "&F127&"|" -> |PAGTO DOC - SEGURO SAÚDE|PLANO DE SAUDE - SEGURO SAÚDE|C CUSTO - 15012|TOTAL: 1238,55| | M127: =SUM(F127:L127) -> 1238.55 | N127: ="|"&"PAGTO DOC - "&F127&"|"&"DESP - "&B127&"|"&"CENTRO CUSTO - "&C127&"|"&I127&"|"&G127&"|"&#REF!&"|"&J127&"|"&H127&"|"&K127&"|"&L127&"|" -> #REF! | O127: =IF(M127=0,0,IF(E127="SEGURO DE VIDA EM GRUPO","31201003","31201005")) -> 31201005
A128: 101 | B128: SEGURO SAÚDE | C128: 15050 | E128: SEGURO SAÚDE | F128: 12798.35 | K128: ="|"&"PAGTO DOC - "&E128&"|"&"PLANO DE SAUDE - "&B128&"|"&"C CUSTO - "&LEFT(C128,5)&"|"&"TOTAL: "&F128&"|" -> |PAGTO DOC - SEGURO SAÚDE|PLANO DE SAUDE - SEGURO SAÚDE|C CUSTO - 15050|TOTAL: 12798,35| | M128: =SUM(F128:L128) -> 12798.35 | N128: ="|"&"PAGTO DOC - "&F128&"|"&"DESP - "&B128&"|"&"CENTRO CUSTO - "&C128&"|"&I128&"|"&G128&"|"&#REF!&"|"&J128&"|"&H128&"|"&K128&"|"&L128&"|" -> #REF! | O128: =IF(M128=0,0,IF(E128="SEGURO DE VIDA EM GRUPO","31201003","31201005")) -> 31201005
A129: 101 | B129: SEGURO SAÚDE | C129: 15051 | E129: SEGURO SAÚDE | F129: 6605.6 | K129: ="|"&"PAGTO DOC - "&E129&"|"&"PLANO DE SAUDE - "&B129&"|"&"C CUSTO - "&LEFT(C129,5)&"|"&"TOTAL: "&F129&"|" -> |PAGTO DOC - SEGURO SAÚDE|PLANO DE SAUDE - SEGURO SAÚDE|C CUSTO - 15051|TOTAL: 6605,6| | M129: =SUM(F129:L129) -> 6605.6 | N129: ="|"&"PAGTO DOC - "&F129&"|"&"DESP - "&B129&"|"&"CENTRO CUSTO - "&C129&"|"&I129&"|"&G129&"|"&#REF!&"|"&J129&"|"&H129&"|"&K129&"|"&L129&"|" -> #REF! | O129: =IF(M129=0,0,IF(E129="SEGURO DE VIDA EM GRUPO","31201003","31201005")) -> 31201005
A130: 101 | B130: SEGURO SAÚDE | C130: 15056 | E130: SEGURO SAÚDE | F130: 10734.1 | K130: ="|"&"PAGTO DOC - "&E130&"|"&"PLANO DE SAUDE - "&B130&"|"&"C CUSTO - "&LEFT(C130,5)&"|"&"TOTAL: "&F130&"|" -> |PAGTO DOC - SEGURO SAÚDE|PLANO DE SAUDE - SEGURO SAÚDE|C CUSTO - 15056|TOTAL: 10734,1| | M130: =SUM(F130:L130) -> 10734.1 | N130: ="|"&"PAGTO DOC - "&F130&"|"&"DESP - "&B130&"|"&"CENTRO CUSTO - "&C130&"|"&I130&"|"&G130&"|"&#REF!&"|"&J130&"|"&H130&"|"&K130&"|"&L130&"|" -> #REF! | O130: =IF(M130=0,0,IF(E130="SEGURO DE VIDA EM GRUPO","31201003","31201005")) -> 31201005
A131: 101 | B131: SEGURO SAÚDE | C131: 15058 | E131: SEGURO SAÚDE | F131: 7431.3 | K131: ="|"&"PAGTO DOC - "&E131&"|"&"PLANO DE SAUDE - "&B131&"|"&"C CUSTO - "&LEFT(C131,5)&"|"&"TOTAL: "&F131&"|" -> |PAGTO DOC - SEGURO SAÚDE|PLANO DE SAUDE - SEGURO SAÚDE|C CUSTO - 15058|TOTAL: 7431,3| | M131: =SUM(F131:L131) -> 7431.3 | N131: ="|"&"PAGTO DOC - "&F131&"|"&"DESP - "&B131&"|"&"CENTRO CUSTO - "&C131&"|"&I131&"|"&G131&"|"&#REF!&"|"&J131&"|"&H131&"|"&K131&"|"&L131&"|" -> #REF! | O131: =IF(M131=0,0,IF(E131="SEGURO DE VIDA EM GRUPO","31201003","31201005")) -> 31201005
A132: 101 | B132: SEGURO SAÚDE | C132: 15059 | E132: SEGURO SAÚDE | F132: 7431.3 | K132: ="|"&"PAGTO DOC - "&E132&"|"&"PLANO DE SAUDE - "&B132&"|"&"C CUSTO - "&LEFT(C132,5)&"|"&"TOTAL: "&F132&"|" -> |PAGTO DOC - SEGURO SAÚDE|PLANO DE SAUDE - SEGURO SAÚDE|C CUSTO - 15059|TOTAL: 7431,3| | M132: =SUM(F132:L132) -> 7431.3 | N132: ="|"&"PAGTO DOC - "&F132&"|"&"DESP - "&B132&"|"&"CENTRO CUSTO - "&C132&"|"&I132&"|"&G132&"|"&#REF!&"|"&J132&"|"&H132&"|"&K132&"|"&L132&"|" -> #REF! | O132: =IF(M132=0,0,IF(E132="SEGURO DE VIDA EM GRUPO","31201003","31201005")) -> 31201005
... A134: 101 | B134: SEGURO SAÚDE | C134: 33010 | E134: SEGURO SAÚDE | F134: 10422.93 | K134: ="|"&"PAGTO DOC - "&E134&"|"&"PLANO DE SAUDE - "&B134&"|"&"C CUSTO - "&LEFT(C134,5)&"|"&"TOTAL: "&F134&"|" -> |PAGTO DOC - SEGURO SAÚDE|PLANO DE SAUDE - SEGURO SAÚDE|C CUSTO - 33010|TOTAL: 10422,93| | M134: =SUM(F134:L134) -> 10422.93 | N134: ="|"&"PAGTO DOC - "&F134&"|"&"DESP - "&B134&"|"&"CENTRO CUSTO - "&C134&"|"&I134&"|"&G134&"|"&#REF!&"|"&J134&"|"&H134&"|"&K134&"|"&L134&"|" -> #REF! | O134: =IF(M134=0,0,IF(E134="SEGURO DE VIDA EM GRUPO","31201003","31201005")) -> 31201005
A135: 106 | B135: SEGURO UNIMED | C135: 13013 | F135: 8.04 | K135: ="|"&"PAGTO DOC - "&E135&"|"&"PLANO DE SAUDE - "&B135&"|"&"C CUSTO - "&LEFT(C135,5)&"|"&"TOTAL: "&F135&"|" -> |PAGTO DOC - |PLANO DE SAUDE - SEGURO UNIMED|C CUSTO - 13013|TOTAL: 8,04| | M135: =SUM(F135:L135) -> 8.04 | N135: ="|"&"PAGTO DOC - "&F135&"|"&"DESP - "&B135&"|"&"CENTRO CUSTO - "&C135&"|"&I135&"|"&G135&"|"&#REF!&"|"&J135&"|"&H135&"|"&K135&"|"&L135&"|" -> #REF! | O135: =IF(M135=0,0,IF(E135="SEGURO DE VIDA EM GRUPO","31201003","31201005")) -> 31201005
A136: 106 | B136: SEGURO UNIMED | C136: 32001 | F136: 56.28 | K136: ="|"&"PAGTO DOC - "&E136&"|"&"PLANO DE SAUDE - "&B136&"|"&"C CUSTO - "&LEFT(C136,5)&"|"&"TOTAL: "&F136&"|" -> |PAGTO DOC - |PLANO DE SAUDE - SEGURO UNIMED|C CUSTO - 32001|TOTAL: 56,28| | M136: =SUM(F136:L136) -> 56.28 | N136: ="|"&"PAGTO DOC - "&F136&"|"&"DESP - "&B136&"|"&"CENTRO CUSTO - "&C136&"|"&I136&"|"&G136&"|"&#REF!&"|"&J136&"|"&H136&"|"&K136&"|"&L136&"|" -> #REF! | O136: =IF(M136=0,0,IF(E136="SEGURO DE VIDA EM GRUPO","31201003","31201005")) -> 31201005
A137: 106 | B137: SEGURO UNIMED | C137: 32002 | F137: 209.04 | K137: ="|"&"PAGTO DOC - "&E137&"|"&"PLANO DE SAUDE - "&B137&"|"&"C CUSTO - "&LEFT(C137,5)&"|"&"TOTAL: "&F137&"|" -> |PAGTO DOC - |PLANO DE SAUDE - SEGURO UNIMED|C CUSTO - 32002|TOTAL: 209,04| | M137: =SUM(F137:L137) -> 209.04 | N137: ="|"&"PAGTO DOC - "&F137&"|"&"DESP - "&B137&"|"&"CENTRO CUSTO - "&C137&"|"&I137&"|"&G137&"|"&#REF!&"|"&J137&"|"&H137&"|"&K137&"|"&L137&"|" -> #REF! | O137: =IF(M137=0,0,IF(E137="SEGURO DE VIDA EM GRUPO","31201003","31201005")) -> 31201005
A138: 106 | B138: SEGURO UNIMED | C138: 32003 | F138: 168.84 | K138: ="|"&"PAGTO DOC - "&E138&"|"&"PLANO DE SAUDE - "&B138&"|"&"C CUSTO - "&LEFT(C138,5)&"|"&"TOTAL: "&F138&"|" -> |PAGTO DOC - |PLANO DE SAUDE - SEGURO UNIMED|C CUSTO - 32003|TOTAL: 168,84| | M138: =SUM(F138:L138) -> 168.84 | N138: ="|"&"PAGTO DOC - "&F138&"|"&"DESP - "&B138&"|"&"CENTRO CUSTO - "&C138&"|"&I138&"|"&G138&"|"&#REF!&"|"&J138&"|"&H138&"|"&K138&"|"&L138&"|" -> #REF! | O138: =IF(M138=0,0,IF(E138="SEGURO DE VIDA EM GRUPO","31201003","31201005")) -> 31201005
A139: 106 | B139: SEGURO UNIMED | C139: 32007 | F139: 112.56 | K139: ="|"&"PAGTO DOC - "&E139&"|"&"PLANO DE SAUDE - "&B139&"|"&"C CUSTO - "&LEFT(C139,5)&"|"&"TOTAL: "&F139&"|" -> |PAGTO DOC - |PLANO DE SAUDE - SEGURO UNIMED|C CUSTO - 32007|TOTAL: 112,56| | M139: =SUM(F139:L139) -> 112.56 | N139: ="|"&"PAGTO DOC - "&F139&"|"&"DESP - "&B139&"|"&"CENTRO CUSTO - "&C139&"|"&I139&"|"&G139&"|"&#REF!&"|"&J139&"|"&H139&"|"&K139&"|"&L139&"|" -> #REF! | O139: =IF(M139=0,0,IF(E139="SEGURO DE VIDA EM GRUPO","31201003","31201005")) -> 31201005
A140: 106 | B140: SEGURO UNIMED | C140: 32100 | F140: 24.12 | K140: ="|"&"PAGTO DOC - "&E140&"|"&"PLANO DE SAUDE - "&B140&"|"&"C CUSTO - "&LEFT(C140,5)&"|"&"TOTAL: "&F140&"|" -> |PAGTO DOC - |PLANO DE SAUDE - SEGURO UNIMED|C CUSTO - 32100|TOTAL: 24,12| | M140: =SUM(F140:L140) -> 24.12 | N140: ="|"&"PAGTO DOC - "&F140&"|"&"DESP - "&B140&"|"&"CENTRO CUSTO - "&C140&"|"&I140&"|"&G140&"|"&#REF!&"|"&J140&"|"&H140&"|"&K140&"|"&L140&"|" -> #REF! | O140: =IF(M140=0,0,IF(E140="SEGURO DE VIDA EM GRUPO","31201003","31201005")) -> 31201005
A141: 106 | B141: SEGURO UNIMED | C141: 34001 | F141: 64.32 | K141: ="|"&"PAGTO DOC - "&E141&"|"&"PLANO DE SAUDE - "&B141&"|"&"C CUSTO - "&LEFT(C141,5)&"|"&"TOTAL: "&F141&"|" -> |PAGTO DOC - |PLANO DE SAUDE - SEGURO UNIMED|C CUSTO - 34001|TOTAL: 64,32| | M141: =SUM(F141:L141) -> 64.32 | N141: ="|"&"PAGTO DOC - "&F141&"|"&"DESP - "&B141&"|"&"CENTRO CUSTO - "&C141&"|"&I141&"|"&G141&"|"&#REF!&"|"&J141&"|"&H141&"|"&K141&"|"&L141&"|" -> #REF! | O141: =IF(M141=0,0,IF(E141="SEGURO DE VIDA EM GRUPO","31201003","31201005")) -> 31201005
A142: 106 | B142: SEGURO UNIMED | C142: 15056 | F142: 297.48 | K142: ="|"&"PAGTO DOC - "&E142&"|"&"PLANO DE SAUDE - "&B142&"|"&"C CUSTO - "&LEFT(C142,5)&"|"&"TOTAL: "&F142&"|" -> |PAGTO DOC - |PLANO DE SAUDE - SEGURO UNIMED|C CUSTO - 15056|TOTAL: 297,48| | M142: =SUM(F142:L142) -> 297.48 | N142: ="|"&"PAGTO DOC - "&F142&"|"&"DESP - "&B142&"|"&"CENTRO CUSTO - "&C142&"|"&I142&"|"&G142&"|"&#REF!&"|"&J142&"|"&H142&"|"&K142&"|"&L142&"|" -> #REF! | O142: =IF(M142=0,0,IF(E142="SEGURO DE VIDA EM GRUPO","31201003","31201005")) -> 31201005
A143: 106 | B143: SEGURO UNIMED | C143: 15058 | F143: 176.88 | K143: ="|"&"PAGTO DOC - "&E143&"|"&"PLANO DE SAUDE - "&B143&"|"&"C CUSTO - "&LEFT(C143,5)&"|"&"TOTAL: "&F143&"|" -> |PAGTO DOC - |PLANO DE SAUDE - SEGURO UNIMED|C CUSTO - 15058|TOTAL: 176,88| | M143: =SUM(F143:L143) -> 176.88 | N143: ="|"&"PAGTO DOC - "&F143&"|"&"DESP - "&B143&"|"&"CENTRO CUSTO - "&C143&"|"&I143&"|"&G143&"|"&#REF!&"|"&J143&"|"&H143&"|"&K143&"|"&L143&"|" -> #REF! | O143: =IF(M143=0,0,IF(E143="SEGURO DE VIDA EM GRUPO","31201003","31201005")) -> 31201005
A144: 104 | B144: SEGURO UNIMED | C144: 15059 | F144: 152.76 | K144: ="|"&"PAGTO DOC - "&E144&"|"&"PLANO DE SAUDE - "&B144&"|"&"C CUSTO - "&LEFT(C144,5)&"|"&"TOTAL: "&F144&"|" -> |PAGTO DOC - |PLANO DE SAUDE - SEGURO UNIMED|C CUSTO - 15059|TOTAL: 152,76| | M144: =SUM(F144:L144) -> 152.76 | N144: ="|"&"PAGTO DOC - "&F144&"|"&"DESP - "&B144&"|"&"CENTRO CUSTO - "&C144&"|"&I144&"|"&G144&"|"&#REF!&"|"&J144&"|"&H144&"|"&K144&"|"&L144&"|" -> #REF! | O144: =IF(M144=0,0,IF(E144="SEGURO DE VIDA EM GRUPO","31201003","31201005")) -> 31201005
A145: 104 | B145: SEGURO UNIMED | C145: 22002 | F145: 48.24 | K145: ="|"&"PAGTO DOC - "&E145&"|"&"PLANO DE SAUDE - "&B145&"|"&"C CUSTO - "&LEFT(C145,5)&"|"&"TOTAL: "&F145&"|" -> |PAGTO DOC - |PLANO DE SAUDE - SEGURO UNIMED|C CUSTO - 22002|TOTAL: 48,24| | M145: =SUM(F145:L145) -> 48.24 | N145: ="|"&"PAGTO DOC - "&F145&"|"&"DESP - "&B145&"|"&"CENTRO CUSTO - "&C145&"|"&I145&"|"&G145&"|"&#REF!&"|"&J145&"|"&H145&"|"&K145&"|"&L145&"|" -> #REF! | O145: =IF(M145=0,0,IF(E145="SEGURO DE VIDA EM GRUPO","31201003","31201005")) -> 31201005
A146: 101 | B146: SORRISO ODONTO | C146: 13011 | F146: 213.6 | K146: ="|"&"PAGTO DOC - "&E146&"|"&"PLANO DE SAUDE - "&B146&"|"&"C CUSTO - "&LEFT(C146,5)&"|"&"TOTAL: "&F146&"|" -> |PAGTO DOC - |PLANO DE SAUDE - SORRISO ODONTO|C CUSTO - 13011|TOTAL: 213,6| | M146: =SUM(F146:L146) -> 213.6 | N146: ="|"&"PAGTO DOC - "&F146&"|"&"DESP - "&B146&"|"&"CENTRO CUSTO - "&C146&"|"&I146&"|"&G146&"|"&#REF!&"|"&J146&"|"&H146&"|"&K146&"|"&L146&"|" -> #REF! | O146: =IF(M146=0,0,IF(E146="SEGURO DE VIDA EM GRUPO","31201003","31201005")) -> 31201005
... A167: 101 | B167: SORRISO ODONTO | C167: 55030 | F167: 75 | K167: ="|"&"PAGTO DOC - "&E167&"|"&"PLANO DE SAUDE - "&B167&"|"&"C CUSTO - "&LEFT(C167,5)&"|"&"TOTAL: "&F167&"|" -> |PAGTO DOC - |PLANO DE SAUDE - SORRISO ODONTO|C CUSTO - 55030|TOTAL: 75| | M167: =SUM(F167:L167) -> 75 | N167: ="|"&"PAGTO DOC - "&F167&"|"&"DESP - "&B167&"|"&"CENTRO CUSTO - "&C167&"|"&I167&"|"&G167&"|"&#REF!&"|"&J167&"|"&H167&"|"&K167&"|"&L167&"|" -> #REF! | O167: =IF(M167=0,0,IF(E167="SEGURO DE VIDA EM GRUPO","31201003","31201005")) -> 31201005
A168: 101 | B168: UNIMED ODONTO | C168: 15056 | F168: 43.65 | K168: ="|"&"PAGTO DOC - "&E168&"|"&"PLANO DE SAUDE - "&B168&"|"&"C CUSTO - "&LEFT(C168,5)&"|"&"TOTAL: "&F168&"|" -> |PAGTO DOC - |PLANO DE SAUDE - UNIMED ODONTO|C CUSTO - 15056|TOTAL: 43,65| | M168: =SUM(F168:L168) -> 43.65 | N168: ="|"&"PAGTO DOC - "&F168&"|"&"DESP - "&B168&"|"&"CENTRO CUSTO - "&C168&"|"&I168&"|"&G168&"|"&#REF!&"|"&J168&"|"&H168&"|"&K168&"|"&L168&"|" -> #REF! | O168: =IF(M168=0,0,IF(E168="SEGURO DE VIDA EM GRUPO","31201003","31201005")) -> 31201005
A169: 101 | B169: UNIMED ODONTO | C169: 15058 | F169: -14.55 | K169: ="|"&"PAGTO DOC - "&E169&"|"&"PLANO DE SAUDE - "&B169&"|"&"C CUSTO - "&LEFT(C169,5)&"|"&"TOTAL: "&F169&"|" -> |PAGTO DOC - |PLANO DE SAUDE - UNIMED ODONTO|C CUSTO - 15058|TOTAL: -14,55| | M169: =SUM(F169:L169) -> -14.55 | N169: ="|"&"PAGTO DOC - "&F169&"|"&"DESP - "&B169&"|"&"CENTRO CUSTO - "&C169&"|"&I169&"|"&G169&"|"&#REF!&"|"&J169&"|"&H169&"|"&K169&"|"&L169&"|" -> #REF! | O169: =IF(M169=0,0,IF(E169="SEGURO DE VIDA EM GRUPO","31201003","31201005")) -> 31201005
A170: 101 | B170: UNIMED ODONTO | C170: 13012 | F170: 43.65 | K170: ="|"&"PAGTO DOC - "&E170&"|"&"PLANO DE SAUDE - "&B170&"|"&"C CUSTO - "&LEFT(C170,5)&"|"&"TOTAL: "&F170&"|" -> |PAGTO DOC - |PLANO DE SAUDE - UNIMED ODONTO|C CUSTO - 13012|TOTAL: 43,65| | M170: =SUM(F170:L170) -> 43.65 | N170: ="|"&"PAGTO DOC - "&F170&"|"&"DESP - "&B170&"|"&"CENTRO CUSTO - "&C170&"|"&I170&"|"&G170&"|"&#REF!&"|"&J170&"|"&H170&"|"&K170&"|"&L170&"|" -> #REF! | O170: =IF(M170=0,0,IF(E170="SEGURO DE VIDA EM GRUPO","31201003","31201005")) -> 31201005
A171: 101 | B171: UNIMED ODONTO | C171: 13014 | F171: 43.65 | K171: ="|"&"PAGTO DOC - "&E171&"|"&"PLANO DE SAUDE - "&B171&"|"&"C CUSTO - "&LEFT(C171,5)&"|"&"TOTAL: "&F171&"|" -> |PAGTO DOC - |PLANO DE SAUDE - UNIMED ODONTO|C CUSTO - 13014|TOTAL: 43,65| | M171: =SUM(F171:L171) -> 43.65 | N171: ="|"&"PAGTO DOC - "&F171&"|"&"DESP - "&B171&"|"&"CENTRO CUSTO - "&C171&"|"&I171&"|"&G171&"|"&#REF!&"|"&J171&"|"&H171&"|"&K171&"|"&L171&"|" -> #REF! | O171: =IF(M171=0,0,IF(E171="SEGURO DE VIDA EM GRUPO","31201003","31201005")) -> 31201005
A172: 101 | B172: UNIMED ODONTO | C172: 13016 | F172: 43.65 | K172: ="|"&"PAGTO DOC - "&E172&"|"&"PLANO DE SAUDE - "&B172&"|"&"C CUSTO - "&LEFT(C172,5)&"|"&"TOTAL: "&F172&"|" -> |PAGTO DOC - |PLANO DE SAUDE - UNIMED ODONTO|C CUSTO - 13016|TOTAL: 43,65| | M172: =SUM(F172:L172) -> 43.65 | N172: ="|"&"PAGTO DOC - "&F172&"|"&"DESP - "&B172&"|"&"CENTRO CUSTO - "&C172&"|"&I172&"|"&G172&"|"&#REF!&"|"&J172&"|"&H172&"|"&K172&"|"&L172&"|" -> #REF! | O172: =IF(M172=0,0,IF(E172="SEGURO DE VIDA EM GRUPO","31201003","31201005")) -> 31201005
A173: 101 | B173: UNIMED ODONTO | C173: 13018 | F173: 72.75 | K173: ="|"&"PAGTO DOC - "&E173&"|"&"PLANO DE SAUDE - "&B173&"|"&"C CUSTO - "&LEFT(C173,5)&"|"&"TOTAL: "&F173&"|" -> |PAGTO DOC - |PLANO DE SAUDE - UNIMED ODONTO|C CUSTO - 13018|TOTAL: 72,75| | M173: =SUM(F173:L173) -> 72.75 | N173: ="|"&"PAGTO DOC - "&F173&"|"&"DESP - "&B173&"|"&"CENTRO CUSTO - "&C173&"|"&I173&"|"&G173&"|"&#REF!&"|"&J173&"|"&H173&"|"&K173&"|"&L173&"|" -> #REF! | O173: =IF(M173=0,0,IF(E173="SEGURO DE VIDA EM GRUPO","31201003","31201005")) -> 31201005
A174: 101 | B174: UNIMED ODONTO | C174: 14012 | F174: 14.55 | K174: ="|"&"PAGTO DOC - "&E174&"|"&"PLANO DE SAUDE - "&B174&"|"&"C CUSTO - "&LEFT(C174,5)&"|"&"TOTAL: "&F174&"|" -> |PAGTO DOC - |PLANO DE SAUDE - UNIMED ODONTO|C CUSTO - 14012|TOTAL: 14,55| | M174: =SUM(F174:L174) -> 14.55 | N174: ="|"&"PAGTO DOC - "&F174&"|"&"DESP - "&B174&"|"&"CENTRO CUSTO - "&C174&"|"&I174&"|"&G174&"|"&#REF!&"|"&J174&"|"&H174&"|"&K174&"|"&L174&"|" -> #REF! | O174: =IF(M174=0,0,IF(E174="SEGURO DE VIDA EM GRUPO","31201003","31201005")) -> 31201005
A175: 101 | B175: UNIMED ODONTO | C175: 14056 | F175: 101.85 | K175: ="|"&"PAGTO DOC - "&E175&"|"&"PLANO DE SAUDE - "&B175&"|"&"C CUSTO - "&LEFT(C175,5)&"|"&"TOTAL: "&F175&"|" -> |PAGTO DOC - |PLANO DE SAUDE - UNIMED ODONTO|C CUSTO - 14056|TOTAL: 101,85| | M175: =SUM(F175:L175) -> 101.85 | N175: ="|"&"PAGTO DOC - "&F175&"|"&"DESP - "&B175&"|"&"CENTRO CUSTO - "&C175&"|"&I175&"|"&G175&"|"&#REF!&"|"&J175&"|"&H175&"|"&K175&"|"&L175&"|" -> #REF! | O175: =IF(M175=0,0,IF(E175="SEGURO DE VIDA EM GRUPO","31201003","31201005")) -> 31201005
A176: 101 | B176: UNIMED ODONTO | C176: 15012 | F176: 14.55 | K176: ="|"&"PAGTO DOC - "&E176&"|"&"PLANO DE SAUDE - "&B176&"|"&"C CUSTO - "&LEFT(C176,5)&"|"&"TOTAL: "&F176&"|" -> |PAGTO DOC - |PLANO DE SAUDE - UNIMED ODONTO|C CUSTO - 15012|TOTAL: 14,55| | M176: =SUM(F176:L176) -> 14.55 | N176: ="|"&"PAGTO DOC - "&F176&"|"&"DESP - "&B176&"|"&"CENTRO CUSTO - "&C176&"|"&I176&"|"&G176&"|"&#REF!&"|"&J176&"|"&H176&"|"&K176&"|"&L176&"|" -> #REF! | O176: =IF(M176=0,0,IF(E176="SEGURO DE VIDA EM GRUPO","31201003","31201005")) -> 31201005
A177: 101 | B177: UNIMED ODONTO | C177: 15050 | F177: 421.95 | K177: ="|"&"PAGTO DOC - "&E177&"|"&"PLANO DE SAUDE - "&B177&"|"&"C CUSTO - "&LEFT(C177,5)&"|"&"TOTAL: "&F177&"|" -> |PAGTO DOC - |PLANO DE SAUDE - UNIMED ODONTO|C CUSTO - 15050|TOTAL: 421,95| | M177: =SUM(F177:L177) -> 421.95 | N177: ="|"&"PAGTO DOC - "&F177&"|"&"DESP - "&B177&"|"&"CENTRO CUSTO - "&C177&"|"&I177&"|"&G177&"|"&#REF!&"|"&J177&"|"&H177&"|"&K177&"|"&L177&"|" -> #REF! | O177: =IF(M177=0,0,IF(E177="SEGURO DE VIDA EM GRUPO","31201003","31201005")) -> 31201005
A178: 101 | B178: UNIMED ODONTO | C178: 15051 | F178: 247.35 | K178: ="|"&"PAGTO DOC - "&E178&"|"&"PLANO DE SAUDE - "&B178&"|"&"C CUSTO - "&LEFT(C178,5)&"|"&"TOTAL: "&F178&"|" -> |PAGTO DOC - |PLANO DE SAUDE - UNIMED ODONTO|C CUSTO - 15051|TOTAL: 247,35| | M178: =SUM(F178:L178) -> 247.35 | N178: ="|"&"PAGTO DOC - "&F178&"|"&"DESP - "&B178&"|"&"CENTRO CUSTO - "&C178&"|"&I178&"|"&G178&"|"&#REF!&"|"&J178&"|"&H178&"|"&K178&"|"&L178&"|" -> #REF! | O178: =IF(M178=0,0,IF(E178="SEGURO DE VIDA EM GRUPO","31201003","31201005")) -> 31201005
A179: 101 | B179: UNIMED ODONTO | C179: 15056 | F179: 349.2 | K179: ="|"&"PAGTO DOC - "&E179&"|"&"PLANO DE SAUDE - "&B179&"|"&"C CUSTO - "&LEFT(C179,5)&"|"&"TOTAL: "&F179&"|" -> |PAGTO DOC - |PLANO DE SAUDE - UNIMED ODONTO|C CUSTO - 15056|TOTAL: 349,2| | M179: =SUM(F179:L179) -> 349.2 | N179: ="|"&"PAGTO DOC - "&F179&"|"&"DESP - "&B179&"|"&"CENTRO CUSTO - "&C179&"|"&I179&"|"&G179&"|"&#REF!&"|"&J179&"|"&H179&"|"&K179&"|"&L179&"|" -> #REF! | O179: =IF(M179=0,0,IF(E179="SEGURO DE VIDA EM GRUPO","31201003","31201005")) -> 31201005
A180: 101 | B180: UNIMED ODONTO | C180: 15058 | F180: 232.8 | K180: ="|"&"PAGTO DOC - "&E180&"|"&"PLANO DE SAUDE - "&B180&"|"&"C CUSTO - "&LEFT(C180,5)&"|"&"TOTAL: "&F180&"|" -> |PAGTO DOC - |PLANO DE SAUDE - UNIMED ODONTO|C CUSTO - 15058|TOTAL: 232,8| | M180: =SUM(F180:L180) -> 232.8 | N180: ="|"&"PAGTO DOC - "&F180&"|"&"DESP - "&B180&"|"&"CENTRO CUSTO - "&C180&"|"&I180&"|"&G180&"|"&#REF!&"|"&J180&"|"&H180&"|"&K180&"|"&L180&"|" -> #REF! | O180: =IF(M180=0,0,IF(E180="SEGURO DE VIDA EM GRUPO","31201003","31201005")) -> 31201005
...

Sheet Consolidado
F1: =SUM(F3:F243) -> 291294.1
A2: ESTAB | B2: TIPO DE DESP: | C2: CCUSTO | D2: DATA | E2: Nº DOC | F2: MENSAL | G2: EXAME | H2: DESCON | I2: REPRES | J2: INSCRI | K2: X | L2: Z | M2: TOTAL | N2: CONTA
A3: 101 | B3: UNIMED ITUVERAVA | C3: 13021 | E3: UNIMED ITUVERAVA | F3: 546.96 | M3: =F3 -> 546.96 | N3: =IF(B3="SEGURO DE VIDA EM GRUPO","31201003","31201005") -> 31201005
A4: 101 | B4: UNIMED ITUVERAVA | C4: 14051 | E4: UNIMED ITUVERAVA | F4: 2161.26 | M4: =F4 -> 2161.26 | N4: =IF(B4="SEGURO DE VIDA EM GRUPO","31201003","31201005") -> 31201005
A5: 101 | B5: UNIMED ITUVERAVA | C5: 14058 | E5: UNIMED ITUVERAVA | F5: 2014.32 | M5: =F5 -> 2014.32 | N5: =IF(B5="SEGURO DE VIDA EM GRUPO","31201003","31201005") -> 31201005
A6: 101 | B6: UNIMED ITUVERAVA | C6: 31060 | E6: UNIMED ITUVERAVA | F6: 546.96 | M6: =F6 -> 546.96 | N6: =IF(B6="SEGURO DE VIDA EM GRUPO","31201003","31201005") -> 31201005
A7: 101 | B7: UNIMED ITUVERAVA | C7: 31070 | E7: UNIMED ITUVERAVA | F7: 546.96 | M7: =F7 -> 546.96 | N7: =IF(B7="SEGURO DE VIDA EM GRUPO","31201003","31201005") -> 31201005
A8: 101 | B8: UNIMED ITUVERAVA | C8: 31114 | E8: UNIMED ITUVERAVA | F8: 2417.14 | M8: =F8 -> 2417.14 | N8: =IF(B8="SEGURO DE VIDA EM GRUPO","31201003","31201005") -> 31201005
A9: 101 | B9: UNIMED ITUVERAVA | C9: 11012 | E9: UNIMED ITUVERAVA | F9: 1093.92 | M9: =F9 -> 1093.92 | N9: =IF(B9="SEGURO DE VIDA EM GRUPO","31201003","31201005") -> 31201005
A10: 101 | B10: UNIMED ITUVERAVA | C10: 13011 | E10: UNIMED ITUVERAVA | F10: 1323.22 | M10: =F10 -> 1323.22 | N10: =IF(B10="SEGURO DE VIDA EM GRUPO","31201003","31201005") -> 31201005
A11: 101 | B11: UNIMED ITUVERAVA | C11: 13012 | E11: UNIMED ITUVERAVA | F11: 1005.56 | M11: =F11 -> 1005.56 | N11: =IF(B11="SEGURO DE VIDA EM GRUPO","31201003","31201005") -> 31201005
A12: 101 | B12: UNIMED ITUVERAVA | C12: 13013 | E12: UNIMED ITUVERAVA | F12: 8067.44 | M12: =F12 -> 8067.44 | N12: =IF(B12="SEGURO DE VIDA EM GRUPO","31201003","31201005") -> 31201005
A13: 101 | B13: UNIMED ITUVERAVA | C13: 13014 | E13: UNIMED ITUVERAVA | F13: 2187.84 | M13: =F13 -> 2187.84 | N13: =IF(B13="SEGURO DE VIDA EM GRUPO","31201003","31201005") -> 31201005
A14: 101 | B14: UNIMED ITUVERAVA | C14: 13016 | E14: UNIMED ITUVERAVA | F14: 1464.16 | M14: =F14 -> 1464.16 | N14: =IF(B14="SEGURO DE VIDA EM GRUPO","31201003","31201005") -> 31201005
A15: 101 | B15: UNIMED ITUVERAVA | C15: 13017 | E15: UNIMED ITUVERAVA | F15: 1640.88 | M15: =F15 -> 1640.88 | N15: =IF(B15="SEGURO DE VIDA EM GRUPO","31201003","31201005") -> 31201005
A16: 101 | B16: UNIMED ITUVERAVA | C16: 13018 | E16: UNIMED ITUVERAVA | F16: 1005.56 | M16: =F16 -> 1005.56 | N16: =IF(B16="SEGURO DE VIDA EM GRUPO","31201003","31201005") -> 31201005
A17: 101 | B17: UNIMED ITUVERAVA | C17: 13019 | E17: UNIMED ITUVERAVA | F17: 776.26 | M17: =F17 -> 776.26 | N17: =IF(B17="SEGURO DE VIDA EM GRUPO","31201003","31201005") -> 31201005
A18: 101 | B18: UNIMED ITUVERAVA | C18: 13021 | E18: UNIMED ITUVERAVA | F18: 2646.44 | M18: =F18 -> 2646.44 | N18: =IF(B18="SEGURO DE VIDA EM GRUPO","31201003","31201005") -> 31201005
A19: 101 | B19: UNIMED ITUVERAVA | C19: 14012 | E19: UNIMED ITUVERAVA | F19: 1870.18 | M19: =F19 -> 1870.18 | N19: =IF(B19="SEGURO DE VIDA EM GRUPO","31201003","31201005") -> 31201005
A20: 101 | B20: UNIMED ITUVERAVA | C20: 14051 | E20: UNIMED ITUVERAVA | F20: 2707.02 | M20: =F20 -> 2707.02 | N20: =IF(B20="SEGURO DE VIDA EM GRUPO","31201003","31201005") -> 31201005
... A41: 101 | B41: UNIMED ITUVERAVA | C41: 55030 | E41: UNIMED ITUVERAVA | F41: 546.96 | M41: =F41 -> 546.96 | N41: =IF(B41="SEGURO DE VIDA EM GRUPO","31201003","31201005") -> 31201005
A42: 101 | B42: UNIMED ITUVERAVA | C42: 21012 | E42: UNIMED ITUVERAVA | F42: 229.3 | M42: =F42 -> 229.3 | N42: =IF(B42="SEGURO DE VIDA EM GRUPO","31201003","31201005") -> 31201005
A43: 101 | B43: UNIMED ITUVERAVA | C43: 31090 | E43: UNIMED ITUVERAVA | F43: 546.96 | M43: =F43 -> 546.96 | N43: =IF(B43="SEGURO DE VIDA EM GRUPO","31201003","31201005") -> 31201005
A44: 101 | B44: UNIMED ITUVERAVA | C44: 13016 | E44: UNIMED ITUVERAVA | F44: 229.3 | M44: =F44 -> 229.3 | N44: =IF(B44="SEGURO DE VIDA EM GRUPO","31201003","31201005") -> 31201005
A45: 101 | B45: UNIMED ITUVERAVA | C45: 33050 | E45: UNIMED ITUVERAVA | F45: 546.96 | M45: =F45 -> 546.96 | N45: =IF(B45="SEGURO DE VIDA EM GRUPO","31201003","31201005") -> 31201005
A46: 101 | B46: UNIMED ITUVERAVA | C46: 21011 | E46: UNIMED ITUVERAVA | F46: 229.3 | M46: =F46 -> 229.3 | N46: =IF(B46="SEGURO DE VIDA EM GRUPO","31201003","31201005") -> 31201005
A48: 101 | B48: SEGURO DE VIDA EM GRUPO | C48: 11011 | E48: SEGURO DE VIDA EM GRUPO | F48: 74.15 | M48: =F48 -> 74.15 | N48: =IF(B48="SEGURO DE VIDA EM GRUPO","31201003","31201005") -> 31201003
A49: 101 | B49: SEGURO DE VIDA EM GRUPO | C49: 13013 | E49: SEGURO DE VIDA EM GRUPO | F49: 8.04 | M49: =F49 -> 8.04 | N49: =IF(B49="SEGURO DE VIDA EM GRUPO","31201003","31201005") -> 31201003
A50: 101 | B50: SEGURO DE VIDA EM GRUPO | C50: 13014 | E50: SEGURO DE VIDA EM GRUPO | F50: 74.15 | M50: =F50 -> 74.15 | N50: =IF(B50="SEGURO DE VIDA EM GRUPO","31201003","31201005") -> 31201003
A51: 101 | B51: SEGURO DE VIDA EM GRUPO | C51: 14050 | E51: SEGURO DE VIDA EM GRUPO | F51: 72.36 | M51: =F51 -> 72.36 | N51: =IF(B51="SEGURO DE VIDA EM GRUPO","31201003","31201005") -> 31201003
A52: 101 | B52: SEGURO DE VIDA EM GRUPO | C52: 14051 | E52: SEGURO DE VIDA EM GRUPO | F52: 201 | M52: =F52 -> 201 | N52: =IF(B52="SEGURO DE VIDA EM GRUPO","31201003","31201005") -> 31201003
A53: 101 | B53: SEGURO DE VIDA EM GRUPO | C53: 14052 | E53: SEGURO DE VIDA EM GRUPO | F53: 88.44 | M53: =F53 -> 88.44 | N53: =IF(B53="SEGURO DE VIDA EM GRUPO","31201003","31201005") -> 31201003
A54: 101 | B54: SEGURO DE VIDA EM GRUPO | C54: 14054 | E54: SEGURO DE VIDA EM GRUPO | F54: 90.23 | M54: =F54 -> 90.23 | N54: =IF(B54="SEGURO DE VIDA EM GRUPO","31201003","31201005") -> 31201003
... A65: 101 | B65: SEGURO DE VIDA EM GRUPO | C65: 31200 | E65: SEGURO DE VIDA EM GRUPO | F65: 8.04 | M65: =F65 -> 8.04 | N65: =IF(B65="SEGURO DE VIDA EM GRUPO","31201003","31201005") -> 31201003
A66: 101 | B66: SEGURO DE VIDA EM GRUPO | C66: 11011 | E66: SEGURO DE VIDA EM GRUPO | F66: 230.49 | M66: =F66 -> 230.49 | N66: =IF(B66="SEGURO DE VIDA EM GRUPO","31201003","31201005") -> 31201003
A67: 101 | B67: SEGURO DE VIDA EM GRUPO | C67: 11012 | E67: SEGURO DE VIDA EM GRUPO | F67: 90.23 | M67: =F67 -> 90.23 | N67: =IF(B67="SEGURO DE VIDA EM GRUPO","31201003","31201005") -> 31201003
A68: 101 | B68: SEGURO DE VIDA EM GRUPO | C68: 11013 | E68: SEGURO DE VIDA EM GRUPO | F68: 74.15 | M68: =F68 -> 74.15 | N68: =IF(B68="SEGURO DE VIDA EM GRUPO","31201003","31201005") -> 31201003
A69: 101 | B69: SEGURO DE VIDA EM GRUPO | C69: 13011 | E69: SEGURO DE VIDA EM GRUPO | F69: 64.32 | M69: =F69 -> 64.32 | N69: =IF(B69="SEGURO DE VIDA EM GRUPO","31201003","31201005") -> 31201003
A70: 101 | B70: SEGURO DE VIDA EM GRUPO | C70: 13012 | E70: SEGURO DE VIDA EM GRUPO | F70: 16.08 | M70: =F70 -> 16.08 | N70: =IF(B70="SEGURO DE VIDA EM GRUPO","31201003","31201005") -> 31201003
A71: 101 | B71: SEGURO DE VIDA EM GRUPO | C71: 13013 | E71: SEGURO DE VIDA EM GRUPO | F71: 128.33 | M71: =F71 -> 128.33 | N71: =IF(B71="SEGURO DE VIDA EM GRUPO","31201003","31201005") -> 31201003
A72: 101 | B72: SEGURO DE VIDA EM GRUPO | C72: 13014 | E72: SEGURO DE VIDA EM GRUPO | F72: 40.2 | M72: =F72 -> 40.2 | N72: =IF(B72="SEGURO DE VIDA EM GRUPO","31201003","31201005") -> 31201003
A73: 101 | B73: SEGURO DE VIDA EM GRUPO | C73: 13016 | E73: SEGURO DE VIDA EM GRUPO | F73: 40.2 | M73: =F73 -> 40.2 | N73: =IF(B73="SEGURO DE VIDA EM GRUPO","31201003","31201005") -> 31201003
A74: 101 | B74: SEGURO DE VIDA EM GRUPO | C74: 13017 | E74: SEGURO DE VIDA EM GRUPO | F74: 32.16 | M74: =F74 -> 32.16 | N74: =IF(B74="SEGURO DE VIDA EM GRUPO","31201003","31201005") -> 31201003
A75: 101 | B75: SEGURO DE VIDA EM GRUPO | C75: 13018 | E75: SEGURO DE VIDA EM GRUPO | F75: 24.12 | M75: =F75 -> 24.12 | N75: =IF(B75="SEGURO DE VIDA EM GRUPO","31201003","31201005") -> 31201003
A76: 101 | B76: SEGURO DE VIDA EM GRUPO | C76: 13019 | E76: SEGURO DE VIDA EM GRUPO | F76: 24.12 | M76: =F76 -> 24.12 | N76: =IF(B76="SEGURO DE VIDA EM GRUPO","31201003","31201005") -> 31201003
A77: 101 | B77: SEGURO DE VIDA EM GRUPO | C77: 13021 | E77: SEGURO DE VIDA EM GRUPO | F77: 64.32 | M77: =F77 -> 64.32 | N77: =IF(B77="SEGURO DE VIDA EM GRUPO","31201003","31201005") -> 31201003
... A107: 101 | B107: SEGURO DE VIDA EM GRUPO | C107: 55030 | E107: SEGURO DE VIDA EM GRUPO | F107: 16.08 | M107: =F107 -> 16.08 | N107: =IF(B107="SEGURO DE VIDA EM GRUPO","31201003","31201005") -> 31201003
A108: 101 | B108: SEGURO DE VIDA EM GRUPO | C108: 31090 | E108: SEGURO DE VIDA EM GRUPO | F108: 8.04 | M108: =F108 -> 8.04 | N108: =IF(B108="SEGURO DE VIDA EM GRUPO","31201003","31201005") -> 31201003
A109: 101 | B109: SEGURO DE VIDA EM GRUPO | C109: 31116 | E109: SEGURO DE VIDA EM GRUPO | F109: 16.08 | M109: =F109 -> 16.08 | N109: =IF(B109="SEGURO DE VIDA EM GRUPO","31201003","31201005") -> 31201003
A110: 101 | B110: SEGURO DE VIDA EM GRUPO | C110: 33050 | E110: SEGURO DE VIDA EM GRUPO | F110: 16.08 | M110: =F110 -> 16.08 | N110: =IF(B110="SEGURO DE VIDA EM GRUPO","31201003","31201005") -> 31201003
A111: 101 | B111: SEGURO DE VIDA EM GRUPO | C111: 14012 | E111: SEGURO DE VIDA EM GRUPO | F111: 16.08 | M111: =F111 -> 16.08 | N111: =IF(B111="SEGURO DE VIDA EM GRUPO","31201003","31201005") -> 31201003
A112: 101 | B112: SEGURO DE VIDA EM GRUPO | C112: 21012 | E112: SEGURO DE VIDA EM GRUPO | F112: 8.04 | M112: =F112 -> 8.04 | N112: =IF(B112="SEGURO DE VIDA EM GRUPO","31201003","31201005") -> 31201003
A113: 101 | B113: SEGURO DE VIDA EM GRUPO | C113: 13016 | E113: SEGURO DE VIDA EM GRUPO | F113: 8.04 | M113: =F113 -> 8.04 | N113: =IF(B113="SEGURO DE VIDA EM GRUPO","31201003","31201005") -> 31201003
A114: 101 | B114: SEGURO DE VIDA EM GRUPO | C114: 13021 | E114: SEGURO DE VIDA EM GRUPO | F114: 8.04 | M114: =F114 -> 8.04 | N114: =IF(B114="SEGURO DE VIDA EM GRUPO","31201003","31201005") -> 31201003
A115: 101 | B115: SEGURO DE VIDA EM GRUPO | C115: 21011 | E115: SEGURO DE VIDA EM GRUPO | F115: 8.04 | M115: =F115 -> 8.04 | N115: =IF(B115="SEGURO DE VIDA EM GRUPO","31201003","31201005") -> 31201003
A116: 101 | B116: SEGURO DE VIDA EM GRUPO | C116: 33010 | E116: SEGURO DE VIDA EM GRUPO | F116: 8.04 | M116: =F116 -> 8.04 | N116: =IF(B116="SEGURO DE VIDA EM GRUPO","31201003","31201005") -> 31201003
A118: 101 | B118: SEGURO SAÚDE | C118: 13014 | E118: SEGURO SAÚDE | F118: 2502.52 | M118: =F118 -> 2502.52 | N118: =IF(B118="SEGURO DE VIDA EM GRUPO","31201003","31201005") -> 31201005
A119: 101 | B119: SEGURO SAÚDE | C119: 14050 | E119: SEGURO SAÚDE | F119: 1238.55 | M119: =F119 -> 1238.55 | N119: =IF(B119="SEGURO DE VIDA EM GRUPO","31201003","31201005") -> 31201005
A120: 101 | B120: SEGURO SAÚDE | C120: 15012 | E120: SEGURO SAÚDE | F120: 2502.52 | M120: =F120 -> 2502.52 | N120: =IF(B120="SEGURO DE VIDA EM GRUPO","31201003","31201005") -> 31201005
A121: 101 | B121: SEGURO SAÚDE | C121: 15056 | E121: SEGURO SAÚDE | F121: 1238.55 | M121: =F121 -> 1238.55 | N121: =IF(B121="SEGURO DE VIDA EM GRUPO","31201003","31201005") -> 31201005
A122: 101 | B122: SEGURO SAÚDE | C122: 11011 | E122: SEGURO SAÚDE | F122: 33358.46 | M122: =F122 -> 33358.46 | N122: =IF(B122="SEGURO DE VIDA EM GRUPO","31201003","31201005") -> 31201005
A123: 101 | B123: SEGURO SAÚDE | C123: 11012 | E123: SEGURO SAÚDE | F123: 15015.12 | M123: =F123 -> 15015.12 | N123: =IF(B123="SEGURO DE VIDA EM GRUPO","31201003","31201005") -> 31201005
A124: 101 | B124: SEGURO SAÚDE | C124: 11013 | E124: SEGURO SAÚDE | F124: 7507.56 | M124: =F124 -> 7507.56 | N124: =IF(B124="SEGURO DE VIDA EM GRUPO","31201003","31201005") -> 31201005
A125: 101 | B125: SEGURO SAÚDE | C125: 13013 | E125: SEGURO SAÚDE | F125: 5005.04 | M125: =F125 -> 5005.04 | N125: =IF(B125="SEGURO DE VIDA EM GRUPO","31201003","31201005") -> 31201005
A126: 101 | B126: SEGURO SAÚDE | C126: 14051 | E126: SEGURO SAÚDE | F126: 4979.62 | M126: =F126 -> 4979.62 | N126: =IF(B126="SEGURO DE VIDA EM GRUPO","31201003","31201005") -> 31201005
A127: 101 | B127: SEGURO SAÚDE | C127: 14056 | E127: SEGURO SAÚDE | F127: 2477.1 | M127: =F127 -> 2477.1 | N127: =IF(B127="SEGURO DE VIDA EM GRUPO","31201003","31201005") -> 31201005
A128: 101 | B128: SEGURO SAÚDE | C128: 15012 | E128: SEGURO SAÚDE | F128: 1238.55 | M128: =F128 -> 1238.55 | N128: =IF(B128="SEGURO DE VIDA EM GRUPO","31201003","31201005") -> 31201005
A129: 101 | B129: SEGURO SAÚDE | C129: 15050 | E129: SEGURO SAÚDE | F129: 12798.35 | M129: =F129 -> 12798.35 | N129: =IF(B129="SEGURO DE VIDA EM GRUPO","31201003","31201005") -> 31201005
A130: 101 | B130: SEGURO SAÚDE | C130: 15051 | E130: SEGURO SAÚDE | F130: 6605.6 | M130: =F130 -> 6605.6 | N130: =IF(B130="SEGURO DE VIDA EM GRUPO","31201003","31201005") -> 31201005
A131: 101 | B131: SEGURO SAÚDE | C131: 15056 | E131: SEGURO SAÚDE | F131: 10734.1 | M131: =F131 -> 10734.1 | N131: =IF(B131="SEGURO DE VIDA EM GRUPO","31201003","31201005") -> 31201005
A132: 101 | B132: SEGURO SAÚDE | C132: 15058 | E132: SEGURO SAÚDE | F132: 7431.3 | M132: =F132 -> 7431.3 | N132: =IF(B132="SEGURO DE VIDA EM GRUPO","31201003","31201005") -> 31201005
A133: 101 | B133: SEGURO SAÚDE | C133: 15059 | E133: SEGURO SAÚDE | F133: 7431.3 | M133: =F133 -> 7431.3 | N133: =IF(B133="SEGURO DE VIDA EM GRUPO","31201003","31201005") -> 31201005
... A135: 101 | B135: SEGURO SAÚDE | C135: 33010 | E135: SEGURO SAÚDE | F135: 10422.93 | M135: =F135 -> 10422.93 | N135: =IF(B135="SEGURO DE VIDA EM GRUPO","31201003","31201005") -> 31201005
A137: 106 | B137: SEGURO UNIMED | C137: 13013 | F137: 8.04 | M137: =F137 -> 8.04 | N137: =IF(B137="SEGURO DE VIDA EM GRUPO","31201003","31201005") -> 31201005
A138: 106 | B138: SEGURO UNIMED | C138: 32001 | F138: 56.28 | M138: =F138 -> 56.28 | N138: =IF(B138="SEGURO DE VIDA EM GRUPO","31201003","31201005") -> 31201005
A139: 106 | B139: SEGURO UNIMED | C139: 32002 | F139: 209.04 | M139: =F139 -> 209.04 | N139: =IF(B139="SEGURO DE VIDA EM GRUPO","31201003","31201005") -> 31201005
A140: 106 | B140: SEGURO UNIMED | C140: 32003 | F140: 168.84 | M140: =F140 -> 168.84 | N140: =IF(B140="SEGURO DE VIDA EM GRUPO","31201003","31201005") -> 31201005
A141: 106 | B141: SEGURO UNIMED | C141: 32007 | F141: 112.56 | M141: =F141 -> 112.56 | N141: =IF(B141="SEGURO DE VIDA EM GRUPO","31201003","31201005") -> 31201005
A142: 106 | B142: SEGURO UNIMED | C142: 32100 | F142: 24.12 | M142: =F142 -> 24.12 | N142: =IF(B142="SEGURO DE VIDA EM GRUPO","31201003","31201005") -> 31201005
A143: 106 | B143: SEGURO UNIMED | C143: 34001 | F143: 64.32 | M143: =F143 -> 64.32 | N143: =IF(B143="SEGURO DE VIDA EM GRUPO","31201003","31201005") -> 31201005
A145: 104 | B145: SEGURO UNIMED | C145: 15056 | F145: 297.48 | M145: =F145 -> 297.48 | N145: =IF(B145="SEGURO DE VIDA EM GRUPO","31201003","31201005") -> 31201005
A146: 104 | B146: SEGURO UNIMED | C146: 15058 | F146: 176.88 | M146: =F146 -> 176.88 | N146: =IF(B146="SEGURO DE VIDA EM GRUPO","31201003","31201005") -> 31201005
A147: 104 | B147: SEGURO UNIMED | C147: 15059 | F147: 152.76 | M147: =F147 -> 152.76 | N147: =IF(B147="SEGURO DE VIDA EM GRUPO","31201003","31201005") -> 31201005
A148: 104 | B148: SEGURO UNIMED | C148: 22002 | F148: 48.24 | M148: =F148 -> 48.24 | N148: =IF(B148="SEGURO DE VIDA EM GRUPO","31201003","31201005") -> 31201005
A150: 101 | B150: SORRISO ODONTO | C150: 13011 | F150: 213.6 | M150: =F150 -> 213.6 | N150: =IF(B150="SEGURO DE VIDA EM GRUPO","31201003","31201005") -> 31201005
... A171: 101 | B171: SORRISO ODONTO | C171: 55030 | F171: 75 | M171: =F171 -> 75 | N171: =IF(B171="SEGURO DE VIDA EM GRUPO","31201003","31201005") -> 31201005
A173: 101 | B173: UNIMED ODONTO | C173: 15056 | F173: 43.65 | M173: =F173 -> 43.65 | N173: =IF(B173="SEGURO DE VIDA EM GRUPO","31201003","31201005") -> 31201005
A174: 101 | B174: UNIMED ODONTO | C174: 15058 | F174: -14.55 | M174: =F174 -> -14.55 | N174: =IF(B174="SEGURO DE VIDA EM GRUPO","31201003","31201005") -> 31201005
A175: 101 | B175: UNIMED ODONTO | C175: 13012 | F175: 43.65 | M175: =F175 -> 43.65 | N175: =IF(B175="SEGURO DE VIDA EM GRUPO","31201003","31201005") -> 31201005
A176: 101 | B176: UNIMED ODONTO | C176: 13014 | F176: 43.65 | M176: =F176 -> 43.65 | N176: =IF(B176="SEGURO DE VIDA EM GRUPO","31201003","31201005") -> 31201005
A177: 101 | B177: UNIMED ODONTO | C177: 13016 | F177: 43.65 | M177: =F177 -> 43.65 | N177: =IF(B177="SEGURO DE VIDA EM GRUPO","31201003","31201005") -> 31201005
A178: 101 | B178: UNIMED ODONTO | C178: 13018 | F178: 72.75 | M178: =F178 -> 72.75 | N178: =IF(B178="SEGURO DE VIDA EM GRUPO","31201003","31201005") -> 31201005
A179: 101 | B179: UNIMED ODONTO | C179: 14012 | F179: 14.55 | M179: =F179 -> 14.55 | N179: =IF(B179="SEGURO DE VIDA EM GRUPO","31201003","31201005") -> 31201005
A180: 101 | B180: UNIMED ODONTO | C180: 14056 | F180: 101.85 | M180: =F180 -> 101.85 | N180: =IF(B180="SEGURO DE VIDA EM GRUPO","31201003","31201005") -> 31201005
A181: 101 | B181: UNIMED ODONTO | C181: 15012 | F181: 14.55 | M181: =F181 -> 14.55 | N181: =IF(B181="SEGURO DE VIDA EM GRUPO","31201003","31201005") -> 31201005
A182: 101 | B182: UNIMED ODONTO | C182: 15050 | F182: 421.95 | M182: =F182 -> 421.95 | N182: =IF(B182="SEGURO DE VIDA EM GRUPO","31201003","31201005") -> 31201005
A183: 101 | B183: UNIMED ODONTO | C183: 15051 | F183: 247.35 | M183: =F183 -> 247.35 | N183: =IF(B183="SEGURO DE VIDA EM GRUPO","31201003","31201005") -> 31201005
A184: 101 | B184: UNIMED ODONTO | C184: 15056 | F184: 349.2 | M184: =F184 -> 349.2 | N184: =IF(B184="SEGURO DE VIDA EM GRUPO","31201003","31201005") -> 31201005
A185: 101 | B185: UNIMED ODONTO | C185: 15058 | F185: 232.8 | M185: =F185 -> 232.8 | N185: =IF(B185="SEGURO DE VIDA EM GRUPO","31201003","31201005") -> 31201005
A186: 101 | B186: UNIMED ODONTO | C186: 15059 | F186: 247.35 | M186: =F186 -> 247.35 | N186: =IF(B186="SEGURO DE VIDA EM GRUPO","31201003","31201005") -> 31201005
...

Sheet SAUDE AGO2026
A1: REAL | B1: 1 | C1: 1 | D1: FGL | E1: 546.96 | F1: GERAL | G1: 46265 | H1: 1 | I1: CR | K1: 101 | L1: PLANO MÊS 08/2026 | M1: 1 | N1: 31550109 | O1: |PAGTO DOC - UNIMED ITUVERAVA|PLANO DE SAUDE - UNIMED ITUVERAVA|C CUSTO - 13021|TOTAL: 546,96| | Q1: NAO | R1: GERAL | S1: 13021 | T1: 19000 | U1: 31201005 | V1: 2 | W1: ='PLANO DE SAÚDE'!C4 -> 13021
A2: REAL | B2: =B1+2 -> 3 | C2: 1 | D2: FGL | E2: 2161.26 | F2: GERAL | G2: 46265 | H2: 1 | I2: CR | K2: 101 | L2: PLANO MÊS 08/2026 | M2: 1 | N2: 31550109 | O2: |PAGTO DOC - UNIMED ITUVERAVA|PLANO DE SAUDE - UNIMED ITUVERAVA|C CUSTO - 14051|TOTAL: 2161,26| | Q2: NAO | R2: GERAL | S2: 14051 | T2: 19000 | U2: 31201005 | V2: =V1+2 -> 4 | W2: ='PLANO DE SAÚDE'!C5 -> 14051
A3: REAL | B3: =B2+2 -> 5 | C3: 1 | D3: FGL | E3: 2014.32 | F3: GERAL | G3: 46265 | H3: 1 | I3: CR | K3: 101 | L3: PLANO MÊS 08/2026 | M3: 1 | N3: 31550109 | O3: |PAGTO DOC - UNIMED ITUVERAVA|PLANO DE SAUDE - UNIMED ITUVERAVA|C CUSTO - 14058|TOTAL: 2014,32| | Q3: NAO | R3: GERAL | S3: 14058 | T3: 19000 | U3: 31201005 | V3: =V2+2 -> 6 | W3: ='PLANO DE SAÚDE'!C6 -> 14058
A4: REAL | B4: =B3+2 -> 7 | C4: 1 | D4: FGL | E4: 546.96 | F4: GERAL | G4: 46265 | H4: 1 | I4: CR | K4: 101 | L4: PLANO MÊS 08/2026 | M4: 1 | N4: 31550109 | O4: |PAGTO DOC - UNIMED ITUVERAVA|PLANO DE SAUDE - UNIMED ITUVERAVA|C CUSTO - 31060|TOTAL: 546,96| | Q4: NAO | R4: GERAL | S4: 31060 | T4: 19000 | U4: 31201005 | V4: =V3+2 -> 8 | W4: ='PLANO DE SAÚDE'!C7 -> 31060
A5: REAL | B5: =B4+2 -> 9 | C5: 1 | D5: FGL | E5: 546.96 | F5: GERAL | G5: 46265 | H5: 1 | I5: CR | K5: 101 | L5: PLANO MÊS 08/2026 | M5: 1 | N5: 31550109 | O5: |PAGTO DOC - UNIMED ITUVERAVA|PLANO DE SAUDE - UNIMED ITUVERAVA|C CUSTO - 31070|TOTAL: 546,96| | Q5: NAO | R5: GERAL | S5: 31070 | T5: 19000 | U5: 31201005 | V5: =V4+2 -> 10 | W5: ='PLANO DE SAÚDE'!C8 -> 31070
A6: REAL | B6: =B5+2 -> 11 | C6: 1 | D6: FGL | E6: 2417.14 | F6: GERAL | G6: 46265 | H6: 1 | I6: CR | K6: 101 | L6: PLANO MÊS 08/2026 | M6: 1 | N6: 31550109 | O6: |PAGTO DOC - UNIMED ITUVERAVA|PLANO DE SAUDE - UNIMED ITUVERAVA|C CUSTO - 31114|TOTAL: 2417,14| | Q6: NAO | R6: GERAL | S6: 31114 | T6: 19000 | U6: 31201005 | V6: =V5+2 -> 12 | W6: ='PLANO DE SAÚDE'!C9 -> 31114
A7: REAL | B7: =B6+2 -> 13 | C7: 1 | D7: FGL | E7: 1093.92 | F7: GERAL | G7: 46265 | H7: 1 | I7: CR | K7: 101 | L7: PLANO MÊS 08/2026 | M7: 1 | N7: 31550109 | O7: |PAGTO DOC - UNIMED ITUVERAVA|PLANO DE SAUDE - UNIMED ITUVERAVA|C CUSTO - 11012|TOTAL: 1093,92| | Q7: NAO | R7: GERAL | S7: 11012 | T7: 19000 | U7: 31201005 | V7: =V6+2 -> 14 | W7: ='PLANO DE SAÚDE'!C10 -> 11012
A8: REAL | B8: =B7+2 -> 15 | C8: 1 | D8: FGL | E8: 1323.22 | F8: GERAL | G8: 46265 | H8: 1 | I8: CR | K8: 101 | L8: PLANO MÊS 08/2026 | M8: 1 | N8: 31550109 | O8: |PAGTO DOC - UNIMED ITUVERAVA|PLANO DE SAUDE - UNIMED ITUVERAVA|C CUSTO - 13011|TOTAL: 1323,22| | Q8: NAO | R8: GERAL | S8: 13011 | T8: 19000 | U8: 31201005 | V8: =V7+2 -> 16 | W8: ='PLANO DE SAÚDE'!C11 -> 13011
A9: REAL | B9: =B8+2 -> 17 | C9: 1 | D9: FGL | E9: 1005.56 | F9: GERAL | G9: 46265 | H9: 1 | I9: CR | K9: 101 | L9: PLANO MÊS 08/2026 | M9: 1 | N9: 31550109 | O9: |PAGTO DOC - UNIMED ITUVERAVA|PLANO DE SAUDE - UNIMED ITUVERAVA|C CUSTO - 13012|TOTAL: 1005,56| | Q9: NAO | R9: GERAL | S9: 13012 | T9: 19000 | U9: 31201005 | V9: =V8+2 -> 18 | W9: ='PLANO DE SAÚDE'!C12 -> 13012
A10: REAL | B10: =B9+2 -> 19 | C10: 1 | D10: FGL | E10: 8067.44 | F10: GERAL | G10: 46265 | H10: 1 | I10: CR | K10: 101 | L10: PLANO MÊS 08/2026 | M10: 1 | N10: 31550109 | O10: |PAGTO DOC - UNIMED ITUVERAVA|PLANO DE SAUDE - UNIMED ITUVERAVA|C CUSTO - 13013|TOTAL: 8067,44| | Q10: NAO | R10: GERAL | S10: 13013 | T10: 19000 | U10: 31201005 | V10: =V9+2 -> 20 | W10: ='PLANO DE SAÚDE'!C13 -> 13013
A11: REAL | B11: =B10+2 -> 21 | C11: 1 | D11: FGL | E11: 2187.84 | F11: GERAL | G11: 46265 | H11: 1 | I11: CR | K11: 101 | L11: PLANO MÊS 08/2026 | M11: 1 | N11: 31550109 | O11: |PAGTO DOC - UNIMED ITUVERAVA|PLANO DE SAUDE - UNIMED ITUVERAVA|C CUSTO - 13014|TOTAL: 2187,84| | Q11: NAO | R11: GERAL | S11: 13014 | T11: 19000 | U11: 31201005 | V11: =V10+2 -> 22 | W11: ='PLANO DE SAÚDE'!C14 -> 13014
A12: REAL | B12: =B11+2 -> 23 | C12: 1 | D12: FGL | E12: 1464.16 | F12: GERAL | G12: 46265 | H12: 1 | I12: CR | K12: 101 | L12: PLANO MÊS 08/2026 | M12: 1 | N12: 31550109 | O12: |PAGTO DOC - UNIMED ITUVERAVA|PLANO DE SAUDE - UNIMED ITUVERAVA|C CUSTO - 13016|TOTAL: 1464,16| | Q12: NAO | R12: GERAL | S12: 13016 | T12: 19000 | U12: 31201005 | V12: =V11+2 -> 24 | W12: ='PLANO DE SAÚDE'!C15 -> 13016
A13: REAL | B13: =B12+2 -> 25 | C13: 1 | D13: FGL | E13: 1640.88 | F13: GERAL | G13: 46265 | H13: 1 | I13: CR | K13: 101 | L13: PLANO MÊS 08/2026 | M13: 1 | N13: 31550109 | O13: |PAGTO DOC - UNIMED ITUVERAVA|PLANO DE SAUDE - UNIMED ITUVERAVA|C CUSTO - 13017|TOTAL: 1640,88| | Q13: NAO | R13: GERAL | S13: 13017 | T13: 19000 | U13: 31201005 | V13: =V12+2 -> 26 | W13: ='PLANO DE SAÚDE'!C16 -> 13017
A14: REAL | B14: =B13+2 -> 27 | C14: 1 | D14: FGL | E14: 1005.56 | F14: GERAL | G14: 46265 | H14: 1 | I14: CR | K14: 101 | L14: PLANO MÊS 08/2026 | M14: 1 | N14: 31550109 | O14: |PAGTO DOC - UNIMED ITUVERAVA|PLANO DE SAUDE - UNIMED ITUVERAVA|C CUSTO - 13018|TOTAL: 1005,56| | Q14: NAO | R14: GERAL | S14: 13018 | T14: 19000 | U14: 31201005 | V14: =V13+2 -> 28 | W14: ='PLANO DE SAÚDE'!C17 -> 13018
A15: REAL | B15: =B14+2 -> 29 | C15: 1 | D15: FGL | E15: 776.26 | F15: GERAL | G15: 46265 | H15: 1 | I15: CR | K15: 101 | L15: PLANO MÊS 08/2026 | M15: 1 | N15: 31550109 | O15: |PAGTO DOC - UNIMED ITUVERAVA|PLANO DE SAUDE - UNIMED ITUVERAVA|C CUSTO - 13019|TOTAL: 776,26| | Q15: NAO | R15: GERAL | S15: 13019 | T15: 19000 | U15: 31201005 | V15: =V14+2 -> 30 | W15: ='PLANO DE SAÚDE'!C18 -> 13019
A16: REAL | B16: =B15+2 -> 31 | C16: 1 | D16: FGL | E16: 2646.44 | F16: GERAL | G16: 46265 | H16: 1 | I16: CR | K16: 101 | L16: PLANO MÊS 08/2026 | M16: 1 | N16: 31550109 | O16: |PAGTO DOC - UNIMED ITUVERAVA|PLANO DE SAUDE - UNIMED ITUVERAVA|C CUSTO - 13021|TOTAL: 2646,44| | Q16: NAO | R16: GERAL | S16: 13021 | T16: 19000 | U16: 31201005 | V16: =V15+2 -> 32 | W16: ='PLANO DE SAÚDE'!C19 -> 13021
A17: REAL | B17: =B16+2 -> 33 | C17: 1 | D17: FGL | E17: 1870.18 | F17: GERAL | G17: 46265 | H17: 1 | I17: CR | K17: 101 | L17: PLANO MÊS 08/2026 | M17: 1 | N17: 31550109 | O17: |PAGTO DOC - UNIMED ITUVERAVA|PLANO DE SAUDE - UNIMED ITUVERAVA|C CUSTO - 14012|TOTAL: 1870,18| | Q17: NAO | R17: GERAL | S17: 14012 | T17: 19000 | U17: 31201005 | V17: =V16+2 -> 34 | W17: ='PLANO DE SAÚDE'!C20 -> 14012
A18: REAL | B18: =B17+2 -> 35 | C18: 1 | D18: FGL | E18: 2707.02 | F18: GERAL | G18: 46265 | H18: 1 | I18: CR | K18: 101 | L18: PLANO MÊS 08/2026 | M18: 1 | N18: 31550109 | O18: |PAGTO DOC - UNIMED ITUVERAVA|PLANO DE SAUDE - UNIMED ITUVERAVA|C CUSTO - 14051|TOTAL: 2707,02| | Q18: NAO | R18: GERAL | S18: 14051 | T18: 19000 | U18: 31201005 | V18: =V17+2 -> 36 | W18: ='PLANO DE SAÚDE'!C21 -> 14051
... A39: REAL | B39: =B38+2 -> 77 | C39: 1 | D39: FGL | E39: 546.96 | F39: GERAL | G39: 46265 | H39: 1 | I39: CR | K39: 101 | L39: PLANO MÊS 08/2026 | M39: 1 | N39: 31550109 | O39: |PAGTO DOC - UNIMED ITUVERAVA|PLANO DE SAUDE - UNIMED ITUVERAVA|C CUSTO - 55030|TOTAL: 546,96| | Q39: NAO | R39: GERAL | S39: 55030 | T39: 19000 | U39: 31201005 | V39: =V38+2 -> 78 | W39: ='PLANO DE SAÚDE'!C42 -> 55030
A40: REAL | B40: =B39+2 -> 79 | C40: 1 | D40: FGL | E40: 229.3 | F40: GERAL | G40: 46265 | H40: 1 | I40: CR | K40: 101 | L40: PLANO MÊS 08/2026 | M40: 1 | N40: 31550109 | O40: |PAGTO DOC - UNIMED ITUVERAVA|PLANO DE SAUDE - UNIMED ITUVERAVA|C CUSTO - 21012|TOTAL: 229,3| | Q40: NAO | R40: GERAL | S40: 21012 | T40: 19000 | U40: 31201005 | V40: =V39+2 -> 80 | W40: ='PLANO DE SAÚDE'!C43 -> 21012
A41: REAL | B41: =B40+2 -> 81 | C41: 1 | D41: FGL | E41: 546.96 | F41: GERAL | G41: 46265 | H41: 1 | I41: CR | K41: 101 | L41: PLANO MÊS 08/2026 | M41: 1 | N41: 31550109 | O41: |PAGTO DOC - UNIMED ITUVERAVA|PLANO DE SAUDE - UNIMED ITUVERAVA|C CUSTO - 31090|TOTAL: 546,96| | Q41: NAO | R41: GERAL | S41: 31090 | T41: 19000 | U41: 31201005 | V41: =V40+2 -> 82 | W41: ='PLANO DE SAÚDE'!C44 -> 31090
A42: REAL | B42: =B41+2 -> 83 | C42: 1 | D42: FGL | E42: 229.3 | F42: GERAL | G42: 46265 | H42: 1 | I42: CR | K42: 101 | L42: PLANO MÊS 08/2026 | M42: 1 | N42: 31550109 | O42: |PAGTO DOC - UNIMED ITUVERAVA|PLANO DE SAUDE - UNIMED ITUVERAVA|C CUSTO - 13016|TOTAL: 229,3| | Q42: NAO | R42: GERAL | S42: 13016 | T42: 19000 | U42: 31201005 | V42: =V41+2 -> 84 | W42: ='PLANO DE SAÚDE'!C45 -> 13016
A43: REAL | B43: =B42+2 -> 85 | C43: 1 | D43: FGL | E43: 546.96 | F43: GERAL | G43: 46265 | H43: 1 | I43: CR | K43: 101 | L43: PLANO MÊS 08/2026 | M43: 1 | N43: 31550109 | O43: |PAGTO DOC - UNIMED ITUVERAVA|PLANO DE SAUDE - UNIMED ITUVERAVA|C CUSTO - 33050|TOTAL: 546,96| | Q43: NAO | R43: GERAL | S43: 33050 | T43: 19000 | U43: 31201005 | V43: =V42+2 -> 86 | W43: ='PLANO DE SAÚDE'!C46 -> 33050
A44: REAL | B44: =B43+2 -> 87 | C44: 1 | D44: FGL | E44: 229.3 | F44: GERAL | G44: 46265 | H44: 1 | I44: CR | K44: 101 | L44: PLANO MÊS 08/2026 | M44: 1 | N44: 31550109 | O44: |PAGTO DOC - UNIMED ITUVERAVA|PLANO DE SAUDE - UNIMED ITUVERAVA|C CUSTO - 21011|TOTAL: 229,3| | Q44: NAO | R44: GERAL | S44: 21011 | T44: 19000 | U44: 31201005 | V44: =V43+2 -> 88 | W44: ='PLANO DE SAÚDE'!C47 -> 21011
A45: REAL | B45: =B44+2 -> 89 | C45: 1 | D45: FGL | E45: 74.15 | F45: GERAL | G45: 46265 | H45: 1 | I45: CR | K45: 101 | L45: PLANO MÊS 08/2026 | M45: 1 | N45: 31550109 | O45: |PAGTO DOC - SEGURO DE VIDA EM GRUPO|PLANO DE SAUDE - SEGURO DE VIDA EM GRUPO|C CUSTO - 11011|TOTAL: 74,15| | Q45: NAO | R45: GERAL | S45: 11011 | T45: 19000 | U45: 31201003 | V45: =V44+2 -> 90 | W45: ='PLANO DE SAÚDE'!#REF! -> #REF!
A46: REAL | B46: =B45+2 -> 91 | C46: 1 | D46: FGL | E46: 8.04 | F46: GERAL | G46: 46265 | H46: 1 | I46: CR | K46: 101 | L46: PLANO MÊS 08/2026 | M46: 1 | N46: 31550109 | O46: |PAGTO DOC - SEGURO DE VIDA EM GRUPO|PLANO DE SAUDE - SEGURO DE VIDA EM GRUPO|C CUSTO - 13013|TOTAL: 8,04| | Q46: NAO | R46: GERAL | S46: 13013 | T46: 19000 | U46: 31201003 | V46: =V45+2 -> 92 | W46: ='PLANO DE SAÚDE'!#REF! -> #REF!
A47: REAL | B47: =B46+2 -> 93 | C47: 1 | D47: FGL | E47: 74.15 | F47: GERAL | G47: 46265 | H47: 1 | I47: CR | K47: 101 | L47: PLANO MÊS 08/2026 | M47: 1 | N47: 31550109 | O47: |PAGTO DOC - SEGURO DE VIDA EM GRUPO|PLANO DE SAUDE - SEGURO DE VIDA EM GRUPO|C CUSTO - 13014|TOTAL: 74,15| | Q47: NAO | R47: GERAL | S47: 13014 | T47: 19000 | U47: 31201003 | V47: =V46+2 -> 94 | W47: ='PLANO DE SAÚDE'!C48 -> 11011
A48: REAL | B48: =B47+2 -> 95 | C48: 1 | D48: FGL | E48: 72.36 | F48: GERAL | G48: 46265 | H48: 1 | I48: CR | K48: 101 | L48: PLANO MÊS 08/2026 | M48: 1 | N48: 31550109 | O48: |PAGTO DOC - SEGURO DE VIDA EM GRUPO|PLANO DE SAUDE - SEGURO DE VIDA EM GRUPO|C CUSTO - 14050|TOTAL: 72,36| | Q48: NAO | R48: GERAL | S48: 14050 | T48: 19000 | U48: 31201003 | V48: =V47+2 -> 96 | W48: ='PLANO DE SAÚDE'!C49 -> 13013
A49: REAL | B49: =B48+2 -> 97 | C49: 1 | D49: FGL | E49: 201 | F49: GERAL | G49: 46265 | H49: 1 | I49: CR | K49: 101 | L49: PLANO MÊS 08/2026 | M49: 1 | N49: 31550109 | O49: |PAGTO DOC - SEGURO DE VIDA EM GRUPO|PLANO DE SAUDE - SEGURO DE VIDA EM GRUPO|C CUSTO - 14051|TOTAL: 201| | Q49: NAO | R49: GERAL | S49: 14051 | T49: 19000 | U49: 31201003 | V49: =V48+2 -> 98 | W49: ='PLANO DE SAÚDE'!C50 -> 13014
A50: REAL | B50: =B49+2 -> 99 | C50: 1 | D50: FGL | E50: 88.44 | F50: GERAL | G50: 46265 | H50: 1 | I50: CR | K50: 101 | L50: PLANO MÊS 08/2026 | M50: 1 | N50: 31550109 | O50: |PAGTO DOC - SEGURO DE VIDA EM GRUPO|PLANO DE SAUDE - SEGURO DE VIDA EM GRUPO|C CUSTO - 14052|TOTAL: 88,44| | Q50: NAO | R50: GERAL | S50: 14052 | T50: 19000 | U50: 31201003 | V50: =V49+2 -> 100 | W50: ='PLANO DE SAÚDE'!C51 -> 14050
A51: REAL | B51: =B50+2 -> 101 | C51: 1 | D51: FGL | E51: 90.23 | F51: GERAL | G51: 46265 | H51: 1 | I51: CR | K51: 101 | L51: PLANO MÊS 08/2026 | M51: 1 | N51: 31550109 | O51: |PAGTO DOC - SEGURO DE VIDA EM GRUPO|PLANO DE SAUDE - SEGURO DE VIDA EM GRUPO|C CUSTO - 14054|TOTAL: 90,23| | Q51: NAO | R51: GERAL | S51: 14054 | T51: 19000 | U51: 31201003 | V51: =V50+2 -> 102 | W51: ='PLANO DE SAÚDE'!C52 -> 14051
A52: REAL | B52: =B51+2 -> 103 | C52: 1 | D52: FGL | E52: 64.32 | F52: GERAL | G52: 46265 | H52: 1 | I52: CR | K52: 101 | L52: PLANO MÊS 08/2026 | M52: 1 | N52: 31550109 | O52: |PAGTO DOC - SEGURO DE VIDA EM GRUPO|PLANO DE SAUDE - SEGURO DE VIDA EM GRUPO|C CUSTO - 14056|TOTAL: 64,32| | Q52: NAO | R52: GERAL | S52: 14056 | T52: 19000 | U52: 31201003 | V52: =V51+2 -> 104 | W52: ='PLANO DE SAÚDE'!C53 -> 14052
A53: REAL | B53: =B52+2 -> 105 | C53: 1 | D53: FGL | E53: 209.04 | F53: GERAL | G53: 46265 | H53: 1 | I53: CR | K53: 101 | L53: PLANO MÊS 08/2026 | M53: 1 | N53: 31550109 | O53: |PAGTO DOC - SEGURO DE VIDA EM GRUPO|PLANO DE SAUDE - SEGURO DE VIDA EM GRUPO|C CUSTO - 14058|TOTAL: 209,04| | Q53: NAO | R53: GERAL | S53: 14058 | T53: 19000 | U53: 31201003 | V53: =V52+2 -> 106 | W53: ='PLANO DE SAÚDE'!C54 -> 14054
A54: REAL | B54: =B53+2 -> 107 | C54: 1 | D54: FGL | E54: 8.04 | F54: GERAL | G54: 46265 | H54: 1 | I54: CR | K54: 101 | L54: PLANO MÊS 08/2026 | M54: 1 | N54: 31550109 | O54: |PAGTO DOC - SEGURO DE VIDA EM GRUPO|PLANO DE SAUDE - SEGURO DE VIDA EM GRUPO|C CUSTO - 14062|TOTAL: 8,04| | Q54: NAO | R54: GERAL | S54: 14062 | T54: 19000 | U54: 31201003 | V54: =V53+2 -> 108 | W54: ='PLANO DE SAÚDE'!C55 -> 14056
A55: REAL | B55: =B54+2 -> 109 | C55: 1 | D55: FGL | E55: 74.15 | F55: GERAL | G55: 46265 | H55: 1 | I55: CR | K55: 101 | L55: PLANO MÊS 08/2026 | M55: 1 | N55: 31550109 | O55: |PAGTO DOC - SEGURO DE VIDA EM GRUPO|PLANO DE SAUDE - SEGURO DE VIDA EM GRUPO|C CUSTO - 15012|TOTAL: 74,15| | Q55: NAO | R55: GERAL | S55: 15012 | T55: 19000 | U55: 31201003 | V55: =V54+2 -> 110 | W55: ='PLANO DE SAÚDE'!C56 -> 14058
A56: REAL | B56: =B55+2 -> 111 | C56: 1 | D56: FGL | E56: 24.12 | F56: GERAL | G56: 46265 | H56: 1 | I56: CR | K56: 101 | L56: PLANO MÊS 08/2026 | M56: 1 | N56: 31550109 | O56: |PAGTO DOC - SEGURO DE VIDA EM GRUPO|PLANO DE SAUDE - SEGURO DE VIDA EM GRUPO|C CUSTO - 15050|TOTAL: 24,12| | Q56: NAO | R56: GERAL | S56: 15050 | T56: 19000 | U56: 31201003 | V56: =V55+2 -> 112 | W56: ='PLANO DE SAÚDE'!C57 -> 14062
A57: REAL | B57: =B56+2 -> 113 | C57: 1 | D57: FGL | E57: 16.08 | F57: GERAL | G57: 46265 | H57: 1 | I57: CR | K57: 101 | L57: PLANO MÊS 08/2026 | M57: 1 | N57: 31550109 | O57: |PAGTO DOC - SEGURO DE VIDA EM GRUPO|PLANO DE SAUDE - SEGURO DE VIDA EM GRUPO|C CUSTO - 15051|TOTAL: 16,08| | Q57: NAO | R57: GERAL | S57: 15051 | T57: 19000 | U57: 31201003 | V57: =V56+2 -> 114 | W57: ='PLANO DE SAÚDE'!C58 -> 15012
A58: REAL | B58: =B57+2 -> 115 | C58: 1 | D58: FGL | E58: 48.24 | F58: GERAL | G58: 46265 | H58: 1 | I58: CR | K58: 101 | L58: PLANO MÊS 08/2026 | M58: 1 | N58: 31550109 | O58: |PAGTO DOC - SEGURO DE VIDA EM GRUPO|PLANO DE SAUDE - SEGURO DE VIDA EM GRUPO|C CUSTO - 31060|TOTAL: 48,24| | Q58: NAO | R58: GERAL | S58: 31060 | T58: 19000 | U58: 31201003 | V58: =V57+2 -> 116 | W58: ='PLANO DE SAÚDE'!C59 -> 15050
... A62: REAL | B62: =B61+2 -> 123 | C62: 1 | D62: FGL | E62: 8.04 | F62: GERAL | G62: 46265 | H62: 1 | I62: CR | K62: 101 | L62: PLANO MÊS 08/2026 | M62: 1 | N62: 31550109 | O62: |PAGTO DOC - SEGURO DE VIDA EM GRUPO|PLANO DE SAUDE - SEGURO DE VIDA EM GRUPO|C CUSTO - 31200|TOTAL: 8,04| | Q62: NAO | R62: GERAL | S62: 31200 | T62: 19000 | U62: 31201003 | V62: =V61+2 -> 124 | W62: ='PLANO DE SAÚDE'!C63 -> 31111
A63: REAL | B63: =B62+2 -> 125 | C63: 1 | D63: FGL | E63: 230.49 | F63: GERAL | G63: 46265 | H63: 1 | I63: CR | K63: 101 | L63: PLANO MÊS 08/2026 | M63: 1 | N63: 31550109 | O63: |PAGTO DOC - SEGURO DE VIDA EM GRUPO|PLANO DE SAUDE - SEGURO DE VIDA EM GRUPO|C CUSTO - 11011|TOTAL: 230,49| | Q63: NAO | R63: GERAL | S63: 11011 | T63: 19000 | U63: 31201003 | V63: =V62+2 -> 126 | W63: ='PLANO DE SAÚDE'!C64 -> 31114
A64: REAL | B64: =B63+2 -> 127 | C64: 1 | D64: FGL | E64: 90.23 | F64: GERAL | G64: 46265 | H64: 1 | I64: CR | K64: 101 | L64: PLANO MÊS 08/2026 | M64: 1 | N64: 31550109 | O64: |PAGTO DOC - SEGURO DE VIDA EM GRUPO|PLANO DE SAUDE - SEGURO DE VIDA EM GRUPO|C CUSTO - 11012|TOTAL: 90,23| | Q64: NAO | R64: GERAL | S64: 11012 | T64: 19000 | U64: 31201003 | V64: =V63+2 -> 128 | W64: ='PLANO DE SAÚDE'!C65 -> 31200
A65: REAL | B65: =B64+2 -> 129 | C65: 1 | D65: FGL | E65: 74.15 | F65: GERAL | G65: 46265 | H65: 1 | I65: CR | K65: 101 | L65: PLANO MÊS 08/2026 | M65: 1 | N65: 31550109 | O65: |PAGTO DOC - SEGURO DE VIDA EM GRUPO|PLANO DE SAUDE - SEGURO DE VIDA EM GRUPO|C CUSTO - 11013|TOTAL: 74,15| | Q65: NAO | R65: GERAL | S65: 11013 | T65: 19000 | U65: 31201003 | V65: =V64+2 -> 130 | W65: ='PLANO DE SAÚDE'!C66 -> 11011
A66: REAL | B66: =B65+2 -> 131 | C66: 1 | D66: FGL | E66: 64.32 | F66: GERAL | G66: 46265 | H66: 1 | I66: CR | K66: 101 | L66: PLANO MÊS 08/2026 | M66: 1 | N66: 31550109 | O66: |PAGTO DOC - SEGURO DE VIDA EM GRUPO|PLANO DE SAUDE - SEGURO DE VIDA EM GRUPO|C CUSTO - 13011|TOTAL: 64,32| | Q66: NAO | R66: GERAL | S66: 13011 | T66: 19000 | U66: 31201003 | V66: =V65+2 -> 132 | W66: ='PLANO DE SAÚDE'!C67 -> 11012
A67: REAL | B67: =B66+2 -> 133 | C67: 1 | D67: FGL | E67: 16.08 | F67: GERAL | G67: 46265 | H67: 1 | I67: CR | K67: 101 | L67: PLANO MÊS 08/2026 | M67: 1 | N67: 31550109 | O67: |PAGTO DOC - SEGURO DE VIDA EM GRUPO|PLANO DE SAUDE - SEGURO DE VIDA EM GRUPO|C CUSTO - 13012|TOTAL: 16,08| | Q67: NAO | R67: GERAL | S67: 13012 | T67: 19000 | U67: 31201003 | V67: =V66+2 -> 134 | W67: ='PLANO DE SAÚDE'!C68 -> 11013
A68: REAL | B68: =B67+2 -> 135 | C68: 1 | D68: FGL | E68: 128.33 | F68: GERAL | G68: 46265 | H68: 1 | I68: CR | K68: 101 | L68: PLANO MÊS 08/2026 | M68: 1 | N68: 31550109 | O68: |PAGTO DOC - SEGURO DE VIDA EM GRUPO|PLANO DE SAUDE - SEGURO DE VIDA EM GRUPO|C CUSTO - 13013|TOTAL: 128,33| | Q68: NAO | R68: GERAL | S68: 13013 | T68: 19000 | U68: 31201003 | V68: =V67+2 -> 136 | W68: ='PLANO DE SAÚDE'!C69 -> 13011
A69: REAL | B69: =B68+2 -> 137 | C69: 1 | D69: FGL | E69: 40.2 | F69: GERAL | G69: 46265 | H69: 1 | I69: CR | K69: 101 | L69: PLANO MÊS 08/2026 | M69: 1 | N69: 31550109 | O69: |PAGTO DOC - SEGURO DE VIDA EM GRUPO|PLANO DE SAUDE - SEGURO DE VIDA EM GRUPO|C CUSTO - 13014|TOTAL: 40,2| | Q69: NAO | R69: GERAL | S69: 13014 | T69: 19000 | U69: 31201003 | V69: =V68+2 -> 138 | W69: ='PLANO DE SAÚDE'!C70 -> 13012
A70: REAL | B70: =B69+2 -> 139 | C70: 1 | D70: FGL | E70: 40.2 | F70: GERAL | G70: 46265 | H70: 1 | I70: CR | K70: 101 | L70: PLANO MÊS 08/2026 | M70: 1 | N70: 31550109 | O70: |PAGTO DOC - SEGURO DE VIDA EM GRUPO|PLANO DE SAUDE - SEGURO DE VIDA EM GRUPO|C CUSTO - 13016|TOTAL: 40,2| | Q70: NAO | R70: GERAL | S70: 13016 | T70: 19000 | U70: 31201003 | V70: =V69+2 -> 140 | W70: ='PLANO DE SAÚDE'!C71 -> 13013
A71: REAL | B71: =B70+2 -> 141 | C71: 1 | D71: FGL | E71: 32.16 | F71: GERAL | G71: 46265 | H71: 1 | I71: CR | K71: 101 | L71: PLANO MÊS 08/2026 | M71: 1 | N71: 31550109 | O71: |PAGTO DOC - SEGURO DE VIDA EM GRUPO|PLANO DE SAUDE - SEGURO DE VIDA EM GRUPO|C CUSTO - 13017|TOTAL: 32,16| | Q71: NAO | R71: GERAL | S71: 13017 | T71: 19000 | U71: 31201003 | V71: =V70+2 -> 142 | W71: ='PLANO DE SAÚDE'!C72 -> 13014
A72: REAL | B72: =B71+2 -> 143 | C72: 1 | D72: FGL | E72: 24.12 | F72: GERAL | G72: 46265 | H72: 1 | I72: CR | K72: 101 | L72: PLANO MÊS 08/2026 | M72: 1 | N72: 31550109 | O72: |PAGTO DOC - SEGURO DE VIDA EM GRUPO|PLANO DE SAUDE - SEGURO DE VIDA EM GRUPO|C CUSTO - 13018|TOTAL: 24,12| | Q72: NAO | R72: GERAL | S72: 13018 | T72: 19000 | U72: 31201003 | V72: =V71+2 -> 144 | W72: ='PLANO DE SAÚDE'!C73 -> 13016
A73: REAL | B73: =B72+2 -> 145 | C73: 1 | D73: FGL | E73: 24.12 | F73: GERAL | G73: 46265 | H73: 1 | I73: CR | K73: 101 | L73: PLANO MÊS 08/2026 | M73: 1 | N73: 31550109 | O73: |PAGTO DOC - SEGURO DE VIDA EM GRUPO|PLANO DE SAUDE - SEGURO DE VIDA EM GRUPO|C CUSTO - 13019|TOTAL: 24,12| | Q73: NAO | R73: GERAL | S73: 13019 | T73: 19000 | U73: 31201003 | V73: =V72+2 -> 146 | W73: ='PLANO DE SAÚDE'!C74 -> 13017
A74: REAL | B74: =B73+2 -> 147 | C74: 1 | D74: FGL | E74: 64.32 | F74: GERAL | G74: 46265 | H74: 1 | I74: CR | K74: 101 | L74: PLANO MÊS 08/2026 | M74: 1 | N74: 31550109 | O74: |PAGTO DOC - SEGURO DE VIDA EM GRUPO|PLANO DE SAUDE - SEGURO DE VIDA EM GRUPO|C CUSTO - 13021|TOTAL: 64,32| | Q74: NAO | R74: GERAL | S74: 13021 | T74: 19000 | U74: 31201003 | V74: =V73+2 -> 148 | W74: ='PLANO DE SAÚDE'!C75 -> 13018
... A104: REAL | B104: =B103+2 -> 207 | C104: 1 | D104: FGL | E104: 16.08 | F104: GERAL | G104: 46265 | H104: 1 | I104: CR | K104: 101 | L104: PLANO MÊS 08/2026 | M104: 1 | N104: 31550109 | O104: |PAGTO DOC - SEGURO DE VIDA EM GRUPO|PLANO DE SAUDE - SEGURO DE VIDA EM GRUPO|C CUSTO - 55030|TOTAL: 16,08| | Q104: NAO | R104: GERAL | S104: 55030 | T104: 19000 | U104: 31201003 | V104: =V103+2 -> 208 | W104: ='PLANO DE SAÚDE'!C105 -> 33050
A105: REAL | B105: =B104+2 -> 209 | C105: 1 | D105: FGL | E105: 8.04 | F105: GERAL | G105: 46265 | H105: 1 | I105: CR | K105: 101 | L105: PLANO MÊS 08/2026 | M105: 1 | N105: 31550109 | O105: |PAGTO DOC - SEGURO DE VIDA EM GRUPO|PLANO DE SAUDE - SEGURO DE VIDA EM GRUPO|C CUSTO - 31090|TOTAL: 8,04| | Q105: NAO | R105: GERAL | S105: 31090 | T105: 19000 | U105: 31201003 | V105: =V104+2 -> 210 | W105: ='PLANO DE SAÚDE'!C106 -> 33060
A106: REAL | B106: =B105+2 -> 211 | C106: 1 | D106: FGL | E106: 16.08 | F106: GERAL | G106: 46265 | H106: 1 | I106: CR | K106: 101 | L106: PLANO MÊS 08/2026 | M106: 1 | N106: 31550109 | O106: |PAGTO DOC - SEGURO DE VIDA EM GRUPO|PLANO DE SAUDE - SEGURO DE VIDA EM GRUPO|C CUSTO - 31116|TOTAL: 16,08| | Q106: NAO | R106: GERAL | S106: 31116 | T106: 19000 | U106: 31201003 | V106: =V105+2 -> 212 | W106: ='PLANO DE SAÚDE'!C109 -> 31116
A107: REAL | B107: =B106+2 -> 213 | C107: 1 | D107: FGL | E107: 16.08 | F107: GERAL | G107: 46265 | H107: 1 | I107: CR | K107: 101 | L107: PLANO MÊS 08/2026 | M107: 1 | N107: 31550109 | O107: |PAGTO DOC - SEGURO DE VIDA EM GRUPO|PLANO DE SAUDE - SEGURO DE VIDA EM GRUPO|C CUSTO - 33050|TOTAL: 16,08| | Q107: NAO | R107: GERAL | S107: 33050 | T107: 19000 | U107: 31201003 | V107: =V106+2 -> 214 | W107: ='PLANO DE SAÚDE'!C110 -> 33050
A108: REAL | B108: =B107+2 -> 215 | C108: 1 | D108: FGL | E108: 16.08 | F108: GERAL | G108: 46265 | H108: 1 | I108: CR | K108: 101 | L108: PLANO MÊS 08/2026 | M108: 1 | N108: 31550109 | O108: |PAGTO DOC - SEGURO DE VIDA EM GRUPO|PLANO DE SAUDE - SEGURO DE VIDA EM GRUPO|C CUSTO - 14012|TOTAL: 16,08| | Q108: NAO | R108: GERAL | S108: 14012 | T108: 19000 | U108: 31201003 | V108: =V107+2 -> 216 | W108: ='PLANO DE SAÚDE'!C111 -> 14012
A109: REAL | B109: =B108+2 -> 217 | C109: 1 | D109: FGL | E109: 8.04 | F109: GERAL | G109: 46265 | H109: 1 | I109: CR | K109: 101 | L109: PLANO MÊS 08/2026 | M109: 1 | N109: 31550109 | O109: |PAGTO DOC - SEGURO DE VIDA EM GRUPO|PLANO DE SAUDE - SEGURO DE VIDA EM GRUPO|C CUSTO - 21012|TOTAL: 8,04| | Q109: NAO | R109: GERAL | S109: 21012 | T109: 19000 | U109: 31201003 | V109: =V108+2 -> 218 | W109: ='PLANO DE SAÚDE'!C112 -> 21012
A110: REAL | B110: =B109+2 -> 219 | C110: 1 | D110: FGL | E110: 8.04 | F110: GERAL | G110: 46265 | H110: 1 | I110: CR | K110: 101 | L110: PLANO MÊS 08/2026 | M110: 1 | N110: 31550109 | O110: |PAGTO DOC - SEGURO DE VIDA EM GRUPO|PLANO DE SAUDE - SEGURO DE VIDA EM GRUPO|C CUSTO - 13016|TOTAL: 8,04| | Q110: NAO | R110: GERAL | S110: 13016 | T110: 19000 | U110: 31201003 | V110: =V109+2 -> 220 | W110: ='PLANO DE SAÚDE'!C113 -> 13016
A111: REAL | B111: =B110+2 -> 221 | C111: 1 | D111: FGL | E111: 8.04 | F111: GERAL | G111: 46265 | H111: 1 | I111: CR | K111: 101 | L111: PLANO MÊS 08/2026 | M111: 1 | N111: 31550109 | O111: |PAGTO DOC - SEGURO DE VIDA EM GRUPO|PLANO DE SAUDE - SEGURO DE VIDA EM GRUPO|C CUSTO - 13021|TOTAL: 8,04| | Q111: NAO | R111: GERAL | S111: 13021 | T111: 19000 | U111: 31201003 | V111: =V110+2 -> 222 | W111: ='PLANO DE SAÚDE'!C114 -> 13021
A112: REAL | B112: =B111+2 -> 223 | C112: 1 | D112: FGL | E112: 8.04 | F112: GERAL | G112: 46265 | H112: 1 | I112: CR | K112: 101 | L112: PLANO MÊS 08/2026 | M112: 1 | N112: 31550109 | O112: |PAGTO DOC - SEGURO DE VIDA EM GRUPO|PLANO DE SAUDE - SEGURO DE VIDA EM GRUPO|C CUSTO - 21011|TOTAL: 8,04| | Q112: NAO | R112: GERAL | S112: 21011 | T112: 19000 | U112: 31201003 | V112: =V111+2 -> 224 | W112: ='PLANO DE SAÚDE'!C115 -> 21011
A113: REAL | B113: =B112+2 -> 225 | C113: 1 | D113: FGL | E113: 8.04 | F113: GERAL | G113: 46265 | H113: 1 | I113: CR | K113: 101 | L113: PLANO MÊS 08/2026 | M113: 1 | N113: 31550109 | O113: |PAGTO DOC - SEGURO DE VIDA EM GRUPO|PLANO DE SAUDE - SEGURO DE VIDA EM GRUPO|C CUSTO - 33010|TOTAL: 8,04| | Q113: NAO | R113: GERAL | S113: 33010 | T113: 19000 | U113: 31201003 | V113: =V112+2 -> 226 | W113: ='PLANO DE SAÚDE'!C116 -> 33010
A114: REAL | B114: =B113+2 -> 227 | C114: 1 | D114: FGL | E114: 2502.52 | F114: GERAL | G114: 46265 | H114: 1 | I114: CR | K114: 101 | L114: PLANO MÊS 08/2026 | M114: 1 | N114: 31550109 | O114: |PAGTO DOC - SEGURO SAÚDE|PLANO DE SAUDE - SEGURO SAÚDE|C CUSTO - 13014|TOTAL: 2502,52| | Q114: NAO | R114: GERAL | S114: 13014 | T114: 19000 | U114: 31201005 | V114: =V113+2 -> 228 | W114: ='PLANO DE SAÚDE'!C117 -> 13014
A115: REAL | B115: =B114+2 -> 229 | C115: 1 | D115: FGL | E115: 1238.55 | F115: GERAL | G115: 46265 | H115: 1 | I115: CR | K115: 101 | L115: PLANO MÊS 08/2026 | M115: 1 | N115: 31550109 | O115: |PAGTO DOC - SEGURO SAÚDE|PLANO DE SAUDE - SEGURO SAÚDE|C CUSTO - 14050|TOTAL: 1238,55| | Q115: NAO | R115: GERAL | S115: 14050 | T115: 19000 | U115: 31201005 | V115: =V114+2 -> 230 | W115: ='PLANO DE SAÚDE'!C118 -> 14050
A116: REAL | B116: =B115+2 -> 231 | C116: 1 | D116: FGL | E116: 2502.52 | F116: GERAL | G116: 46265 | H116: 1 | I116: CR | K116: 101 | L116: PLANO MÊS 08/2026 | M116: 1 | N116: 31550109 | O116: |PAGTO DOC - SEGURO SAÚDE|PLANO DE SAUDE - SEGURO SAÚDE|C CUSTO - 15012|TOTAL: 2502,52| | Q116: NAO | R116: GERAL | S116: 15012 | T116: 19000 | U116: 31201005 | V116: =V115+2 -> 232 | W116: ='PLANO DE SAÚDE'!C119 -> 15012
A117: REAL | B117: =B116+2 -> 233 | C117: 1 | D117: FGL | E117: 1238.55 | F117: GERAL | G117: 46265 | H117: 1 | I117: CR | K117: 101 | L117: PLANO MÊS 08/2026 | M117: 1 | N117: 31550109 | O117: |PAGTO DOC - SEGURO SAÚDE|PLANO DE SAUDE - SEGURO SAÚDE|C CUSTO - 15056|TOTAL: 1238,55| | Q117: NAO | R117: GERAL | S117: 15056 | T117: 19000 | U117: 31201005 | V117: =V116+2 -> 234 | W117: ='PLANO DE SAÚDE'!C120 -> 15056
A118: REAL | B118: =B117+2 -> 235 | C118: 1 | D118: FGL | E118: 33358.46 | F118: GERAL | G118: 46265 | H118: 1 | I118: CR | K118: 101 | L118: PLANO MÊS 08/2026 | M118: 1 | N118: 31550109 | O118: |PAGTO DOC - SEGURO SAÚDE|PLANO DE SAUDE - SEGURO SAÚDE|C CUSTO - 11011|TOTAL: 33358,46| | Q118: NAO | R118: GERAL | S118: 11011 | T118: 19000 | U118: 31201005 | V118: =V117+2 -> 236 | W118: ='PLANO DE SAÚDE'!C121 -> 11011
A119: REAL | B119: =B118+2 -> 237 | C119: 1 | D119: FGL | E119: 15015.12 | F119: GERAL | G119: 46265 | H119: 1 | I119: CR | K119: 101 | L119: PLANO MÊS 08/2026 | M119: 1 | N119: 31550109 | O119: |PAGTO DOC - SEGURO SAÚDE|PLANO DE SAUDE - SEGURO SAÚDE|C CUSTO - 11012|TOTAL: 15015,12| | Q119: NAO | R119: GERAL | S119: 11012 | T119: 19000 | U119: 31201005 | V119: =V118+2 -> 238 | W119: ='PLANO DE SAÚDE'!C122 -> 11012
A120: REAL | B120: =B119+2 -> 239 | C120: 1 | D120: FGL | E120: 7507.56 | F120: GERAL | G120: 46265 | H120: 1 | I120: CR | K120: 101 | L120: PLANO MÊS 08/2026 | M120: 1 | N120: 31550109 | O120: |PAGTO DOC - SEGURO SAÚDE|PLANO DE SAUDE - SEGURO SAÚDE|C CUSTO - 11013|TOTAL: 7507,56| | Q120: NAO | R120: GERAL | S120: 11013 | T120: 19000 | U120: 31201005 | V120: =V119+2 -> 240 | W120: ='PLANO DE SAÚDE'!C123 -> 11013
A121: REAL | B121: =B120+2 -> 241 | C121: 1 | D121: FGL | E121: 5005.04 | F121: GERAL | G121: 46265 | H121: 1 | I121: CR | K121: 101 | L121: PLANO MÊS 08/2026 | M121: 1 | N121: 31550109 | O121: |PAGTO DOC - SEGURO SAÚDE|PLANO DE SAUDE - SEGURO SAÚDE|C CUSTO - 13013|TOTAL: 5005,04| | Q121: NAO | R121: GERAL | S121: 13013 | T121: 19000 | U121: 31201005 | V121: =V120+2 -> 242 | W121: ='PLANO DE SAÚDE'!C124 -> 13013
A122: REAL | B122: =B121+2 -> 243 | C122: 1 | D122: FGL | E122: 4979.62 | F122: GERAL | G122: 46265 | H122: 1 | I122: CR | K122: 101 | L122: PLANO MÊS 08/2026 | M122: 1 | N122: 31550109 | O122: |PAGTO DOC - SEGURO SAÚDE|PLANO DE SAUDE - SEGURO SAÚDE|C CUSTO - 14051|TOTAL: 4979,62| | Q122: NAO | R122: GERAL | S122: 14051 | T122: 19000 | U122: 31201005 | V122: =V121+2 -> 244 | W122: ='PLANO DE SAÚDE'!C125 -> 14051
A123: REAL | B123: =B122+2 -> 245 | C123: 1 | D123: FGL | E123: 2477.1 | F123: GERAL | G123: 46265 | H123: 1 | I123: CR | K123: 101 | L123: PLANO MÊS 08/2026 | M123: 1 | N123: 31550109 | O123: |PAGTO DOC - SEGURO SAÚDE|PLANO DE SAUDE - SEGURO SAÚDE|C CUSTO - 14056|TOTAL: 2477,1| | Q123: NAO | R123: GERAL | S123: 14056 | T123: 19000 | U123: 31201005 | V123: =V122+2 -> 246 | W123: ='PLANO DE SAÚDE'!C126 -> 14056
A124: REAL | B124: =B123+2 -> 247 | C124: 1 | D124: FGL | E124: 1238.55 | F124: GERAL | G124: 46265 | H124: 1 | I124: CR | K124: 101 | L124: PLANO MÊS 08/2026 | M124: 1 | N124: 31550109 | O124: |PAGTO DOC - SEGURO SAÚDE|PLANO DE SAUDE - SEGURO SAÚDE|C CUSTO - 15012|TOTAL: 1238,55| | Q124: NAO | R124: GERAL | S124: 15012 | T124: 19000 | U124: 31201005 | V124: =V123+2 -> 248 | W124: ='PLANO DE SAÚDE'!C127 -> 15012
A125: REAL | B125: =B124+2 -> 249 | C125: 1 | D125: FGL | E125: 12798.35 | F125: GERAL | G125: 46265 | H125: 1 | I125: CR | K125: 101 | L125: PLANO MÊS 08/2026 | M125: 1 | N125: 31550109 | O125: |PAGTO DOC - SEGURO SAÚDE|PLANO DE SAUDE - SEGURO SAÚDE|C CUSTO - 15050|TOTAL: 12798,35| | Q125: NAO | R125: GERAL | S125: 15050 | T125: 19000 | U125: 31201005 | V125: =V124+2 -> 250 | W125: ='PLANO DE SAÚDE'!C128 -> 15050
A126: REAL | B126: =B125+2 -> 251 | C126: 1 | D126: FGL | E126: 6605.6 | F126: GERAL | G126: 46265 | H126: 1 | I126: CR | K126: 101 | L126: PLANO MÊS 08/2026 | M126: 1 | N126: 31550109 | O126: |PAGTO DOC - SEGURO SAÚDE|PLANO DE SAUDE - SEGURO SAÚDE|C CUSTO - 15051|TOTAL: 6605,6| | Q126: NAO | R126: GERAL | S126: 15051 | T126: 19000 | U126: 31201005 | V126: =V125+2 -> 252 | W126: ='PLANO DE SAÚDE'!C129 -> 15051
A127: REAL | B127: =B126+2 -> 253 | C127: 1 | D127: FGL | E127: 10734.1 | F127: GERAL | G127: 46265 | H127: 1 | I127: CR | K127: 101 | L127: PLANO MÊS 08/2026 | M127: 1 | N127: 31550109 | O127: |PAGTO DOC - SEGURO SAÚDE|PLANO DE SAUDE - SEGURO SAÚDE|C CUSTO - 15056|TOTAL: 10734,1| | Q127: NAO | R127: GERAL | S127: 15056 | T127: 19000 | U127: 31201005 | V127: =V126+2 -> 254 | W127: ='PLANO DE SAÚDE'!C130 -> 15056
A128: REAL | B128: =B127+2 -> 255 | C128: 1 | D128: FGL | E128: 7431.3 | F128: GERAL | G128: 46265 | H128: 1 | I128: CR | K128: 101 | L128: PLANO MÊS 08/2026 | M128: 1 | N128: 31550109 | O128: |PAGTO DOC - SEGURO SAÚDE|PLANO DE SAUDE - SEGURO SAÚDE|C CUSTO - 15058|TOTAL: 7431,3| | Q128: NAO | R128: GERAL | S128: 15058 | T128: 19000 | U128: 31201005 | V128: =V127+2 -> 256 | W128: ='PLANO DE SAÚDE'!C131 -> 15058
A129: REAL | B129: =B128+2 -> 257 | C129: 1 | D129: FGL | E129: 7431.3 | F129: GERAL | G129: 46265 | H129: 1 | I129: CR | K129: 101 | L129: PLANO MÊS 08/2026 | M129: 1 | N129: 31550109 | O129: |PAGTO DOC - SEGURO SAÚDE|PLANO DE SAUDE - SEGURO SAÚDE|C CUSTO - 15059|TOTAL: 7431,3| | Q129: NAO | R129: GERAL | S129: 15059 | T129: 19000 | U129: 31201005 | V129: =V128+2 -> 258 | W129: ='PLANO DE SAÚDE'!C132 -> 15059
... A131: REAL | B131: =B130+2 -> 261 | C131: 1 | D131: FGL | E131: 10422.93 | F131: GERAL | G131: 46265 | H131: 1 | I131: CR | K131: 101 | L131: PLANO MÊS 08/2026 | M131: 1 | N131: 31550109 | O131: |PAGTO DOC - SEGURO SAÚDE|PLANO DE SAUDE - SEGURO SAÚDE|C CUSTO - 33010|TOTAL: 10422,93| | Q131: NAO | R131: GERAL | S131: 33010 | T131: 19000 | U131: 31201005 | V131: =V130+2 -> 262 | W131: ='PLANO DE SAÚDE'!C134 -> 33010
A132: REAL | B132: =B131+2 -> 263 | C132: 1 | D132: FGL | E132: 8.04 | F132: GERAL | G132: 46265 | H132: 1 | I132: CR | K132: 106 | L132: PLANO MÊS 08/2026 | M132: 1 | N132: 31550109 | O132: |PAGTO DOC - |PLANO DE SAUDE - SEGURO UNIMED|C CUSTO - 13013|TOTAL: 8,04| | Q132: NAO | R132: GERAL | S132: 13013 | T132: 19000 | U132: 31201005 | V132: =V131+2 -> 264 | W132: ='PLANO DE SAÚDE'!#REF! -> #REF!
A133: REAL | B133: =B132+2 -> 265 | C133: 1 | D133: FGL | E133: 56.28 | F133: GERAL | G133: 46265 | H133: 1 | I133: CR | K133: 106 | L133: PLANO MÊS 08/2026 | M133: 1 | N133: 31550109 | O133: |PAGTO DOC - |PLANO DE SAUDE - SEGURO UNIMED|C CUSTO - 32001|TOTAL: 56,28| | Q133: NAO | R133: GERAL | S133: 32001 | T133: 19000 | U133: 31201005 | V133: =V132+2 -> 266 | W133: ='PLANO DE SAÚDE'!#REF! -> #REF!
A134: REAL | B134: =B133+2 -> 267 | C134: 1 | D134: FGL | E134: 209.04 | F134: GERAL | G134: 46265 | H134: 1 | I134: CR | K134: 106 | L134: PLANO MÊS 08/2026 | M134: 1 | N134: 31550109 | O134: |PAGTO DOC - |PLANO DE SAUDE - SEGURO UNIMED|C CUSTO - 32002|TOTAL: 209,04| | Q134: NAO | R134: GERAL | S134: 32002 | T134: 19000 | U134: 31201005 | V134: =V133+2 -> 268 | W134: ='PLANO DE SAÚDE'!C135 -> 13013
A135: REAL | B135: =B134+2 -> 269 | C135: 1 | D135: FGL | E135: 168.84 | F135: GERAL | G135: 46265 | H135: 1 | I135: CR | K135: 106 | L135: PLANO MÊS 08/2026 | M135: 1 | N135: 31550109 | O135: |PAGTO DOC - |PLANO DE SAUDE - SEGURO UNIMED|C CUSTO - 32003|TOTAL: 168,84| | Q135: NAO | R135: GERAL | S135: 32003 | T135: 19000 | U135: 31201005 | V135: =V134+2 -> 270 | W135: ='PLANO DE SAÚDE'!C136 -> 32001
A136: REAL | B136: =B135+2 -> 271 | C136: 1 | D136: FGL | E136: 112.56 | F136: GERAL | G136: 46265 | H136: 1 | I136: CR | K136: 106 | L136: PLANO MÊS 08/2026 | M136: 1 | N136: 31550109 | O136: |PAGTO DOC - |PLANO DE SAUDE - SEGURO UNIMED|C CUSTO - 32007|TOTAL: 112,56| | Q136: NAO | R136: GERAL | S136: 32007 | T136: 19000 | U136: 31201005 | V136: =V135+2 -> 272 | W136: ='PLANO DE SAÚDE'!C137 -> 32002
A137: REAL | B137: =B136+2 -> 273 | C137: 1 | D137: FGL | E137: 24.12 | F137: GERAL | G137: 46265 | H137: 1 | I137: CR | K137: 106 | L137: PLANO MÊS 08/2026 | M137: 1 | N137: 31550109 | O137: |PAGTO DOC - |PLANO DE SAUDE - SEGURO UNIMED|C CUSTO - 32100|TOTAL: 24,12| | Q137: NAO | R137: GERAL | S137: 32100 | T137: 19000 | U137: 31201005 | V137: =V136+2 -> 274 | W137: ='PLANO DE SAÚDE'!C138 -> 32003
A138: REAL | B138: =B137+2 -> 275 | C138: 1 | D138: FGL | E138: 64.32 | F138: GERAL | G138: 46265 | H138: 1 | I138: CR | K138: 106 | L138: PLANO MÊS 08/2026 | M138: 1 | N138: 31550109 | O138: |PAGTO DOC - |PLANO DE SAUDE - SEGURO UNIMED|C CUSTO - 34001|TOTAL: 64,32| | Q138: NAO | R138: GERAL | S138: 34001 | T138: 19000 | U138: 31201005 | V138: =V137+2 -> 276 | W138: ='PLANO DE SAÚDE'!C139 -> 32007
A139: REAL | B139: =B138+2 -> 277 | C139: 1 | D139: FGL | E139: 297.48 | F139: GERAL | G139: 46265 | H139: 1 | I139: CR | K139: 106 | L139: PLANO MÊS 08/2026 | M139: 1 | N139: 31550109 | O139: |PAGTO DOC - |PLANO DE SAUDE - SEGURO UNIMED|C CUSTO - 15056|TOTAL: 297,48| | Q139: NAO | R139: GERAL | S139: 15056 | T139: 19000 | U139: 31201005 | V139: =V138+2 -> 278 | W139: ='PLANO DE SAÚDE'!C140 -> 32100
A140: REAL | B140: =B139+2 -> 279 | C140: 1 | D140: FGL | E140: 176.88 | F140: GERAL | G140: 46265 | H140: 1 | I140: CR | K140: 106 | L140: PLANO MÊS 08/2026 | M140: 1 | N140: 31550109 | O140: |PAGTO DOC - |PLANO DE SAUDE - SEGURO UNIMED|C CUSTO - 15058|TOTAL: 176,88| | Q140: NAO | R140: GERAL | S140: 15058 | T140: 19000 | U140: 31201005 | V140: =V139+2 -> 280 | W140: ='PLANO DE SAÚDE'!C141 -> 34001
A141: REAL | B141: =B140+2 -> 281 | C141: 1 | D141: FGL | E141: 152.76 | F141: GERAL | G141: 46265 | H141: 1 | I141: CR | K141: 104 | L141: PLANO MÊS 08/2026 | M141: 1 | N141: 31550109 | O141: |PAGTO DOC - |PLANO DE SAUDE - SEGURO UNIMED|C CUSTO - 15059|TOTAL: 152,76| | Q141: NAO | R141: GERAL | S141: 15059 | T141: 19000 | U141: 31201005 | V141: =V140+2 -> 282 | W141: ='PLANO DE SAÚDE'!#REF! -> #REF!
A142: REAL | B142: =B141+2 -> 283 | C142: 1 | D142: FGL | E142: 48.24 | F142: GERAL | G142: 46265 | H142: 1 | I142: CR | K142: 104 | L142: PLANO MÊS 08/2026 | M142: 1 | N142: 31550109 | O142: |PAGTO DOC - |PLANO DE SAUDE - SEGURO UNIMED|C CUSTO - 22002|TOTAL: 48,24| | Q142: NAO | R142: GERAL | S142: 22002 | T142: 19000 | U142: 31201005 | V142: =V141+2 -> 284 | W142: ='PLANO DE SAÚDE'!C142 -> 15056
A143: REAL | B143: =B142+2 -> 285 | C143: 1 | D143: FGL | E143: 213.6 | F143: GERAL | G143: 46265 | H143: 1 | I143: CR | K143: 101 | L143: PLANO MÊS 08/2026 | M143: 1 | N143: 31550109 | O143: |PAGTO DOC - |PLANO DE SAUDE - SORRISO ODONTO|C CUSTO - 13011|TOTAL: 213,6| | Q143: NAO | R143: GERAL | S143: 13011 | T143: 19000 | U143: 31201005 | V143: =V142+2 -> 286 | W143: ='PLANO DE SAÚDE'!C143 -> 15058
A144: REAL | B144: =B143+2 -> 287 | C144: 1 | D144: FGL | E144: 48 | F144: GERAL | G144: 46265 | H144: 1 | I144: CR | K144: 101 | L144: PLANO MÊS 08/2026 | M144: 1 | N144: 31550109 | O144: |PAGTO DOC - |PLANO DE SAUDE - SORRISO ODONTO|C CUSTO - 13013|TOTAL: 48| | Q144: NAO | R144: GERAL | S144: 13013 | T144: 19000 | U144: 31201005 | V144: =V143+2 -> 288 | W144: ='PLANO DE SAÚDE'!C144 -> 15059
A145: REAL | B145: =B144+2 -> 289 | C145: 1 | D145: FGL | E145: 105 | F145: GERAL | G145: 46265 | H145: 1 | I145: CR | K145: 101 | L145: PLANO MÊS 08/2026 | M145: 1 | N145: 31550109 | O145: |PAGTO DOC - |PLANO DE SAUDE - SORRISO ODONTO|C CUSTO - 13017|TOTAL: 105| | Q145: NAO | R145: GERAL | S145: 13017 | T145: 19000 | U145: 31201005 | V145: =V144+2 -> 290 | W145: ='PLANO DE SAÚDE'!C145 -> 22002
A146: REAL | B146: =B145+2 -> 291 | C146: 1 | D146: FGL | E146: 85 | F146: GERAL | G146: 46265 | H146: 1 | I146: CR | K146: 101 | L146: PLANO MÊS 08/2026 | M146: 1 | N146: 31550109 | O146: |PAGTO DOC - |PLANO DE SAUDE - SORRISO ODONTO|C CUSTO - 13019|TOTAL: 85| | Q146: NAO | R146: GERAL | S146: 13019 | T146: 19000 | U146: 31201005 | V146: =V145+2 -> 292 | W146: ='PLANO DE SAÚDE'!#REF! -> #REF!
A147: REAL | B147: =B146+2 -> 293 | C147: 1 | D147: FGL | E147: 224.15 | F147: GERAL | G147: 46265 | H147: 1 | I147: CR | K147: 101 | L147: PLANO MÊS 08/2026 | M147: 1 | N147: 31550109 | O147: |PAGTO DOC - |PLANO DE SAUDE - SORRISO ODONTO|C CUSTO - 13021|TOTAL: 224,15| | Q147: NAO | R147: GERAL | S147: 13021 | T147: 19000 | U147: 31201005 | V147: =V146+2 -> 294 | W147: ='PLANO DE SAÚDE'!#REF! -> #REF!
A148: REAL | B148: =B147+2 -> 295 | C148: 1 | D148: FGL | E148: 222 | F148: GERAL | G148: 46265 | H148: 1 | I148: CR | K148: 101 | L148: PLANO MÊS 08/2026 | M148: 1 | N148: 31550109 | O148: |PAGTO DOC - |PLANO DE SAUDE - SORRISO ODONTO|C CUSTO - 21012|TOTAL: 222| | Q148: NAO | R148: GERAL | S148: 21012 | T148: 19000 | U148: 31201005 | V148: =V147+2 -> 296 | W148: ='PLANO DE SAÚDE'!C146 -> 13011
A149: REAL | B149: =B148+2 -> 297 | C149: 1 | D149: FGL | E149: 175.45 | F149: GERAL | G149: 46265 | H149: 1 | I149: CR | K149: 101 | L149: PLANO MÊS 08/2026 | M149: 1 | N149: 31550109 | O149: |PAGTO DOC - |PLANO DE SAUDE - SORRISO ODONTO|C CUSTO - 31040|TOTAL: 175,45| | Q149: NAO | R149: GERAL | S149: 31040 | T149: 19000 | U149: 31201005 | V149: =V148+2 -> 298 | W149: ='PLANO DE SAÚDE'!C147 -> 13013
A150: REAL | B150: =B149+2 -> 299 | C150: 1 | D150: FGL | E150: 1013.6 | F150: GERAL | G150: 46265 | H150: 1 | I150: CR | K150: 101 | L150: PLANO MÊS 08/2026 | M150: 1 | N150: 31550109 | O150: |PAGTO DOC - |PLANO DE SAUDE - SORRISO ODONTO|C CUSTO - 31060|TOTAL: 1013,6| | Q150: NAO | R150: GERAL | S150: 31060 | T150: 19000 | U150: 31201005 | V150: =V149+2 -> 300 | W150: ='PLANO DE SAÚDE'!C148 -> 13017
A151: REAL | B151: =B150+2 -> 301 | C151: 1 | D151: FGL | E151: 132 | F151: GERAL | G151: 46265 | H151: 1 | I151: CR | K151: 101 | L151: PLANO MÊS 08/2026 | M151: 1 | N151: 31550109 | O151: |PAGTO DOC - |PLANO DE SAUDE - SORRISO ODONTO|C CUSTO - 31070|TOTAL: 132| | Q151: NAO | R151: GERAL | S151: 31070 | T151: 19000 | U151: 31201005 | V151: =V150+2 -> 302 | W151: ='PLANO DE SAÚDE'!C149 -> 13019
A152: REAL | B152: =B151+2 -> 303 | C152: 1 | D152: FGL | E152: 968.9 | F152: GERAL | G152: 46265 | H152: 1 | I152: CR | K152: 101 | L152: PLANO MÊS 08/2026 | M152: 1 | N152: 31550109 | O152: |PAGTO DOC - |PLANO DE SAUDE - SORRISO ODONTO|C CUSTO - 31090|TOTAL: 968,9| | Q152: NAO | R152: GERAL | S152: 31090 | T152: 19000 | U152: 31201005 | V152: =V151+2 -> 304 | W152: ='PLANO DE SAÚDE'!C150 -> 13021
A153: REAL | B153: =B152+2 -> 305 | C153: 1 | D153: FGL | E153: 35 | F153: GERAL | G153: 46265 | H153: 1 | I153: CR | K153: 101 | L153: PLANO MÊS 08/2026 | M153: 1 | N153: 31550109 | O153: |PAGTO DOC - |PLANO DE SAUDE - SORRISO ODONTO|C CUSTO - 31100|TOTAL: 35| | Q153: NAO | R153: GERAL | S153: 31100 | T153: 19000 | U153: 31201005 | V153: =V152+2 -> 306 | W153: ='PLANO DE SAÚDE'!C151 -> 21012
...

Sheet SAUDE
A1: REAL 1 1FGL 7.159,75GERAL 31/01/2023 1CRFISCAL 101PLANO MÊS 01/2023 1 31550109 | B1: |PAGTO DOC - SEGURO SAÚDE|PLANO DE SAUDE - SEGURO SAÚDE|C CUSTO - 14113|TOTAL: 7159,75| NAOGERAL 141131900031201005 2
A2: REAL 3 1FGL 4.868,63GERAL 31/01/2023 1CRFISCAL 101PLANO MÊS 01/2023 1 31550109 | B2: |PAGTO DOC - SEGURO SAÚDE|PLANO DE SAUDE - SEGURO SAÚDE|C CUSTO - 14119|TOTAL: 4868,63| NAOGERAL 141191900031201005 4
A3: REAL 5 1FGL 4.295,85GERAL 31/01/2023 1CRFISCAL 101PLANO MÊS 01/2023 1 31550109 | B3: |PAGTO DOC - SEGURO SAÚDE|PLANO DE SAUDE - SEGURO SAÚDE|C CUSTO - 14111|TOTAL: 4295,85| NAOGERAL 141111900031201005 6
A4: REAL 7 1FGL 2.291,12GERAL 31/01/2023 1CRFISCAL 101PLANO MÊS 01/2023 1 31550109 | B4: |PAGTO DOC - SEGURO SAÚDE|PLANO DE SAUDE - SEGURO SAÚDE|C CUSTO - 14056|TOTAL: 2291,12| NAOGERAL 140561900031201005 8
A5: REAL 9 1FGL 5.155,02GERAL 31/01/2023 1CRFISCAL 101PLANO MÊS 01/2023 1 31550109 | B5: |PAGTO DOC - SEGURO SAÚDE|PLANO DE SAUDE - SEGURO SAÚDE|C CUSTO - 14116|TOTAL: 5155,02| NAOGERAL 141161900031201005 10
A6: REAL 11 1FGL 23.140,13GERAL 31/01/2023 1CRFISCAL 101PLANO MÊS 01/2023 1 31550109 | B6: |PAGTO DOC - SEGURO SAÚDE|PLANO DE SAUDE - SEGURO SAÚDE|C CUSTO - 11011|TOTAL: 23140,13| NAOGERAL 110111900031201005 12
A7: REAL 13 1FGL 859,17GERAL 31/01/2023 1CRFISCAL 101PLANO MÊS 01/2023 1 31550109 | B7: |PAGTO DOC - SEGURO SAÚDE|PLANO DE SAUDE - SEGURO SAÚDE|C CUSTO - 14112|TOTAL: 859,17| NAOGERAL 141121900031201005 14
A8: REAL 15 1FGL 7.230,19GERAL 31/01/2023 1CRFISCAL 101PLANO MÊS 01/2023 1 31550109 | B8: |PAGTO DOC - SEGURO SAÚDE|PLANO DE SAUDE - SEGURO SAÚDE|C CUSTO - 14051|TOTAL: 7230,19| NAOGERAL 140511900031201005 16
A9: REAL 17 1FGL 3.150,29GERAL 31/01/2023 1CRFISCAL 101PLANO MÊS 01/2023 1 31550109 | B9: |PAGTO DOC - SEGURO SAÚDE|PLANO DE SAUDE - SEGURO SAÚDE|C CUSTO - 14120|TOTAL: 3150,29| NAOGERAL 141201900031201005 18
A10: REAL 19 1FGL 1.145,56GERAL 31/01/2023 1CRFISCAL 101PLANO MÊS 01/2023 1 31550109 | B10: |PAGTO DOC - SEGURO SAÚDE|PLANO DE SAUDE - SEGURO SAÚDE|C CUSTO - 14059|TOTAL: 1145,56| NAOGERAL 140591900031201005 20
A11: REAL 21 1FGL 6.943,80GERAL 31/01/2023 1CRFISCAL 101PLANO MÊS 01/2023 1 31550109 | B11: |PAGTO DOC - SEGURO SAÚDE|PLANO DE SAUDE - SEGURO SAÚDE|C CUSTO - 11012|TOTAL: 6943,8| NAOGERAL 110121900031201005 22
A12: REAL 23 1FGL 859,17GERAL 31/01/2023 1CRFISCAL 101PLANO MÊS 01/2023 1 31550109 | B12: |PAGTO DOC - SEGURO SAÚDE|PLANO DE SAUDE - SEGURO SAÚDE|C CUSTO - 14060|TOTAL: 859,17| NAOGERAL 140601900031201005 24
... A131: REAL 261 1FGL 7,00GERAL 31/01/2023 1CRFISCAL 101PLANO MÊS 01/2023 1 31550109 | B131: |PAGTO DOC - SEGURO DE VIDA EM GRUPO|PLANO DE SAUDE - SEGURO DE VIDA EM GRUPO|C CUSTO - 14110|TOTAL: 7| NAOGERAL 141101900031201003 262

Sheet RAZAO
A1: Data | B1: Plano Contas | C1: Conta Contábil | D1: Transação | E1: Referência | F1: Fornecedor | G1: Nome Abreviado | H1: Estab. | I1: Plano de Centro de Custo | J1: CCusto | K1: Esp | L1: Série | M1: Título | N1: Parcela | O1: Portador | P1: Número Cheque | Q1: Valor DB | R1: Valor CR | S1: Contra Partida | T1: Histor
Q7: =SUM(Q2:Q6) -> 0
G11: APB + CE0403 | H11: PLANILHA
F12: 101 | G12: =SUMIFS($Q$2:$Q$9,$H$2:$H$9,F12)-SUMIFS($R$2:$R$9,$H$2:$H$9,F12)+SUMIFS($P$21:$P$38,$D$21:$D$38,F12) -> 264756.28 | H12: =SUMIFS(Consolidado!F:F,Consolidado!A:A,RAZAO!F12) -> 264756.28 | I12: =G12-H12 -> 0
F13: 104 | G13: =SUMIFS($Q$2:$Q$9,$H$2:$H$9,F13)-SUMIFS($R$2:$R$9,$H$2:$H$9,F13)+SUMIFS($P$21:$P$38,$D$21:$D$38,F13) -> 2513.52 | H13: =SUMIFS(Consolidado!F:F,Consolidado!A:A,RAZAO!F13) -> 2513.52 | I13: =G13-H13 -> 0
F14: 106 | G14: =SUMIFS($Q$2:$Q$9,$H$2:$H$9,F14)-SUMIFS($R$2:$R$9,$H$2:$H$9,F14)+SUMIFS($P$21:$P$38,$D$21:$D$38,F14) -> 24024.3 | H14: =SUMIFS(Consolidado!F:F,Consolidado!A:A,RAZAO!F14) -> 24024.3 | I14: =G14-H14 -> 0
A20: Conta | B20: Centro Custo | C20: UNeg | D20: Estab | E20: Data Trans | F20: Depósito | G20: Espécie | H20: Série | I20: Documento | J20: Emitente | K20: Num Ordem | L20: Item | M20: UM | N20: Qtde | O20: Total | P20: Débito | Q20: Crédito | R20: Narrativa: | S20: Descrição Item | T20: Nome Abrev
A21: 3.1.55.01.09 | C21: 1 | D21: 101 | E21: 46245 | F21: DIR | G21: NFE | H21: 1 | I21: 0012692 | J21: 50337 | K21: 0.00 | L21: DD-014 | M21: UN | N21: 1 | P21: 5501.2 | Q21: 0 | R21: NOSSO PAGAMENTO REFERENTE AO PLANO DE ASSISTENCIA ODONTOLOGICA DOS COLABORADORES DE ITUVERAVA - ESTABELECIMENTO 101 | DOCUMENTO ENVIADO POR E-MAIL PELA AMANDA (RH) NO DIA 05/08/2026. | S21: GASTOS COM CONVENIO MEDICO | T21: UNIDENT
A22: 3.1.55.01.09 | C22: 1 | D22: 101 | E22: 46246 | F22: DIR | G22: NFE | H22: BOL | I22: 6313020 | J22: 53525 | K22: 0.00 | L22: DD-404 | M22: UN | N22: 1 | P22: 3099.15 | Q22: 0 | R22: NOSSO PAGAMENTO REFERENTE AO PLANO DE SAÚDE UNIMED ODONTO DOS COLABORADORES DA MATRIZ SANTA MARIA | DOCUMENTO ENVIADO POR E-MAIL POR AMANDA TEIXEIRA (RH) NO DIA 11/08/2026 | S22: GASTOS COM CONVENIO MEDICO | T22: UNIMED ODONT
A23: 3.1.55.01.09 | C23: 1 | D23: 101 | E23: 46247 | F23: DIR | G23: NFE | H23: FAT | I23: 0000499 | J23: 50426 | K23: 0.00 | L23: DD-404 | M23: UN | N23: 1 | P23: 76224.17 | Q23: 0 | R23: PAGAMENTO MENSAL DE CONVÊNIO MÉDICO COLETIVO EMPRESARIAL DA COMPETÊNCIA 08/2026 | CONFORME DEMONSTRATIVO DE FATURA N° 2600005172.01/000499 MODALIDADE/CONTRATO N° 000041 | DOCUMENTO ENVIADO POR AMANDA TEIXEIRA VIA E-MAIL NO DIA 11/08/2026 | NÚMERO DE ORIGEM DESTE LANÇAMENTO: NUMERO DA FATURA ENVIADA. | S23: FATURA | CONVÊNIO MÉDICO | T23: UNIMED ITUV
A24: 3.1.55.01.09 | C24: 1 | D24: 101 | E24: 46247 | F24: DIR | G24: NFE | H24: FAT | I24: 0000500 | J24: 50426 | K24: 0.00 | L24: DD-404 | M24: UN | N24: 1 | P24: 24426.27 | Q24: 0 | R24: PAGAMENTO MENSAL DE CONVÊNIO MÉDICO COLETIVO EMPRESARIAL DA COMPETÊNCIA 08/2026 | CONFORME DEMONSTRATIVO DE FATURA N° 2600005173.01/000500 MODALIDADE/CONTRATO N° 000048 | DOCUMENTO ENVIADO POR AMANDA TEIXEIRA VIA E-MAIL NO DIA 11/08/2026 | NÚMERO DE ORIGEM DESTE LANÇAMENTO: NUMERO DA FATURA ENVIADA. | S24: FATURA | CONVÊNIO MÉDICO | T24: UNIMED ITUV
A25: 3.1.55.01.09 | C25: 1 | D25: 101 | E25: 46247 | F25: DIR | G25: NFE | H25: FAT | I25: 0000501 | J25: 50426 | K25: 0.00 | L25: DD-404 | M25: UN | N25: 1 | P25: 5393.26 | Q25: 0 | R25: PAGAMENTO MENSAL DE CONVÊNIO MÉDICO COLETIVO EMPRESARIAL DA COMPETÊNCIA 08/2026 | CONFORME DEMONSTRATIVO DE FATURA N° 2600005174.01/000501 MODALIDADE/CONTRATO N° 000242 | DOCUMENTO ENVIADO POR AMANDA TEIXEIRA VIA E-MAIL NO DIA 11/08/2026 | NÚMERO DE ORIGEM DESTE LANÇAMENTO: NUMERO DA FATURA ENVIADA. | S25: FATURA | CONVÊNIO MÉDICO | T25: UNIMED ITUV
A26: 3.1.55.01.09 | C26: 1 | D26: 101 | E26: 46247 | F26: DIR | G26: NFE | H26: FAT | I26: 0000502 | J26: 50426 | K26: 0.00 | L26: DD-404 | M26: UN | N26: 1 | P26: 4868.28 | Q26: 0 | R26: PAGAMENTO MENSAL DE CONVÊNIO MÉDICO COLETIVO EMPRESARIAL DA COMPETÊNCIA 08/2026 | CONFORME DEMONSTRATIVO DE FATURA N° 2600005175.01/000502 MODALIDADE/CONTRATO N° 000271 | DOCUMENTO ENVIADO POR AMANDA TEIXEIRA VIA E-MAIL NO DIA 11/08/2026 | NÚMERO DE ORIGEM DESTE LANÇAMENTO: NUMERO DA FATURA ENVIADA. | S26: FATURA | CONVÊNIO MÉDICO | T26: UNIMED ITUV
A27: 3.1.55.01.09 | C27: 1 | D27: 101 | E27: 46247 | F27: DIR | G27: NFE | H27: FAT | I27: 5160060 | J27: 52915 | K27: 0.00 | L27: DD-404 | M27: UN | N27: 1 | P27: 15015.12 | Q27: 0 | R27: NOSSO PAGAMENTO MENSAL REFERENTE AO SEGURO UNIMED CORPORATIVO SENIOR APTO (FR - TREINAMENTO PROFISSIONAL LTDA) | CONFORME APÓLICE N° 8771499 AGENTE: 994, PERÍODO DE VIGÊNCIA: 01/08/2026 A 31/08/2026 | DOCUMENTO ENVIADO POR AMANDA TEIXEIRA VIA E-MAIL NO DIA 11/08/2026 | NUMERO DE ORIGEM DESTE LANÇAMENTO: NÚMERO DA FATURA RECEBIDA. | S27: FATURA | CONVÊNIO MÉDICO | T27: SEGUROS UNIM
A28: 3.1.55.01.09 | C28: 1 | D28: 101 | E28: 46247 | F28: DIR | G28: NFE | H28: FAT | I28: 5160061 | J28: 52915 | K28: 0.00 | L28: DD-404 | M28: UN | N28: 1 | P28: 12512.6 | Q28: 0 | R28: NOSSO PAGAMENTO MENSAL REFERENTE AO SEGURO UNIMED CORPORATIVO SENIOR APTO (UTILIHOUSE REPRESENTAÇAO DE UTILIDADES DOMESTICAS LTDA) | CONFORME APÓLICE N° 8771499 AGENTE: 994, PERÍODO DE VIGÊNCIA: 01/08/2026 A 31/08/2026 | DOCUMENTO ENVIADO POR AMANDA TEIXEIRA VIA E-MAIL NO DIA 11/08/2026 | NUMERO DE ORIGEM DESTE LANÇAMENTO: NÚMERO DA FATURA RECEBIDA. | S28: FATURA | CONVÊNIO MÉDICO | T28: SEGUROS UNIM
A29: 3.1.55.01.09 | C29: 1 | D29: 101 | E29: 46247 | F29: DIR | G29: NFE | H29: FAT | I29: 5160062 | J29: 52915 | K29: 0.00 | L29: DD-404 | M29: UN | N29: 1 | P29: 412.85 | Q29: 0 | R29: NOSSO PAGAMENTO MENSAL REFERENTE AO SEGURO UNIMED CORPORATIVO COMPACTO ENF (CARLOS ROBERTO REAL ORSATTI) | CONFORME APÓLICE N° 8771499 AGENTE: 994, PERÍODO DE VIGÊNCIA: 01/08/2026 A 31/08/2026 | DOCUMENTO ENVIADO POR AMANDA TEIXEIRA VIA E-MAIL NO DIA 11/08/2026 | NUMERO DE ORIGEM DESTE LANÇAMENTO: NÚMERO DA FATURA RECEBIDA. | S29: FATURA | CONVÊNIO MÉDICO | T29: SEGUROS UNIM
A30: 3.1.55.01.09 | C30: 1 | D30: 101 | E30: 46247 | F30: DIR | G30: NFE | H30: FAT | I30: 5160063 | J30: 52915 | K30: 0.00 | L30: DD-404 | M30: UN | N30: 1 | P30: 87028.96 | Q30: 0 | R30: NOSSO PAGAMENTO MENSAL REFERENTE AO SEGURO UNIMED CORPORATIVO COMPACTO ENF E CORPORATIVO SENIOR APTO (IND E COM SANTA MARIA LTDA) | CONFORME APÓLICE N° 8771499 AGENTE: 994, PERÍODO DE VIGÊNCIA: 01/08/2026 A 31/08/2026 | DOCUMENTO ENVIADO POR AMANDA TEIXEIRA VIA E-MAIL NO DIA 11/08/2026 | NUMERO DE ORIGEM DESTE LANÇAMENTO: NÚMERO DA FATURA RECEBIDA. | S30: FATURA | CONVÊNIO MÉDICO | T30: SEGUROS UNIM
A31: 3.1.55.01.09 | C31: 1 | D31: 101 | E31: 46247 | F31: DIR | G31: NFE | H31: FAT | I31: 5160064 | J31: 52915 | K31: 0.00 | L31: DD-404 | M31: UN | N31: 1 | P31: 25025.2 | Q31: 0 | R31: NOSSO PAGAMENTO MENSAL REFERENTE AO SEGURO UNIMED CORPORATIVO SENIOR APTO (BRANCO E ORSATTI - TREINAMENTO PROFISSIONAL LTDA) | CONFORME APÓLICE N° 8771499 AGENTE: 994, PERÍODO DE VIGÊNCIA: 01/08/2026 A 31/08/2026 | DOCUMENTO ENVIADO POR AMANDA TEIXEIRA VIA E-MAIL NO DIA 11/08/2026 | NUMERO DE ORIGEM DESTE LANÇAMENTO: NÚMERO DA FATURA RECEBIDA. | S31: FATURA | CONVÊNIO MÉDICO | T31: SEGUROS UNIM
A32: 3.1.55.01.09 | C32: 1 | D32: 101 | E32: 46254 | F32: DIR | G32: NFE | H32: 1 | I32: 1422187 | J32: 455354 | K32: 0.00 | L32: DD-014 | M32: UN | N32: 1 | P32: 5249.22 | Q32: 0 | R32: NOSSO PAGAMENTO REFERENTE AO SEGURO DE VIDA DOS COLABORADORES DA MATRIZ SANTA MARIA | COMPETÊNCIA 08/2026 | DOCUMENTO ENVIADO POR LINDOMAR GONÇALVES (RH) EM 17/08/2026 VIA E-MAIL | NÚMERO DE ORIGEM DESTE LANÇAMENTO: NÚMERO DO DOCUMENTO PRESENTE NO BOLETO (2601422187). | S32: FATURA | CONVÊNIO MÉDICO | T32: UNIMED SEG.
... A38: 3.1.55.01.09 | C38: 1 | D38: 106 | E38: 46247 | F38: DIR | G38: NFE | H38: 1 | I38: 1411484 | J38: 455354 | K38: 0.00 | L38: DD-014 | M38: UN | N38: 1 | P38: 643.2 | Q38: 0 | R38: NOSSO PAGAMENTO REFERENTE AO SEGURO DE VIDA DOS COLABORADORES DA FILIAL 106 SANTA MARIA | COMPETÊNCIA 08/2026 | DOCUMENTO ENVIADO POR LINDOMAR GONÇALVES (RH) EM 05/08/2026 VIA E-MAIL | NÚMERO DE ORIGEM DESTE LANÇAMENTO: NÚMERO DO DOCUMENTO PRESENTE NO BOLETO (2601411484). | S38: FATURA | CONVÊNIO MÉDICO | T38: UNIMED SEG.

Sheet Plan2

Sheet Plan4
